Workbook

Sheet Racional
A1: Referencia colores solapas
A2: Solapas financieras
A3: Soalapas auxiliares para dashboard
A4: Solapas económicas
A5: Tablas Dinámicas
A6: Mark Up
A7: Información extra que alimenta fórmulas
A11: Fecha del mes aprox | B11: Proceso General | C11: Tarea | D11: Repsonsables | E11: Solapa a completar/Usar | F11: TD o Solapa que se actualiza automáticamente
A12: Entre el 25/26 de cada mes | B12: Cierre de mes equipo | C12: Se le pide al equipo que cargue horas en Asana tanto del mes que hayan quedado pendientes como las estimadas de los días laborables que quedan. | D12: Vicky Puri / Vicky Acha | E12: N/A | F12: N/A
A13: Entre el 25/26 de cada mes | B13: Cierre de mes equipo | C13: Se crean los proyectos nuevos en Abejita. | D13: Vicky Puri / Vicky Acha | E13: N/A | F13: N/A
A14: Entre el 27/28 de cada mes | B14: Cierre de mes equipo | C14: Completar el cierre de horas mensual en base a las horas cerradas en Asana. Se completa la solapa con la información: Detalle COL A (nombre de la persona. Si no aparace se debe deseocultar la solapa Listas y sumar el nombre de la persona) Subtipo de Costo COL B (automatizada, si no aparece info se deba deseocultar la solapa Clasificaciones y sumar la variable que no tiene información) Mes COL C y Año COL D Tipo de costo COL E (Directo si está asociado a cliente dierto indirecto si es Epical general o Demo) Nro Proyecto COL G (ver fila 16) Tipo de proyecto COL H (Fee, One Shot, Epical para general y Demo si es cliente Epical pero refiere a una demo) Proyecto COL I (si un proyecto está en varios meses siempre mantener el mismo nombre. Si es nuevo se pone un referenica general de lo que es) Cliente COL J (en caso que sea Epical se selecciona Epical) Cantidad de horas Objetivo COL K (se saca de la solapa Horas Asignadas) Cantidad de horas reales Asana COL L (se carga específicamente lo que aparece en Asana indepedientemente si es más o menos de lo que debe trabajar la persona. Por ejemplo si una persona debería completar 160 horas pero completa 150 se cargan las 150) Cantidad de horas para facutración COL M (se carga lo de Asana pero si es necesario se redondea con Epical para arriba o para abajo. Sobre esta columna se calcula el monto a facurar) | D14: Vicky Puri / Vicky Acha | E14: Costos directos e indirectos | F14: TD Costos Directos para CIERRE TD Costos para seguimiento MARKUP
A15: Entre el 27/28 de cada mes | B15: Cierre de mes equipo | C15: Se completan los archivos de honorarios. 1- En caso de ser variables y que cobren una parte en USD se completa en la solapa Hoja 1 la diferencia de horas vs lo que se hizo en el cierre parcial. 2- En caso de ser variables y que cobren todo en ARS se completa en la solapa Hoja 1 el total de horas a facturar. 3- En todos los casos se completa la solapa Control Abejita con la apertura que deben usar para cargar la información en la misma. Para esto, se filtra por persona la TD CIERRE POR CUENTA Y PERSONA y se va copiando y pegando la distribución en cada archivo de honorarios. | D15: Vicky Puri / Vicky Acha | E15: TD Costos Directos para CIERRE Archivos de honorarios de cada persona | F15: N/A
A16: A fin de mes, antes que termine | B16: Cierre de mes equipo | C16: Hacer la carga de información en Abejita para que el equipo pueda cargar las horas. | D16: Michelle | E16: N/A | F16: N/A
A17: Entre el 30/31 de cada mes | B17: Cierre de mes equipo | C17: Una vez que estan cargados los Nros de proyectos en Abejita, se pasan a la solapa Costos Directos e Indirectos en COL G | D17: Vicky Puri / Vicky Acha | E17: Costos directos e indirectos | F17: TD Costos Directos para CIERRE TD Costos para seguimiento MARKUP
A18: Todos los lunes/martes de cada semana | B18: Semanal: Carga Activo | C18: CLIENTES A COBRAR Se mantiende actualizado lo facturado completando Fecha Facturación, Nro de Factura/Comprobante, Razón Social/Cliente, Detalle, Fecha de vencimiento, Moneda original ARS, Moneda original USD. Las columnas con letra en ROJO están automatizadas. Las columnas Cobrado/No Cobrado AL CIERRE y Fecha de pago/Nota de credito se van actualizando en la medida que se pague dentro del mes la factura emitida. Es decir si estamos en agosto y se cobró en agosto, se pone SI en Cobrado/No Cobrado AL CIERRE y se completa la Fecha de Pago/Nota de crédito. | D18: Michelle | E18: Activo | F18: Resumen ejecutivo
A19: Todos los lunes/martes de cada semana | B19: Semanal: Carga Pasivo | C19: Se mantiene actualizado semanalmente los gastos que ingresan. Las columnas a completar son: Detalle, Mes, Año, Fecha de Emisión, Concepto/Detalle, Descripción/Factura, Fecha de vencimiento, Moneda original ARS, Moneda original USD. Las columnas con letrra en ROJO están automatizadas. Las columnas Pagado/No Pagado AL CIERRE y Fecha de pago se van actualizando en la medida que se pague dentro del mes la factura emitida. Es decir si estamos en agosto y se cobró en agosto, se pone SI en Pagado/No Pagado AL CIERRE y se completa la Fecha de Pago. | D19: Michelle | E19: Pasivo | F19: Resumen ejecutivo
A20: Todos los lunes/martes de cada semana | B20: Semanal: Carga Cashflow | C20: Se mantiene actualizado semanalmente los ingresos y egresos de las cuentas USA, ARG y Caja si hubiera. Las columnas con letra en ROJO están automatizadas. En caso que se cargue monton en ARS (COL I), la cotización se trae automaticamente pero es posible que el cálculo en USD (COL K) haya que calcularlos dividiendo COL I / COL J. | D20: Michelle | E20: Cashflow | F20: Resumen ejecutivo
A21: 30/31 de cada mes | B21: Cierre de mes financiero: USD | C21: Se carga el tipo de cambio BLUE del día que cierra el mes. En la solapa Info Tipo de Cambio y REM, a partir de celda A23. | D21: Michelle / Vicky Puri / Vicky Acha | E21: Info Tipo de Cambio y REM = a partir de celda A23. | F21: Todas las solapas Verdes y Naranjas, en consecuencia todas las solapas Rosas, Azules y Amarillas
A22: Entre el 1 y el 10 de cada mes | B22: Cierre de mes financiero: Cashflow | C22: Verificar que todo esté ok para poder sacar los Saldos para el Activo. | D22: Michelle | E22: Cashflow | F22: Resumen Ejecutivo
A23: Entre el 1 y el 10 de cada mes | B23: Cierre de mes financiero: Activo | C23: a) Revisión que todo esté bien cargado. La columna Cobrado/No Cobrado AL CIERRE (COL F) se actualiza para el cierre: 1- Verificar que los valores si/no estén actualizados al momento de cierre en el mes en curso. ¿Qué se cobro y qué no?. Si es SI se actualiza la fecha de cobro. 2- Verificar si hay deudas en el pasado con NO que fueron pagadas en el mes que se está cerrando. Si es SI NO SE MODIFICA LA COLUMNA COBRADO/NO COBRADO AL CIERRE (COL F), queda en NO siempre y se carga solo la fecha de cobro Fecha de pago/Nota de credito (COL G). Esto es para no se rompan los resultados del pasado. A modo informativo: todo lo que dice NO en el pasado y NO tiene fecha de cobro o tiene fecha posterior al cierre de cada mes, se contempla como parte de Clientes a Cobrar en el resumen ejecutivo. b) ACTIVO LIQUIDO SALDOS Se sacan de la solapa Cashflow, con el último dato disponible a la fecha de cierre en las columnas -SALDO SANTANDER (COL L) se carga en pesos en Activo y el Concepto/Banco es Santander-Galicia-Nación -SALDO BOA (COL M) se carga en usd en Activo y el Concepto/Banco es Bank of America. -SALDO CAJA (COL N), si hubiera se carga en la monea correspondiente en Activo y el Concepto/Banco es Caja. c) MEDIANO PLAZO CRYPTO Lo comparte Gastón y se carga como Otras Inversiones en COL A. d) ACTIVO LIQUIDO TRANSFERWISE Se carga como Transferwise en COL A | D23: Michelle a) b) d) Gastón pasa el dato de c) y lo carga Michelle | E23: Activo | F23: Resumen ejecutivo
A24: Entre el 1 y el 10 de cada mes | B24: Cierre de mes financiero: Pasivo | C24: Revisión que todo esté bien cargado. La columna Pagado/No Pagado AL CIERRE (COL E) se actualiza para el cierre: 1- Verificar que los valores si/no estén actualizados al momento de cierre en el mes en curso. ¿Qué se pagó y qué no?. Si es SI se actualiza la fecha de cobro. 2- Verificar si hay deudas en el pasado con NO que fueron pagadas en el mes que se está cerrando. Si es SI NO SE MODIFICA LA COLUMNA PAGADO/NO PAGADO AL CIERRE (COL E), queda en NO siempre y se carga solo la fecha de cobro nada más Fecha de pago (COL F). Esto es para no se rompan los resultados del pasado. A modo informativo: todo lo que dice NO en el pasado y NO tiene fecha de cobro o tiene fecha posterior al cierre de cada mes, se contempla como parte de Deugas a Pagar en el resumen ejecutivo. | E24: Pasivo | F24: Resumen Ejecutivo
A25: Ultima semana del mes | B25: Cierre de mes económico: Costos Estimados | C25: Se validan los costos estimados para actualizar en caso de ser necesario. Además se pasa lo que es el cierre de mes actual a Pasado en COL M, es decir si estamos cerrando Agosto, ese mes se pone como Pasado. Además se cargan los impuestos en ARS estimados (IVA e IIBB), que se sacan de la solapa TD Proyectos Confirmados y Estimados. Se toman solo los meses futuros. LINK A LA TD. | D25: Vicky Puri / Vicky Acha | E25: Costos estimados | F25: TD Costos Estimados para proyección Seguimiento Mark Up General los meses proyectados
A26: Ultima semana del mes | B26: Cierre de mes económico: Proyectos confirmados y Estimados | C26: Se validan los proyectos confirmados y estimados para actualizar en caso de ser necesario. Los proyectos se plasman sin IVA. Sin embargo cualquier actualización en los estimados en PESOS va a tener repercusión en la TD de impiestos mencionada en el punto anterior y debe actualizarse los costos estimados. | D26: Vicky Puri / Vicky Acha | E26: Proyectos confirmados y estimados | F26: TD Proyectos Confirmados y Estimados
A27: Primera semana del mes | B27: Cierre de mes económico: Costos Directos e Indirectos | C27: Traslado de costos pasivo: Una vez que Michelle confirma que el pasivo está actualziado, se trasadan los costos directos e indirectos del mes que se cierra a la solapa Costos Directos e Indirectos. | D27: Vicky Puri / Vicky Acha | E27: Costos directos e indirectos | F27: TD Costos para seguimiento MARKUP
A28: Primera semana del mes | B28: Cierre de mes económico: Seguimiento Mark Up General | C28: Esta solapa se divide en 3 partes señalizadas en Azul Marino: RESULDATOS - INCLUYEN TODOS LOS COSTOS y VENTAS (SIN IVA) 1- Costos directos e indirectos: se utiliza la tabla dinámica TD Costos para Seguimiento MarkUp para poder actualizar el dato del mes que se está cerrando. En esa TD se filtra el mes que se cierra y se copian y pegan todos los costos. También se puede hacer un BUSCARV para que traiga la información. Es sumamente importante chequear que el total que suma en en Seguimiento MarkUp coincida con el total que se suma en la TD. Para esto debajo de la tabla de costos hay una zona en rojo que permite copiar y pegar totales de la TD para hacer un control. LINK A LA TD UTILIZADA 2- Proyectos Confirmados y Estimados: se utiliza la TD Proyectos confirmados y estimados para poder actualizar el dato del mes que se está cerrando y las estimaciones. La carga de información en MarkUp General está automatizada, sin embargo se debe hacer el control totalizador en ROJO por si hay diferencias, se agregan nuevos clientes y hay que ajustar el BuscarV, o cualquier diferencia o ajuste que se haga. 3- Completando esta información se actualizan los resultados pero siempre es importante validar que estén ok y no haya moviemiento de celdas con los ajustes. ARR VENTAS: SE CONSIDERAN LAS VENTAS CONFIRMADAS 100%: se sacan de la solapa TD Proyectos confirmados y estimados. LINK A LA TD UTILIZADA COSTOS: SE CONSIDERAN COSTOS FIJOS, SIN LOS BONOS Y LOS PERFILES EXTRAS. SIN IMPUESTOS ARG USA. SIN INTERESES. Se sacan de la solapa TD Costos Estimados. LINK A LA TD UTILIZADA TABLA PROYECCIONES VENTAS USD Y ARS EN USD CON IVA PARA ESTADO DE SITUACIÓN 60 DÍAS Solo se ponen las ventas dado que los costos salen de la tabla de resultado. En este caso para el estado de situacion si se considera el IVA en las ventas en ARS por eso se arma una nueva tabla. Para esto se utiliza la solapa TD Proyectos confirmados y Estimados. LINK A LA TD UTILIZADA | D28: Vicky Puri / Vicky Acha | E28: Seguimiento MarkUp General | F28: N/A
A29: Primera semana del mes | B29: Cierre de mes económico: MarkUp Clientes | C29: Una vez que están cerradas la solapa Costos Directos e Indirectos, desde la solapa TD Costos Directos para CIERRE usando esta Tabla Dinámica se sacan los datos de equipo para poder estimar el MarkUp del mes de cada cliente tanto proyecto Fee como One shot on going. ¿Cómo usar? Todos los meses, una vez que se actualiza la información para le cierre se presiona en el lapiz (editar) y en filtros > Mes se elige el que se está cerrando y se elige cliente por cliente para ver las horas consumidas por cliente. Esa información se traslada luego a las solapas de MarkUp por cliente | D29: Vicky Puri / Vicky Acha | E29: Seguimiento MarkUp Cliente | F29: N/A
A30: Mitad de mes | B30: Actualización Valor Hora Real y Estimada | C30: A mitad de mes, se valida con Vicky Puricelli los ajustes pautados para poder aplicar el % real. | D30: Vicky Puri / Vicky Acha | E30: Valor Hora Real y Estimada | F30: Costos Directos e indirectos Costos Estimados TD Costos Directos para CIERRE TD Costos para seguimiento MARKUP TD Costos Estimados para proyección
A31: Principio de mes | B31: Actualización Info Tipo de Cambio y REM | C31: Una vez que el BCRA hace la publicación del informe REM se actualiza el tipo de cambio futuro, idealmente antes de enviar el cierre de mes financiero. Se realiza la carga a partir del mes siguiente al mes que se está cerrando. Es decir si se está cerrando agosto se carga las estimaciones para Septiembre, Octubre, Noviembre y Diciembre. | D31: Vicky Acha | E31: Info Tipo de Cambio y REM | F31: Todas las solapas Verdes y Naranjas, en consecuencia todas las solapas Rosas, Azules y Amarillas
A32: Principio de mes | B32: Actualización Pasivos [aux] | C32: A principio de mes, se debe agregar la formula actualizada a todos los subtipos de pasivos del mes cerrado anterior. Esto se hace copiando y pegando la formula del mes anterior, modificando todos los "FIN.MES" para que el mes sea el correcto (2025;9;1= septiembre), también hay que copiar y pegar dos lineas extra donde se tome el mes que sea esta cerrando (ej:+ SUMAR.SI.CONJUNTO(Pasivo!N:N;Pasivo!B:B;A163 ;Pasivo!E:E;"No Pagado";Pasivo!C:C; " MES QUE DESEA CERRAR Pasivo!F:F;"") +SUMAR.SI.CONJUNTO(Pasivo!N:N;Pasivo!B:B;A163 ;Pasivo!E:E;"No Pagado";Pasivo!C:C; " MES QUE DESEA CERRAR ";Pasivo!F:F; ">"&FIN.MES(FECHA(2025;MES QUE DESEA CERRAR;1);0)) Una vez que queda la formula terminada en el primer subtipo, se puede arrastrar formula | D32: Mati Gonzalez | E32: Pasivos [aux] | F32: N/A
A33: Principio de mes | B33: Actualización Activos [aux] | C33: Proceso similar al de Pasivos [aux], pero solo con "clientes a cobrar", el resto es un sumar si conjunto clasico | D33: Mati Gonzalez | E33: Activos [aux] | F33: N/A
A34: Principio de mes | B34: Rendimiento Cliente | C34: Hay quecopiar de todas las solapas de "Seguimiento markup" de clientes en especifico (no del general), la facturación y el costo de los clientes que tuvieron actividad el mes que se esta cerrando y pegarlo en rendimiento cliente | D34: Mati Gonzalez | E34: Rendimiento Cliente | F34: N/A
A35: Principio de mes | B35: Proyección [Total] | C35: Es para una cuestión estetica del dashboard. El último mes cerrado se repite dos veces (una como poryección y otra real) para unir una recta. Cuando se cierra un mes, se debe borrar la fila del mes anterior a ese queesta clasificado como proyeccion y copiar otra fila del mes que se esta cerrando como real. Las formulas de todas las columnas que se aplica ambas filas (tanto el de proyeccion como el real del mes repetido) tiene que ser arrastrada con la formula del real (de arriba para abajo) | D35: Mati Gonzalez | E35: Proyección [Total] | F35: N/A
A38: ENERO ajustar todo 2025 como valor y adaptar las nuevas tablas para 2026
C44: Responsables | D44: Periodicidad de carga | E44: Notas y comentarios
A45: Activo | C45: Lorena y Michelle general Tonga Otras Inversiones Mediano Plazo (cripto) | D45: Semanal con cierre completo al último día del mes. | E45: -Las columnas con fondo gris en el encabezado solo se completan si el Concepto/Banco es "Deuda clientes". -Las columnas con letra en rojo están automatizadas -Al cierre del mes Tonga completa Otras Inversiones Mediano Plazo (cripto) -Al cierre del mes Michelle completa los saldos disponibles / activos líquidos en Santander-Galicia-Nación, Bank Of America, Transferwise que salen del cashflow. Además completa los activos pasados que no fueron cobrados aún. -Mati en proceso de automatización de columnas: año, mes, tipo de activo y cliente -DETROIT se cargó retroactivamente en activo. Lorena no lo tenia presente.
A46: Cashflow
A47: Pasivo
A48: Impuestos
A49: Costos Directos e indirectos
A50: Costos estimados

Sheet Listas
A1: ACTIVO | B1: ACTIVO | C1: ACTIVO / Costos directos e indirectos / Costos Estimados / Protectos confirmados y estimados | D1: Pasivo / Costos directos e indirectos / Costos Estimados | E1: Pasivo / Costos directos e indirectos / Costos Estimados | F1: CASHFLOW | G1: Costos estimados
A2: Concepto/Banco | B2: Tipo de Activo | C2: Cliente | D2: Detalle | E2: Subtipo de costo | F2: Subtipo de ingreso/egreso | G2: Puesto | H2: Mes
A3: Caja | B3: Activo Liquido | C3: Coelsa | D3: Vicky Achabal | E3: Equipo | F3: Equipo | G3: PM | H3: 01 ene
A4: Custodia Socios | B4: Mediano Plazo | C4: Arcos Dorados | D4: Vicky Puricelli | E4: Board | F4: Board | G4: Board | H4: 02 feb
A5: Santander-Galicia-Nación | B5: Clientes a cobrar | C5: Animal Studio | D5: Tomi Criado | E5: Oxean | F5: Oxean | G5: Operation Lead | H5: 03 mar
A6: Santander Inversiones | C6: BID | D6: People | E6: Gastos Varios | F6: Gasto Varios | G6: Analista | H6: 04 abr
A7: Bank Of America | C7: Natura | D7: IIBB | E7: Suscripciones/Herramientas | F7: Suscripciones/Herramientas | G7: Data Tech | H7: 05 may
A8: Transferwise | C8: Betterfly | D8: IVA | E8: Impuestos USA | F8: Impuestos USA | G8: Diseño | H8: 06 jun
A9: Cheques en cartera | C9: Giampaoletti | D9: Tarjeta ARG | E9: Impuestos ARG | F9: Impuestos ARG | G9: Freelance | H9: 07 jul
A10: Deuda Clientes | C10: Google LLC | D10: Impuestos USA | E10: Estudio Contable | F10: Estudio Contable | G10: Marketing | H10: 08 ago
A11: Otras Inversiones | C11: Mastercard | D11: Brandwatch | E11: Otros Proveedores | F11: Otros Proveedores | H11: 09 sep
C12: Moreno Ocampo | D12: Youscan | E12: Administración Finanzas | F12: Administración Finanzas | H12: 10 oct
C13: Sentidos | D13: Otras Suscripciones | E13: Tarjeta | F13: Tarjeta | H13: 11 nov
C14: Play Digital S.A (Modo) | D14: Abogado | E14: People | F14: People | H14: 12 dic
C15: Warner | D15: Regalos | E15: Comisiones Bancarias | F15: Cliente
C16: Netflix | D16: Luan Digital | E16: Equipo - Bono | F16: Movimiento entre cuentas
C17: Vertical Media | D17: Tarjeta USA | E17: Board - Bono
C18: Detroit | D18: Romi Figueroa | E18: Otros Gastos
C19: IRSA | D19: Vanu Lanza | E19: Administración Finanzas - Bono
C20: Uber | D20: Lola Camara | E20: Intereses Oxean
C21: Coca-Cola | D21: Trini Petreigne
C22: Kimberly Clark | D22: Aylu Tamer
C23: Tortugas Open Mall | D23: Maricel Perez
C24: Epical | D24: Mati Gonzalez
C25: Cami Criado | D25: To Merello
C26: PeYa | D26: Cata Astiz
C27: Molino Chacabuco | D27: Ina Ceravolo
C28: PepsiCo | D28: Male Quiroga
D29: Sol Ayala
D30: Xavi Aranzana
D31: Pablo Ovejero
D32: Sandra Heyman
D33: Tomi Facio
D34: Honorarios Oxean
D35: Itecsa
D36: Netquest
D37: Ianece Leandro
D38: Gastón Julian
D39: Belen Lebrón
D40: Estudio Contable
... D55: Cami Burstein

Sheet Clasificaciones
A1: Costos indirectos e directos | D1: Clientes activos
A2: Detalle | B2: Subtipo de costo | D2: ARCOS DORADOS ARGENTINA S.A. | E2: Arcos Dorados
A3: Vicky Achabal | B3: Equipo | D3: PLAY DIGITAL S. A. | E3: Play Digital S.A (Modo)
A4: Vicky Puricelli | B4: Board | D4: COMPENSADORA ELECTRONICA SA | E4: Coelsa
A5: Tomi Criado | B5: Board | D5: MORENO OCAMPO | E5: Moreno Ocampo
A6: People | B6: People | D6: WARNER BROS | E6: Warner
A7: IIBB | B7: Impuestos ARG | D7: VERTICAL MEDIA | E7: Vertical Media
A8: IVA | B8: Impuestos ARG | D8: VERTICAL MEDIA LLC | E8: Vertical Media
A9: Tarjeta ARG | B9: Tarjeta | D9: UBER | E9: Uber
A10: Impuestos USA | B10: Impuestos USA | D10: DETROIT | E10: Detroit
A11: Brandwatch | B11: Suscripciones/Herramientas | D11: SERVICIOS INTEGRADOS DE ADMINISTRACION Y ALTA GER | E11: Coca-Cola
A12: Youscan | B12: Suscripciones/Herramientas | D12: KIMBERLY | E12: Kimberly Clark
A13: Otras Suscripciones | B13: Suscripciones/Herramientas | D13: ANIMAL STUDIO S.R.L. | E13: Animal Studio
... A16: Luan Digital | B16: Gastos Varios | D16: Turner International Latin America, Inc. | E16: Warner
A17: Tarjeta USA | B17: Tarjeta
A18: Romi Figueroa | B18: Equipo
A19: Vanu Lanza | B19: Equipo
A20: Lola Camara | B20: Equipo
A21: Trini Petreigne | B21: Equipo
A22: Aylu Tamer | B22: Equipo
A23: Maricel Perez | B23: Equipo
A24: Mati Gonzalez | B24: Equipo
A25: To Merello | B25: Equipo
A26: Cata Astiz | B26: Equipo
A27: Ina Ceravolo | B27: Equipo
A28: Male Quiroga | B28: Equipo
... A53: Cami Burstein | B53: Equipo

Sheet Impuestos
B1: MAYO | D1: JUNIO | F1: JULIO | H1: AGOSTO | J1: SEPTIEMBRE
B2: ARG | C2: USA | D2: ARG | E2: USA | F2: ARG | G2: USA | H2: ARG | I2: USA | J2: ARG | K2: USA
A3: VTAS | B3: 8204981 | C3: 1750 | D3: 8956556 | E3: =1750+7350 -> 9100 | F3: 9826556 | G3: 8450 | H3: =10551741-1441885 -> 9109856 | I3: 133570 | J3: =14705569-1114000 -> 13591569 | K3: 97420
A4: IVA VTAS | B4: =B3*21% -> 1723046 | C4: 0 | D4: =D3*21% -> 1880876.8 | E4: 0 | F4: =F3*21% -> 2063576.8 | G4: 0 | H4: 1913069.8 | J4: =J3*21% -> 2854229.5
A5: COMPRAS (GTOS-COSTOS) | B5: 34213915 | C5: =15553+21000 -> 36553 | D5: 7918673 | E5: 46416 | F5: 4762446 | G5: =4523 -> 4523 | H5: 12853757 | I5: 40061 | J5: 10904521 | K5: 31766
A6: IVA CPRAS | B6: =5490.08+20564.73+23205 -> 49259.81 | D6: =24990+10338.3+5067.77+4560.99 -> 44957.06 | F6: 50775 | H6: 36275 | J6: 42925.05
A7: IVA | B7: =B4-B6 -> 1673786.2 | D7: =D4-D6 -> 1835919.7 | F7: =F4-F6 -> 2012801.8 | H7: =H4-H6 -> 1876794.8 | J7: =J4-J6 -> 2811304.4
A8: IB | B8: =(B3*0.6175*0.03)+(B3*0.3825*0.05) -> 308917.53 | D8: =(D3*0.6175*0.03)+(D3*0.3825*0.05) -> 337214.33 | F8: =(F3*0.6175*0.03)+(F3*0.3825*0.05) -> 369969.83 | H8: =(H3*0.6175*0.03)+(H3*0.3825*0.05) -> 342986.08 | J8: =(J3*0.6175*0.03)+(J3*0.3825*0.05) -> 511722.57
A9: ESTUDIO CONTABLE (con iva) | B9: =(B3*0.006) -> 49229.886 | D9: =D3*0.006 -> 53739.336 | F9: =(F3*0.006)*1.21 -> 71340.797 | H9: =(H3*0.006)*1.21 -> 66137.555 | J9: =(J3*0.006)*1.21 -> 98674.791
A10: GANANCIAS (ANUAL) | C10: =(C3-C5)*12%+C3*3% -> -4123.86 | E10: =(E3-E5)*12%+E3*3% -> -4204.92 | G10: =(G3-G5)*12%+G3*3% -> 724.74 | I10: =(I3-I5)*12%+I3*3% -> 15228.18 | K10: =(K3-K5)*12%+K3*3% -> 10801.08

Sheet Intereses Oxean
B1: Saldo | C1: Interés
A2: 45838 | B2: -91979 | C2: =B2*1% -> -919.79
A3: 45869 | B3: -68302 | C3: =B3*1% -> -683.02
A4: 45900 | B4: -42553 | C4: =B4*1% -> -425.53
A5: 45930 | B5: -74319.94 | C5: =B5*1% -> -743.1994

Sheet Activo
A1: Concepto/Banco | B1: Tipo de Activo | C1: Cliente | D1: Mes | E1: Año | F1: Cobrado/No Cobrado AL CIERRE | G1: Fecha de pago/Nota de credito | H1: Vencido | I1: Fecha Facturación | J1: Nro de Factura/Comprobante | K1: Razón Social/Cliente | L1: Detalle | M1: Fecha de vencimiento | N1: Moneda original ARS | O1: Moneda original USD | P1: Cotización | Q1: Monto Total USD
A2: Santander-Galicia-Nación | B2: =IF( A2="", "", IF( OR(A2="Santander-Galicia-Nación", A2="Bank Of America", A2="Transferwise", A2="Custodia Socios", A2="Cheques en cartera", A2="Caja"), "Activo Liquido", IF( OR(A2="Otras Inversiones", A2="Santander Inversiones"), "Mediano Plazo", IF( A2="Clientes a cobrar", "Clientes a cobrar", "DATO NO CARGADO" ) ) ) ) -> Activo Liquido | C2: =IF(K2="", "", IFERROR(VLOOKUP(K2, Clasificaciones!D:E, 2, FALSE), "DATO NO CARGADO")) | D2: 01 ene | E2: 2025 | H2: =IF( A2="", "", IF( AND( F2="No", OR(G2="",G2>M2), M2<TODAY() ), "Vencido", "A término" ) ) -> A término | N2: 8217613 | P2: =IF(ISBLANK(N2), "", VLOOKUP(D2&" "&E2, 'Info Tipo de Cambio y REM'!$A$24:$B$35, 2, FALSE)) -> 1220 | Q2: =IF(NOT(ISBLANK(N2)), N2 / P2, IF(NOT(ISBLANK(O2)), O2, "")) -> 6735.7484
A3: Bank Of America | B3: =IF( A3="", "", IF( OR(A3="Santander-Galicia-Nación", A3="Bank Of America", A3="Transferwise", A3="Custodia Socios", A3="Cheques en cartera", A3="Caja"), "Activo Liquido", IF( OR(A3="Otras Inversiones", A3="Santander Inversiones"), "Mediano Plazo", IF( A3="Clientes a cobrar", "Clientes a cobrar", "DATO NO CARGADO" ) ) ) ) -> Activo Liquido | C3: =IF(K3="", "", IFERROR(VLOOKUP(K3, Clasificaciones!D:E, 2, FALSE), "DATO NO CARGADO")) | D3: 01 ene | E3: 2025 | H3: =IF( A3="", "", IF( AND( F3="No", OR(G3="",G3>M3), M3<TODAY() ), "Vencido", "A término" ) ) -> A término | O3: -2840 | P3: =IF(ISBLANK(N3), "", VLOOKUP(D3&" "&E3, 'Info Tipo de Cambio y REM'!$A$24:$B$35, 2, FALSE)) | Q3: =IF(NOT(ISBLANK(N3)), N3 / P3, IF(NOT(ISBLANK(O3)), O3, "")) -> -2840
A4: Transferwise | B4: =IF( A4="", "", IF( OR(A4="Santander-Galicia-Nación", A4="Bank Of America", A4="Transferwise", A4="Custodia Socios", A4="Cheques en cartera", A4="Caja"), "Activo Liquido", IF( OR(A4="Otras Inversiones", A4="Santander Inversiones"), "Mediano Plazo", IF( A4="Clientes a cobrar", "Clientes a cobrar", "DATO NO CARGADO" ) ) ) ) -> Activo Liquido | C4: =IF(K4="", "", IFERROR(VLOOKUP(K4, Clasificaciones!D:E, 2, FALSE), "DATO NO CARGADO")) | D4: 01 ene | E4: 2025 | H4: =IF( A4="", "", IF( AND( F4="No", OR(G4="",G4>M4), M4<TODAY() ), "Vencido", "A término" ) ) -> A término | O4: 230 | P4: =IF(ISBLANK(N4), "", VLOOKUP(D4&" "&E4, 'Info Tipo de Cambio y REM'!$A$24:$B$35, 2, FALSE)) | Q4: =IF(NOT(ISBLANK(N4)), N4 / P4, IF(NOT(ISBLANK(O4)), O4, "")) -> 230
A5: Otras Inversiones | B5: =IF( A5="", "", IF( OR(A5="Santander-Galicia-Nación", A5="Bank Of America", A5="Transferwise", A5="Custodia Socios", A5="Cheques en cartera", A5="Caja"), "Activo Liquido", IF( OR(A5="Otras Inversiones", A5="Santander Inversiones"), "Mediano Plazo", IF( A5="Clientes a cobrar", "Clientes a cobrar", "DATO NO CARGADO" ) ) ) ) -> Mediano Plazo | C5: =IF(K5="", "", IFERROR(VLOOKUP(K5, Clasificaciones!D:E, 2, FALSE), "DATO NO CARGADO")) | D5: 01 ene | E5: 2025 | H5: =IF( A5="", "", IF( AND( F5="No", OR(G5="",G5>M5), M5<TODAY() ), "Vencido", "A término" ) ) -> A término | O5: 9200 | P5: =IF(ISBLANK(N5), "", VLOOKUP(D5&" "&E5, 'Info Tipo de Cambio y REM'!$A$24:$B$35, 2, FALSE)) | Q5: =IF(NOT(ISBLANK(N5)), N5 / P5, IF(NOT(ISBLANK(O5)), O5, "")) -> 9200
A6: Clientes a cobrar | B6: =IF( A6="", "", IF( OR(A6="Santander-Galicia-Nación", A6="Bank Of America", A6="Transferwise", A6="Custodia Socios", A6="Cheques en cartera", A6="Caja"), "Activo Liquido", IF( OR(A6="Otras Inversiones", A6="Santander Inversiones"), "Mediano Plazo", IF( A6="Clientes a cobrar", "Clientes a cobrar", "DATO NO CARGADO" ) ) ) ) -> Clientes a cobrar | C6: =IF(K6="", "", IFERROR(VLOOKUP(K6, Clasificaciones!D:E, 2, FALSE), "DATO NO CARGADO")) -> Arcos Dorados | D6: 01 ene | E6: 2025 | H6: =IF( A6="", "", IF( AND( F6="No", OR(G6="",G6>M6), M6<TODAY() ), "Vencido", "A término" ) ) -> A término | J6: Factura de Crédito MiPyME (FCE) N° A-00008-00000898 | K6: ARCOS DORADOS ARGENTINA S.A. | M6: 45680 | N6: 508200 | P6: =IF(ISBLANK(N6), "", VLOOKUP(D6&" "&E6, 'Info Tipo de Cambio y REM'!$A$24:$B$35, 2, FALSE)) -> 1220 | Q6: =IF(NOT(ISBLANK(N6)), N6 / P6, IF(NOT(ISBLANK(O6)), O6, "")) -> 416.55738
A7: Clientes a cobrar | B7: =IF( A7="", "", IF( OR(A7="Santander-Galicia-Nación", A7="Bank Of America", A7="Transferwise", A7="Custodia Socios", A7="Cheques en cartera", A7="Caja"), "Activo Liquido", IF( OR(A7="Otras Inversiones", A7="Santander Inversiones"), "Mediano Plazo", IF( A7="Clientes a cobrar", "Clientes a cobrar", "DATO NO CARGADO" ) ) ) ) -> Clientes a cobrar | C7: =IF(K7="", "", IFERROR(VLOOKUP(K7, Clasificaciones!D:E, 2, FALSE), "DATO NO CARGADO")) -> Play Digital S.A (Modo) | D7: 01 ene | E7: 2025 | H7: =IF( A7="", "", IF( AND( F7="No", OR(G7="",G7>M7), M7<TODAY() ), "Vencido", "A término" ) ) -> A término | J7: Factura de Venta N° A-00008-00001931 | K7: PLAY DIGITAL S. A. | M7: 45688 | N7: 4744208 | P7: =IF(ISBLANK(N7), "", VLOOKUP(D7&" "&E7, 'Info Tipo de Cambio y REM'!$A$24:$B$35, 2, FALSE)) -> 1220 | Q7: =IF(NOT(ISBLANK(N7)), N7 / P7, IF(NOT(ISBLANK(O7)), O7, "")) -> 3888.6951
A8: Clientes a cobrar | B8: =IF( A8="", "", IF( OR(A8="Santander-Galicia-Nación", A8="Bank Of America", A8="Transferwise", A8="Custodia Socios", A8="Cheques en cartera", A8="Caja"), "Activo Liquido", IF( OR(A8="Otras Inversiones", A8="Santander Inversiones"), "Mediano Plazo", IF( A8="Clientes a cobrar", "Clientes a cobrar", "DATO NO CARGADO" ) ) ) ) -> Clientes a cobrar | C8: =IF(K8="", "", IFERROR(VLOOKUP(K8, Clasificaciones!D:E, 2, FALSE), "DATO NO CARGADO")) -> Coelsa | D8: 01 ene | E8: 2025 | H8: =IF( A8="", "", IF( AND( F8="No", OR(G8="",G8>M8), M8<TODAY() ), "Vencido", "A término" ) ) -> A término | J8: Factura de Crédito MiPyME (FCE) N° A-00008-00000886 | K8: COMPENSADORA ELECTRONICA SA | M8: 45659 | N8: 4499766 | P8: =IF(ISBLANK(N8), "", VLOOKUP(D8&" "&E8, 'Info Tipo de Cambio y REM'!$A$24:$B$35, 2, FALSE)) -> 1220 | Q8: =IF(NOT(ISBLANK(N8)), N8 / P8, IF(NOT(ISBLANK(O8)), O8, "")) -> 3688.3328
A9: Clientes a cobrar | B9: =IF( A9="", "", IF( OR(A9="Santander-Galicia-Nación", A9="Bank Of America", A9="Transferwise", A9="Custodia Socios", A9="Cheques en cartera", A9="Caja"), "Activo Liquido", IF( OR(A9="Otras Inversiones", A9="Santander Inversiones"), "Mediano Plazo", IF( A9="Clientes a cobrar", "Clientes a cobrar", "DATO NO CARGADO" ) ) ) ) -> Clientes a cobrar | C9: =IF(K9="", "", IFERROR(VLOOKUP(K9, Clasificaciones!D:E, 2, FALSE), "DATO NO CARGADO")) -> Moreno Ocampo | D9: 01 ene | E9: 2025 | H9: =IF( A9="", "", IF( AND( F9="No", OR(G9="",G9>M9), M9<TODAY() ), "Vencido", "A término" ) ) -> A término | J9: Invoice 532 | K9: MORENO OCAMPO | M9: 45678 | O9: 250 | P9: =IF(ISBLANK(N9), "", VLOOKUP(D9&" "&E9, 'Info Tipo de Cambio y REM'!$A$24:$B$35, 2, FALSE)) | Q9: =IF(NOT(ISBLANK(N9)), N9 / P9, IF(NOT(ISBLANK(O9)), O9, "")) -> 250
A10: Clientes a cobrar | B10: =IF( A10="", "", IF( OR(A10="Santander-Galicia-Nación", A10="Bank Of America", A10="Transferwise", A10="Custodia Socios", A10="Cheques en cartera", A10="Caja"), "Activo Liquido", IF( OR(A10="Otras Inversiones", A10="Santander Inversiones"), "Mediano Plazo", IF( A10="Clientes a cobrar", "Clientes a cobrar", "DATO NO CARGADO" ) ) ) ) -> Clientes a cobrar | C10: =IF(K10="", "", IFERROR(VLOOKUP(K10, Clasificaciones!D:E, 2, FALSE), "DATO NO CARGADO")) -> Warner | D10: 01 ene | E10: 2025 | H10: =IF( A10="", "", IF( AND( F10="No", OR(G10="",G10>M10), M10<TODAY() ), "Vencido", "A término" ) ) -> A término | J10: Invoice 515 | K10: WARNER BROS | M10: 45714 | O10: 13450 | P10: =IF(ISBLANK(N10), "", VLOOKUP(D10&" "&E10, 'Info Tipo de Cambio y REM'!$A$24:$B$35, 2, FALSE)) | Q10: =IF(NOT(ISBLANK(N10)), N10 / P10, IF(NOT(ISBLANK(O10)), O10, "")) -> 13450
A11: Clientes a cobrar | B11: =IF( A11="", "", IF( OR(A11="Santander-Galicia-Nación", A11="Bank Of America", A11="Transferwise", A11="Custodia Socios", A11="Cheques en cartera", A11="Caja"), "Activo Liquido", IF( OR(A11="Otras Inversiones", A11="Santander Inversiones"), "Mediano Plazo", IF( A11="Clientes a cobrar", "Clientes a cobrar", "DATO NO CARGADO" ) ) ) ) -> Clientes a cobrar | C11: =IF(K11="", "", IFERROR(VLOOKUP(K11, Clasificaciones!D:E, 2, FALSE), "DATO NO CARGADO")) -> Warner | D11: 01 ene | E11: 2025 | H11: =IF( A11="", "", IF( AND( F11="No", OR(G11="",G11>M11), M11<TODAY() ), "Vencido", "A término" ) ) -> A término | J11: Invoice 525 | K11: WARNER BROS | M11: 45726 | O11: 13450 | P11: =IF(ISBLANK(N11), "", VLOOKUP(D11&" "&E11, 'Info Tipo de Cambio y REM'!$A$24:$B$35, 2, FALSE)) | Q11: =IF(NOT(ISBLANK(N11)), N11 / P11, IF(NOT(ISBLANK(O11)), O11, "")) -> 13450
A12: Clientes a cobrar | B12: =IF( A12="", "", IF( OR(A12="Santander-Galicia-Nación", A12="Bank Of America", A12="Transferwise", A12="Custodia Socios", A12="Cheques en cartera", A12="Caja"), "Activo Liquido", IF( OR(A12="Otras Inversiones", A12="Santander Inversiones"), "Mediano Plazo", IF( A12="Clientes a cobrar", "Clientes a cobrar", "DATO NO CARGADO" ) ) ) ) -> Clientes a cobrar | C12: =IF(K12="", "", IFERROR(VLOOKUP(K12, Clasificaciones!D:E, 2, FALSE), "DATO NO CARGADO")) -> Warner | D12: 01 ene | E12: 2025 | H12: =IF( A12="", "", IF( AND( F12="No", OR(G12="",G12>M12), M12<TODAY() ), "Vencido", "A término" ) ) -> A término | J12: Invoice 534 | K12: WARNER BROS | M12: 45750 | O12: 13450 | P12: =IF(ISBLANK(N12), "", VLOOKUP(D12&" "&E12, 'Info Tipo de Cambio y REM'!$A$24:$B$35, 2, FALSE)) | Q12: =IF(NOT(ISBLANK(N12)), N12 / P12, IF(NOT(ISBLANK(O12)), O12, "")) -> 13450
A13: Clientes a cobrar | B13: =IF( A13="", "", IF( OR(A13="Santander-Galicia-Nación", A13="Bank Of America", A13="Transferwise", A13="Custodia Socios", A13="Cheques en cartera", A13="Caja"), "Activo Liquido", IF( OR(A13="Otras Inversiones", A13="Santander Inversiones"), "Mediano Plazo", IF( A13="Clientes a cobrar", "Clientes a cobrar", "DATO NO CARGADO" ) ) ) ) -> Clientes a cobrar | C13: =IF(K13="", "", IFERROR(VLOOKUP(K13, Clasificaciones!D:E, 2, FALSE), "DATO NO CARGADO")) -> Vertical Media | D13: 01 ene | E13: 2025 | H13: =IF( A13="", "", IF( AND( F13="No", OR(G13="",G13>M13), M13<TODAY() ), "Vencido", "A término" ) ) -> A término | J13: INVOICE 539 | K13: VERTICAL MEDIA | M13: 45704 | O13: 1750 | P13: =IF(ISBLANK(N13), "", VLOOKUP(D13&" "&E13, 'Info Tipo de Cambio y REM'!$A$24:$B$35, 2, FALSE)) | Q13: =IF(NOT(ISBLANK(N13)), N13 / P13, IF(NOT(ISBLANK(O13)), O13, "")) -> 1750
A14: Clientes a cobrar | B14: =IF( A14="", "", IF( OR(A14="Santander-Galicia-Nación", A14="Bank Of America", A14="Transferwise", A14="Custodia Socios", A14="Cheques en cartera", A14="Caja"), "Activo Liquido", IF( OR(A14="Otras Inversiones", A14="Santander Inversiones"), "Mediano Plazo", IF( A14="Clientes a cobrar", "Clientes a cobrar", "DATO NO CARGADO" ) ) ) ) -> Clientes a cobrar | C14: =IF(K14="", "", IFERROR(VLOOKUP(K14, Clasificaciones!D:E, 2, FALSE), "DATO NO CARGADO")) -> Uber | D14: 01 ene | E14: 2025 | H14: =IF( A14="", "", IF( AND( F14="No", OR(G14="",G14>M14), M14<TODAY() ), "Vencido", "A término" ) ) -> A término | J14: Invoice 520 | K14: UBER | M14: 45690 | O14: 7150 | P14: =IF(ISBLANK(N14), "", VLOOKUP(D14&" "&E14, 'Info Tipo de Cambio y REM'!$A$24:$B$35, 2, FALSE)) | Q14: =IF(NOT(ISBLANK(N14)), N14 / P14, IF(NOT(ISBLANK(O14)), O14, "")) -> 7150
A15: Santander-Galicia-Nación | B15: =IF( A15="", "", IF( OR(A15="Santander-Galicia-Nación", A15="Bank Of America", A15="Transferwise", A15="Custodia Socios", A15="Cheques en cartera", A15="Caja"), "Activo Liquido", IF( OR(A15="Otras Inversiones", A15="Santander Inversiones"), "Mediano Plazo", IF( A15="Clientes a cobrar", "Clientes a cobrar", "DATO NO CARGADO" ) ) ) ) -> Activo Liquido | C15: =IF(K15="", "", IFERROR(VLOOKUP(K15, Clasificaciones!D:E, 2, FALSE), "DATO NO CARGADO")) | D15: 02 feb | E15: 2025 | H15: =IF( A15="", "", IF( AND( F15="No", OR(G15="",G15>M15), M15<TODAY() ), "Vencido", "A término" ) ) -> A término | N15: 29367 | P15: =IF(ISBLANK(N15), "", VLOOKUP(D15&" "&E15, 'Info Tipo de Cambio y REM'!$A$24:$B$35, 2, FALSE)) -> 1230 | Q15: =IF(NOT(ISBLANK(N15)), N15 / P15, IF(NOT(ISBLANK(O15)), O15, "")) -> 23.87561
A16: Bank Of America | B16: =IF( A16="", "", IF( OR(A16="Santander-Galicia-Nación", A16="Bank Of America", A16="Transferwise", A16="Custodia Socios", A16="Cheques en cartera", A16="Caja"), "Activo Liquido", IF( OR(A16="Otras Inversiones", A16="Santander Inversiones"), "Mediano Plazo", IF( A16="Clientes a cobrar", "Clientes a cobrar", "DATO NO CARGADO" ) ) ) ) -> Activo Liquido | C16: =IF(K16="", "", IFERROR(VLOOKUP(K16, Clasificaciones!D:E, 2, FALSE), "DATO NO CARGADO")) | D16: 02 feb | E16: 2025 | H16: =IF( A16="", "", IF( AND( F16="No", OR(G16="",G16>M16), M16<TODAY() ), "Vencido", "A término" ) ) -> A término | O16: -7604 | P16: =IF(ISBLANK(N16), "", VLOOKUP(D16&" "&E16, 'Info Tipo de Cambio y REM'!$A$24:$B$35, 2, FALSE)) | Q16: =IF(NOT(ISBLANK(N16)), N16 / P16, IF(NOT(ISBLANK(O16)), O16, "")) -> -7604
A17: Transferwise | B17: =IF( A17="", "", IF( OR(A17="Santander-Galicia-Nación", A17="Bank Of America", A17="Transferwise", A17="Custodia Socios", A17="Cheques en cartera", A17="Caja"), "Activo Liquido", IF( OR(A17="Otras Inversiones", A17="Santander Inversiones"), "Mediano Plazo", IF( A17="Clientes a cobrar", "Clientes a cobrar", "DATO NO CARGADO" ) ) ) ) -> Activo Liquido | C17: =IF(K17="", "", IFERROR(VLOOKUP(K17, Clasificaciones!D:E, 2, FALSE), "DATO NO CARGADO")) | D17: 02 feb | E17: 2025 | H17: =IF( A17="", "", IF( AND( F17="No", OR(G17="",G17>M17), M17<TODAY() ), "Vencido", "A término" ) ) -> A término | O17: 230 | P17: =IF(ISBLANK(N17), "", VLOOKUP(D17&" "&E17, 'Info Tipo de Cambio y REM'!$A$24:$B$35, 2, FALSE)) | Q17: =IF(NOT(ISBLANK(N17)), N17 / P17, IF(NOT(ISBLANK(O17)), O17, "")) -> 230
A18: Otras Inversiones | B18: =IF( A18="", "", IF( OR(A18="Santander-Galicia-Nación", A18="Bank Of America", A18="Transferwise", A18="Custodia Socios", A18="Cheques en cartera", A18="Caja"), "Activo Liquido", IF( OR(A18="Otras Inversiones", A18="Santander Inversiones"), "Mediano Plazo", IF( A18="Clientes a cobrar", "Clientes a cobrar", "DATO NO CARGADO" ) ) ) ) -> Mediano Plazo | C18: =IF(K18="", "", IFERROR(VLOOKUP(K18, Clasificaciones!D:E, 2, FALSE), "DATO NO CARGADO")) | D18: 02 feb | E18: 2025 | H18: =IF( A18="", "", IF( AND( F18="No", OR(G18="",G18>M18), M18<TODAY() ), "Vencido", "A término" ) ) -> A término | O18: 6983 | P18: =IF(ISBLANK(N18), "", VLOOKUP(D18&" "&E18, 'Info Tipo de Cambio y REM'!$A$24:$B$35, 2, FALSE)) | Q18: =IF(NOT(ISBLANK(N18)), N18 / P18, IF(NOT(ISBLANK(O18)), O18, "")) -> 6983
A19: Clientes a cobrar | B19: =IF( A19="", "", IF( OR(A19="Santander-Galicia-Nación", A19="Bank Of America", A19="Transferwise", A19="Custodia Socios", A19="Cheques en cartera", A19="Caja"), "Activo Liquido", IF( OR(A19="Otras Inversiones", A19="Santander Inversiones"), "Mediano Plazo", IF( A19="Clientes a cobrar", "Clientes a cobrar", "DATO NO CARGADO" ) ) ) ) -> Clientes a cobrar | C19: =IF(K19="", "", IFERROR(VLOOKUP(K19, Clasificaciones!D:E, 2, FALSE), "DATO NO CARGADO")) -> Play Digital S.A (Modo) | D19: 02 feb | E19: 2025 | H19: =IF( A19="", "", IF( AND( F19="No", OR(G19="",G19>M19), M19<TODAY() ), "Vencido", "A término" ) ) -> A término | J19: Factura de Venta N° A-00008-00001937 | K19: PLAY DIGITAL S. A. | M19: 45719 | N19: 4744208 | P19: =IF(ISBLANK(N19), "", VLOOKUP(D19&" "&E19, 'Info Tipo de Cambio y REM'!$A$24:$B$35, 2, FALSE)) -> 1230 | Q19: =IF(NOT(ISBLANK(N19)), N19 / P19, IF(NOT(ISBLANK(O19)), O19, "")) -> 3857.0797
A20: Clientes a cobrar | B20: =IF( A20="", "", IF( OR(A20="Santander-Galicia-Nación", A20="Bank Of America", A20="Transferwise", A20="Custodia Socios", A20="Cheques en cartera", A20="Caja"), "Activo Liquido", IF( OR(A20="Otras Inversiones", A20="Santander Inversiones"), "Mediano Plazo", IF( A20="Clientes a cobrar", "Clientes a cobrar", "DATO NO CARGADO" ) ) ) ) -> Clientes a cobrar | C20: =IF(K20="", "", IFERROR(VLOOKUP(K20, Clasificaciones!D:E, 2, FALSE), "DATO NO CARGADO")) -> Coelsa | D20: 02 feb | E20: 2025 | H20: =IF( A20="", "", IF( AND( F20="No", OR(G20="",G20>M20), M20<TODAY() ), "Vencido", "A término" ) ) -> A término | J20: Factura de Crédito MiPyME (FCE) N° A-00008-00000906 | K20: COMPENSADORA ELECTRONICA SA | M20: 45719 | N20: 4499766 | P20: =IF(ISBLANK(N20), "", VLOOKUP(D20&" "&E20, 'Info Tipo de Cambio y REM'!$A$24:$B$35, 2, FALSE)) -> 1230 | Q20: =IF(NOT(ISBLANK(N20)), N20 / P20, IF(NOT(ISBLANK(O20)), O20, "")) -> 3658.3463
A21: Clientes a cobrar | B21: =IF( A21="", "", IF( OR(A21="Santander-Galicia-Nación", A21="Bank Of America", A21="Transferwise", A21="Custodia Socios", A21="Cheques en cartera", A21="Caja"), "Activo Liquido", IF( OR(A21="Otras Inversiones", A21="Santander Inversiones"), "Mediano Plazo", IF( A21="Clientes a cobrar", "Clientes a cobrar", "DATO NO CARGADO" ) ) ) ) -> Clientes a cobrar | C21: =IF(K21="", "", IFERROR(VLOOKUP(K21, Clasificaciones!D:E, 2, FALSE), "DATO NO CARGADO")) -> Moreno Ocampo | D21: 02 feb | E21: 2025 | H21: =IF( A21="", "", IF( AND( F21="No", OR(G21="",G21>M21), M21<TODAY() ), "Vencido", "A término" ) ) -> A término | J21: Invoice 532 | K21: MORENO OCAMPO | M21: 45678 | O21: 250 | P21: =IF(ISBLANK(N21), "", VLOOKUP(D21&" "&E21, 'Info Tipo de Cambio y REM'!$A$24:$B$35, 2, FALSE)) | Q21: =IF(NOT(ISBLANK(N21)), N21 / P21, IF(NOT(ISBLANK(O21)), O21, "")) -> 250
A22: Clientes a cobrar | B22: =IF( A22="", "", IF( OR(A22="Santander-Galicia-Nación", A22="Bank Of America", A22="Transferwise", A22="Custodia Socios", A22="Cheques en cartera", A22="Caja"), "Activo Liquido", IF( OR(A22="Otras Inversiones", A22="Santander Inversiones"), "Mediano Plazo", IF( A22="Clientes a cobrar", "Clientes a cobrar", "DATO NO CARGADO" ) ) ) ) -> Clientes a cobrar | C22: =IF(K22="", "", IFERROR(VLOOKUP(K22, Clasificaciones!D:E, 2, FALSE), "DATO NO CARGADO")) -> Warner | D22: 02 feb | E22: 2025 | H22: =IF( A22="", "", IF( AND( F22="No", OR(G22="",G22>M22), M22<TODAY() ), "Vencido", "A término" ) ) -> A término | J22: Invoice 525 | K22: WARNER BROS | M22: 45726 | O22: 13450 | P22: =IF(ISBLANK(N22), "", VLOOKUP(D22&" "&E22, 'Info Tipo de Cambio y REM'!$A$24:$B$35, 2, FALSE)) | Q22: =IF(NOT(ISBLANK(N22)), N22 / P22, IF(NOT(ISBLANK(O22)), O22, "")) -> 13450
A23: Clientes a cobrar | B23: =IF( A23="", "", IF( OR(A23="Santander-Galicia-Nación", A23="Bank Of America", A23="Transferwise", A23="Custodia Socios", A23="Cheques en cartera", A23="Caja"), "Activo Liquido", IF( OR(A23="Otras Inversiones", A23="Santander Inversiones"), "Mediano Plazo", IF( A23="Clientes a cobrar", "Clientes a cobrar", "DATO NO CARGADO" ) ) ) ) -> Clientes a cobrar | C23: =IF(K23="", "", IFERROR(VLOOKUP(K23, Clasificaciones!D:E, 2, FALSE), "DATO NO CARGADO")) -> Warner | D23: 02 feb | E23: 2025 | H23: =IF( A23="", "", IF( AND( F23="No", OR(G23="",G23>M23), M23<TODAY() ), "Vencido", "A término" ) ) -> A término | J23: Invoice 534 | K23: WARNER BROS | M23: 45750 | O23: 13450 | P23: =IF(ISBLANK(N23), "", VLOOKUP(D23&" "&E23, 'Info Tipo de Cambio y REM'!$A$24:$B$35, 2, FALSE)) | Q23: =IF(NOT(ISBLANK(N23)), N23 / P23, IF(NOT(ISBLANK(O23)), O23, "")) -> 13450
A24: Clientes a cobrar | B24: =IF( A24="", "", IF( OR(A24="Santander-Galicia-Nación", A24="Bank Of America", A24="Transferwise", A24="Custodia Socios", A24="Cheques en cartera", A24="Caja"), "Activo Liquido", IF( OR(A24="Otras Inversiones", A24="Santander Inversiones"), "Mediano Plazo", IF( A24="Clientes a cobrar", "Clientes a cobrar", "DATO NO CARGADO" ) ) ) ) -> Clientes a cobrar | C24: =IF(K24="", "", IFERROR(VLOOKUP(K24, Clasificaciones!D:E, 2, FALSE), "DATO NO CARGADO")) -> Warner | D24: 02 feb | E24: 2025 | H24: =IF( A24="", "", IF( AND( F24="No", OR(G24="",G24>M24), M24<TODAY() ), "Vencido", "A término" ) ) -> A término | J24: Invoice 547 | K24: WARNER BROS | M24: 45782 | O24: 13450 | P24: =IF(ISBLANK(N24), "", VLOOKUP(D24&" "&E24, 'Info Tipo de Cambio y REM'!$A$24:$B$35, 2, FALSE)) | Q24: =IF(NOT(ISBLANK(N24)), N24 / P24, IF(NOT(ISBLANK(O24)), O24, "")) -> 13450
A25: Clientes a cobrar | B25: =IF( A25="", "", IF( OR(A25="Santander-Galicia-Nación", A25="Bank Of America", A25="Transferwise", A25="Custodia Socios", A25="Cheques en cartera", A25="Caja"), "Activo Liquido", IF( OR(A25="Otras Inversiones", A25="Santander Inversiones"), "Mediano Plazo", IF( A25="Clientes a cobrar", "Clientes a cobrar", "DATO NO CARGADO" ) ) ) ) -> Clientes a cobrar | C25: =IF(K25="", "", IFERROR(VLOOKUP(K25, Clasificaciones!D:E, 2, FALSE), "DATO NO CARGADO")) -> Vertical Media | D25: 02 feb | E25: 2025 | H25: =IF( A25="", "", IF( AND( F25="No", OR(G25="",G25>M25), M25<TODAY() ), "Vencido", "A término" ) ) -> A término | J25: Invoice 544 | K25: VERTICAL MEDIA | M25: 45719 | O25: 1750 | P25: =IF(ISBLANK(N25), "", VLOOKUP(D25&" "&E25, 'Info Tipo de Cambio y REM'!$A$24:$B$35, 2, FALSE)) | Q25: =IF(NOT(ISBLANK(N25)), N25 / P25, IF(NOT(ISBLANK(O25)), O25, "")) -> 1750
A26: Santander-Galicia-Nación | B26: =IF( A26="", "", IF( OR(A26="Santander-Galicia-Nación", A26="Bank Of America", A26="Transferwise", A26="Custodia Socios", A26="Cheques en cartera", A26="Caja"), "Activo Liquido", IF( OR(A26="Otras Inversiones", A26="Santander Inversiones"), "Mediano Plazo", IF( A26="Clientes a cobrar", "Clientes a cobrar", "DATO NO CARGADO" ) ) ) ) -> Activo Liquido | C26: =IF(K26="", "", IFERROR(VLOOKUP(K26, Clasificaciones!D:E, 2, FALSE), "DATO NO CARGADO")) | D26: 03 mar | E26: 2025 | H26: =IF( A26="", "", IF( AND( F26="No", OR(G26="",G26>M26), M26<TODAY() ), "Vencido", "A término" ) ) -> A término | N26: -429974 | P26: =IF(ISBLANK(N26), "", VLOOKUP(D26&" "&E26, 'Info Tipo de Cambio y REM'!$A$24:$B$35, 2, FALSE)) -> 1325 | Q26: =IF(NOT(ISBLANK(N26)), N26 / P26, IF(NOT(ISBLANK(O26)), O26, "")) -> -324.50868
A27: Bank Of America | B27: =IF( A27="", "", IF( OR(A27="Santander-Galicia-Nación", A27="Bank Of America", A27="Transferwise", A27="Custodia Socios", A27="Cheques en cartera", A27="Caja"), "Activo Liquido", IF( OR(A27="Otras Inversiones", A27="Santander Inversiones"), "Mediano Plazo", IF( A27="Clientes a cobrar", "Clientes a cobrar", "DATO NO CARGADO" ) ) ) ) -> Activo Liquido | C27: =IF(K27="", "", IFERROR(VLOOKUP(K27, Clasificaciones!D:E, 2, FALSE), "DATO NO CARGADO")) | D27: 03 mar | E27: 2025 | H27: =IF( A27="", "", IF( AND( F27="No", OR(G27="",G27>M27), M27<TODAY() ), "Vencido", "A término" ) ) -> A término | O27: -26706 | P27: =IF(ISBLANK(N27), "", VLOOKUP(D27&" "&E27, 'Info Tipo de Cambio y REM'!$A$24:$B$35, 2, FALSE)) | Q27: =IF(NOT(ISBLANK(N27)), N27 / P27, IF(NOT(ISBLANK(O27)), O27, "")) -> -26706
A28: Transferwise | B28: =IF( A28="", "", IF( OR(A28="Santander-Galicia-Nación", A28="Bank Of America", A28="Transferwise", A28="Custodia Socios", A28="Cheques en cartera", A28="Caja"), "Activo Liquido", IF( OR(A28="Otras Inversiones", A28="Santander Inversiones"), "Mediano Plazo", IF( A28="Clientes a cobrar", "Clientes a cobrar", "DATO NO CARGADO" ) ) ) ) -> Activo Liquido | C28: =IF(K28="", "", IFERROR(VLOOKUP(K28, Clasificaciones!D:E, 2, FALSE), "DATO NO CARGADO")) | D28: 03 mar | E28: 2025 | H28: =IF( A28="", "", IF( AND( F28="No", OR(G28="",G28>M28), M28<TODAY() ), "Vencido", "A término" ) ) -> A término | O28: 230 | P28: =IF(ISBLANK(N28), "", VLOOKUP(D28&" "&E28, 'Info Tipo de Cambio y REM'!$A$24:$B$35, 2, FALSE)) | Q28: =IF(NOT(ISBLANK(N28)), N28 / P28, IF(NOT(ISBLANK(O28)), O28, "")) -> 230
A29: Otras Inversiones | B29: =IF( A29="", "", IF( OR(A29="Santander-Galicia-Nación", A29="Bank Of America", A29="Transferwise", A29="Custodia Socios", A29="Cheques en cartera", A29="Caja"), "Activo Liquido", IF( OR(A29="Otras Inversiones", A29="Santander Inversiones"), "Mediano Plazo", IF( A29="Clientes a cobrar", "Clientes a cobrar", "DATO NO CARGADO" ) ) ) ) -> Mediano Plazo | C29: =IF(K29="", "", IFERROR(VLOOKUP(K29, Clasificaciones!D:E, 2, FALSE), "DATO NO CARGADO")) | D29: 03 mar | E29: 2025 | H29: =IF( A29="", "", IF( AND( F29="No", OR(G29="",G29>M29), M29<TODAY() ), "Vencido", "A término" ) ) -> A término | O29: 2499 | P29: =IF(ISBLANK(N29), "", VLOOKUP(D29&" "&E29, 'Info Tipo de Cambio y REM'!$A$24:$B$35, 2, FALSE)) | Q29: =IF(NOT(ISBLANK(N29)), N29 / P29, IF(NOT(ISBLANK(O29)), O29, "")) -> 2499
A30: Clientes a cobrar | B30: =IF( A30="", "", IF( OR(A30="Santander-Galicia-Nación", A30="Bank Of America", A30="Transferwise", A30="Custodia Socios", A30="Cheques en cartera", A30="Caja"), "Activo Liquido", IF( OR(A30="Otras Inversiones", A30="Santander Inversiones"), "Mediano Plazo", IF( A30="Clientes a cobrar", "Clientes a cobrar", "DATO NO CARGADO" ) ) ) ) -> Clientes a cobrar | C30: =IF(K30="", "", IFERROR(VLOOKUP(K30, Clasificaciones!D:E, 2, FALSE), "DATO NO CARGADO")) -> Play Digital S.A (Modo) | D30: 03 mar | E30: 2025 | H30: =IF( A30="", "", IF( AND( F30="No", OR(G30="",G30>M30), M30<TODAY() ), "Vencido", "A término" ) ) -> A término | J30: Factura de Venta N° A-00008-00001939 | K30: PLAY DIGITAL S. A. | M30: 45752 | N30: 5095280 | P30: =IF(ISBLANK(N30), "", VLOOKUP(D30&" "&E30, 'Info Tipo de Cambio y REM'!$A$24:$B$35, 2, FALSE)) -> 1325 | Q30: =IF(NOT(ISBLANK(N30)), N30 / P30, IF(NOT(ISBLANK(O30)), O30, "")) -> 3845.4943
A31: Clientes a cobrar | B31: =IF( A31="", "", IF( OR(A31="Santander-Galicia-Nación", A31="Bank Of America", A31="Transferwise", A31="Custodia Socios", A31="Cheques en cartera", A31="Caja"), "Activo Liquido", IF( OR(A31="Otras Inversiones", A31="Santander Inversiones"), "Mediano Plazo", IF( A31="Clientes a cobrar", "Clientes a cobrar", "DATO NO CARGADO" ) ) ) ) -> Clientes a cobrar | C31: =IF(K31="", "", IFERROR(VLOOKUP(K31, Clasificaciones!D:E, 2, FALSE), "DATO NO CARGADO")) -> Coelsa | D31: 03 mar | E31: 2025 | H31: =IF( A31="", "", IF( AND( F31="No", OR(G31="",G31>M31), M31<TODAY() ), "Vencido", "A término" ) ) -> A término | J31: Factura de Crédito MiPyME (FCE) N° A-00008-00000922 | K31: COMPENSADORA ELECTRONICA SA | M31: 45752 | N31: 4832747 | P31: =IF(ISBLANK(N31), "", VLOOKUP(D31&" "&E31, 'Info Tipo de Cambio y REM'!$A$24:$B$35, 2, FALSE)) -> 1325 | Q31: =IF(NOT(ISBLANK(N31)), N31 / P31, IF(NOT(ISBLANK(O31)), O31, "")) -> 3647.3562
A32: Clientes a cobrar | B32: =IF( A32="", "", IF( OR(A32="Santander-Galicia-Nación", A32="Bank Of America", A32="Transferwise", A32="Custodia Socios", A32="Cheques en cartera", A32="Caja"), "Activo Liquido", IF( OR(A32="Otras Inversiones", A32="Santander Inversiones"), "Mediano Plazo", IF( A32="Clientes a cobrar", "Clientes a cobrar", "DATO NO CARGADO" ) ) ) ) -> Clientes a cobrar | C32: =IF(K32="", "", IFERROR(VLOOKUP(K32, Clasificaciones!D:E, 2, FALSE), "DATO NO CARGADO")) -> Arcos Dorados | D32: 03 mar | E32: 2025 | H32: =IF( A32="", "", IF( AND( F32="No", OR(G32="",G32>M32), M32<TODAY() ), "Vencido", "A término" ) ) -> A término | J32: Factura de Crédito MiPyME (FCE) N° A-00008-00000925 | K32: ARCOS DORADOS ARGENTINA S.A. | M32: 45771 | N32: 4150300 | P32: =IF(ISBLANK(N32), "", VLOOKUP(D32&" "&E32, 'Info Tipo de Cambio y REM'!$A$24:$B$35, 2, FALSE)) -> 1325 | Q32: =IF(NOT(ISBLANK(N32)), N32 / P32, IF(NOT(ISBLANK(O32)), O32, "")) -> 3132.3019
A33: Clientes a cobrar | B33: =IF( A33="", "", IF( OR(A33="Santander-Galicia-Nación", A33="Bank Of America", A33="Transferwise", A33="Custodia Socios", A33="Cheques en cartera", A33="Caja"), "Activo Liquido", IF( OR(A33="Otras Inversiones", A33="Santander Inversiones"), "Mediano Plazo", IF( A33="Clientes a cobrar", "Clientes a cobrar", "DATO NO CARGADO" ) ) ) ) -> Clientes a cobrar | C33: =IF(K33="", "", IFERROR(VLOOKUP(K33, Clasificaciones!D:E, 2, FALSE), "DATO NO CARGADO")) -> Moreno Ocampo | D33: 03 mar | E33: 2025 | H33: =IF( A33="", "", IF( AND( F33="No", OR(G33="",G33>M33), M33<TODAY() ), "Vencido", "A término" ) ) -> A término | J33: Invoice 532 | K33: MORENO OCAMPO | M33: 45678 | O33: 250 | P33: =IF(ISBLANK(N33), "", VLOOKUP(D33&" "&E33, 'Info Tipo de Cambio y REM'!$A$24:$B$35, 2, FALSE)) | Q33: =IF(NOT(ISBLANK(N33)), N33 / P33, IF(NOT(ISBLANK(O33)), O33, "")) -> 250
A34: Clientes a cobrar | B34: =IF( A34="", "", IF( OR(A34="Santander-Galicia-Nación", A34="Bank Of America", A34="Transferwise", A34="Custodia Socios", A34="Cheques en cartera", A34="Caja"), "Activo Liquido", IF( OR(A34="Otras Inversiones", A34="Santander Inversiones"), "Mediano Plazo", IF( A34="Clientes a cobrar", "Clientes a cobrar", "DATO NO CARGADO" ) ) ) ) -> Clientes a cobrar | C34: =IF(K34="", "", IFERROR(VLOOKUP(K34, Clasificaciones!D:E, 2, FALSE), "DATO NO CARGADO")) -> Warner | D34: 03 mar | E34: 2025 | H34: =IF( A34="", "", IF( AND( F34="No", OR(G34="",G34>M34), M34<TODAY() ), "Vencido", "A término" ) ) -> A término | J34: Invoice 525 | K34: WARNER BROS | M34: 45726 | O34: 13450 | P34: =IF(ISBLANK(N34), "", VLOOKUP(D34&" "&E34, 'Info Tipo de Cambio y REM'!$A$24:$B$35, 2, FALSE)) | Q34: =IF(NOT(ISBLANK(N34)), N34 / P34, IF(NOT(ISBLANK(O34)), O34, "")) -> 13450
A35: Clientes a cobrar | B35: =IF( A35="", "", IF( OR(A35="Santander-Galicia-Nación", A35="Bank Of America", A35="Transferwise", A35="Custodia Socios", A35="Cheques en cartera", A35="Caja"), "Activo Liquido", IF( OR(A35="Otras Inversiones", A35="Santander Inversiones"), "Mediano Plazo", IF( A35="Clientes a cobrar", "Clientes a cobrar", "DATO NO CARGADO" ) ) ) ) -> Clientes a cobrar | C35: =IF(K35="", "", IFERROR(VLOOKUP(K35, Clasificaciones!D:E, 2, FALSE), "DATO NO CARGADO")) -> Warner | D35: 03 mar | E35: 2025 | H35: =IF( A35="", "", IF( AND( F35="No", OR(G35="",G35>M35), M35<TODAY() ), "Vencido", "A término" ) ) -> A término | J35: Invoice 534 | K35: WARNER BROS | M35: 45750 | O35: 13450 | P35: =IF(ISBLANK(N35), "", VLOOKUP(D35&" "&E35, 'Info Tipo de Cambio y REM'!$A$24:$B$35, 2, FALSE)) | Q35: =IF(NOT(ISBLANK(N35)), N35 / P35, IF(NOT(ISBLANK(O35)), O35, "")) -> 13450
A36: Clientes a cobrar | B36: =IF( A36="", "", IF( OR(A36="Santander-Galicia-Nación", A36="Bank Of America", A36="Transferwise", A36="Custodia Socios", A36="Cheques en cartera", A36="Caja"), "Activo Liquido", IF( OR(A36="Otras Inversiones", A36="Santander Inversiones"), "Mediano Plazo", IF( A36="Clientes a cobrar", "Clientes a cobrar", "DATO NO CARGADO" ) ) ) ) -> Clientes a cobrar | C36: =IF(K36="", "", IFERROR(VLOOKUP(K36, Clasificaciones!D:E, 2, FALSE), "DATO NO CARGADO")) -> Warner | D36: 03 mar | E36: 2025 | H36: =IF( A36="", "", IF( AND( F36="No", OR(G36="",G36>M36), M36<TODAY() ), "Vencido", "A término" ) ) -> A término | J36: Invoice 547 | K36: WARNER BROS | M36: 45782 | O36: 13450 | P36: =IF(ISBLANK(N36), "", VLOOKUP(D36&" "&E36, 'Info Tipo de Cambio y REM'!$A$24:$B$35, 2, FALSE)) | Q36: =IF(NOT(ISBLANK(N36)), N36 / P36, IF(NOT(ISBLANK(O36)), O36, "")) -> 13450
A37: Clientes a cobrar | B37: =IF( A37="", "", IF( OR(A37="Santander-Galicia-Nación", A37="Bank Of America", A37="Transferwise", A37="Custodia Socios", A37="Cheques en cartera", A37="Caja"), "Activo Liquido", IF( OR(A37="Otras Inversiones", A37="Santander Inversiones"), "Mediano Plazo", IF( A37="Clientes a cobrar", "Clientes a cobrar", "DATO NO CARGADO" ) ) ) ) -> Clientes a cobrar | C37: =IF(K37="", "", IFERROR(VLOOKUP(K37, Clasificaciones!D:E, 2, FALSE), "DATO NO CARGADO")) -> Warner | D37: 03 mar | E37: 2025 | H37: =IF( A37="", "", IF( AND( F37="No", OR(G37="",G37>M37), M37<TODAY() ), "Vencido", "A término" ) ) -> A término | J37: Invoice 553 | K37: WARNER BROS | M37: 45813 | O37: 13450 | P37: =IF(ISBLANK(N37), "", VLOOKUP(D37&" "&E37, 'Info Tipo de Cambio y REM'!$A$24:$B$35, 2, FALSE)) | Q37: =IF(NOT(ISBLANK(N37)), N37 / P37, IF(NOT(ISBLANK(O37)), O37, "")) -> 13450
A38: Clientes a cobrar | B38: =IF( A38="", "", IF( OR(A38="Santander-Galicia-Nación", A38="Bank Of America", A38="Transferwise", A38="Custodia Socios", A38="Cheques en cartera", A38="Caja"), "Activo Liquido", IF( OR(A38="Otras Inversiones", A38="Santander Inversiones"), "Mediano Plazo", IF( A38="Clientes a cobrar", "Clientes a cobrar", "DATO NO CARGADO" ) ) ) ) -> Clientes a cobrar | C38: =IF(K38="", "", IFERROR(VLOOKUP(K38, Clasificaciones!D:E, 2, FALSE), "DATO NO CARGADO")) -> Vertical Media | D38: 03 mar | E38: 2025 | H38: =IF( A38="", "", IF( AND( F38="No", OR(G38="",G38>M38), M38<TODAY() ), "Vencido", "A término" ) ) -> A término | J38: Invoice 560 | K38: VERTICAL MEDIA | M38: 45757 | O38: 1750 | P38: =IF(ISBLANK(N38), "", VLOOKUP(D38&" "&E38, 'Info Tipo de Cambio y REM'!$A$24:$B$35, 2, FALSE)) | Q38: =IF(NOT(ISBLANK(N38)), N38 / P38, IF(NOT(ISBLANK(O38)), O38, "")) -> 1750
A39: Santander-Galicia-Nación | B39: =IF( A39="", "", IF( OR(A39="Santander-Galicia-Nación", A39="Bank Of America", A39="Transferwise", A39="Custodia Socios", A39="Cheques en cartera", A39="Caja"), "Activo Liquido", IF( OR(A39="Otras Inversiones", A39="Santander Inversiones"), "Mediano Plazo", IF( A39="Clientes a cobrar", "Clientes a cobrar", "DATO NO CARGADO" ) ) ) ) -> Activo Liquido | C39: =IF(K39="", "", IFERROR(VLOOKUP(K39, Clasificaciones!D:E, 2, FALSE), "DATO NO CARGADO")) | D39: 04 abr | E39: 2025 | H39: =IF( A39="", "", IF( AND( F39="No", OR(G39="",G39>M39), M39<TODAY() ), "Vencido", "A término" ) ) -> A término | N39: 5365042 | P39: =IF(ISBLANK(N39), "", VLOOKUP(D39&" "&E39, 'Info Tipo de Cambio y REM'!$A$24:$B$35, 2, FALSE)) -> 1185 | Q39: =IF(NOT(ISBLANK(N39)), N39 / P39, IF(NOT(ISBLANK(O39)), O39, "")) -> 4527.4616
A40: Bank Of America | B40: =IF( A40="", "", IF( OR(A40="Santander-Galicia-Nación", A40="Bank Of America", A40="Transferwise", A40="Custodia Socios", A40="Cheques en cartera", A40="Caja"), "Activo Liquido", IF( OR(A40="Otras Inversiones", A40="Santander Inversiones"), "Mediano Plazo", IF( A40="Clientes a cobrar", "Clientes a cobrar", "DATO NO CARGADO" ) ) ) ) -> Activo Liquido | C40: =IF(K40="", "", IFERROR(VLOOKUP(K40, Clasificaciones!D:E, 2, FALSE), "DATO NO CARGADO")) | D40: 04 abr | E40: 2025 | H40: =IF( A40="", "", IF( AND( F40="No", OR(G40="",G40>M40), M40<TODAY() ), "Vencido", "A término" ) ) -> A término | O40: -27709 | P40: =IF(ISBLANK(N40), "", VLOOKUP(D40&" "&E40, 'Info Tipo de Cambio y REM'!$A$24:$B$35, 2, FALSE)) | Q40: =IF(NOT(ISBLANK(N40)), N40 / P40, IF(NOT(ISBLANK(O40)), O40, "")) -> -27709
A41: Transferwise | B41: =IF( A41="", "", IF( OR(A41="Santander-Galicia-Nación", A41="Bank Of America", A41="Transferwise", A41="Custodia Socios", A41="Cheques en cartera", A41="Caja"), "Activo Liquido", IF( OR(A41="Otras Inversiones", A41="Santander Inversiones"), "Mediano Plazo", IF( A41="Clientes a cobrar", "Clientes a cobrar", "DATO NO CARGADO" ) ) ) ) -> Activo Liquido | C41: =IF(K41="", "", IFERROR(VLOOKUP(K41, Clasificaciones!D:E, 2, FALSE), "DATO NO CARGADO")) | D41: 04 abr | E41: 2025 | H41: =IF( A41="", "", IF( AND( F41="No", OR(G41="",G41>M41), M41<TODAY() ), "Vencido", "A término" ) ) -> A término | O41: 230 | P41: =IF(ISBLANK(N41), "", VLOOKUP(D41&" "&E41, 'Info Tipo de Cambio y REM'!$A$24:$B$35, 2, FALSE)) | Q41: =IF(NOT(ISBLANK(N41)), N41 / P41, IF(NOT(ISBLANK(O41)), O41, "")) -> 230
A42: Otras Inversiones | B42: =IF( A42="", "", IF( OR(A42="Santander-Galicia-Nación", A42="Bank Of America", A42="Transferwise", A42="Custodia Socios", A42="Cheques en cartera", A42="Caja"), "Activo Liquido", IF( OR(A42="Otras Inversiones", A42="Santander Inversiones"), "Mediano Plazo", IF( A42="Clientes a cobrar", "Clientes a cobrar", "DATO NO CARGADO" ) ) ) ) -> Mediano Plazo | C42: =IF(K42="", "", IFERROR(VLOOKUP(K42, Clasificaciones!D:E, 2, FALSE), "DATO NO CARGADO")) | D42: 04 abr | E42: 2025 | H42: =IF( A42="", "", IF( AND( F42="No", OR(G42="",G42>M42), M42<TODAY() ), "Vencido", "A término" ) ) -> A término | O42: 2517 | P42: =IF(ISBLANK(N42), "", VLOOKUP(D42&" "&E42, 'Info Tipo de Cambio y REM'!$A$24:$B$35, 2, FALSE)) | Q42: =IF(NOT(ISBLANK(N42)), N42 / P42, IF(NOT(ISBLANK(O42)), O42, "")) -> 2517
A43: Clientes a cobrar | B43: =IF( A43="", "", IF( OR(A43="Santander-Galicia-Nación", A43="Bank Of America", A43="Transferwise", A43="Custodia Socios", A43="Cheques en cartera", A43="Caja"), "Activo Liquido", IF( OR(A43="Otras Inversiones", A43="Santander Inversiones"), "Mediano Plazo", IF( A43="Clientes a cobrar", "Clientes a cobrar", "DATO NO CARGADO" ) ) ) ) -> Clientes a cobrar | C43: =IF(K43="", "", IFERROR(VLOOKUP(K43, Clasificaciones!D:E, 2, FALSE), "DATO NO CARGADO")) -> Warner | D43: 04 abr | E43: 2025 | F43: No | G43: 45779 | H43: =IF( A43="", "", IF( AND( F43="No", OR(G43="",G43>M43), M43<TODAY() ), "Vencido", "A término" ) ) -> A término | I43: 45692 | J43: Invoice 547 | K43: WARNER BROS | M43: 45782 | O43: 13450 | P43: =IF(ISBLANK(N43), "", VLOOKUP(D43&" "&E43, 'Info Tipo de Cambio y REM'!$A$24:$B$35, 2, FALSE)) | Q43: =IF(NOT(ISBLANK(N43)), N43 / P43, IF(NOT(ISBLANK(O43)), O43, "")) -> 13450
A44: Clientes a cobrar | B44: =IF( A44="", "", IF( OR(A44="Santander-Galicia-Nación", A44="Bank Of America", A44="Transferwise", A44="Custodia Socios", A44="Cheques en cartera", A44="Caja"), "Activo Liquido", IF( OR(A44="Otras Inversiones", A44="Santander Inversiones"), "Mediano Plazo", IF( A44="Clientes a cobrar", "Clientes a cobrar", "DATO NO CARGADO" ) ) ) ) -> Clientes a cobrar | C44: =IF(K44="", "", IFERROR(VLOOKUP(K44, Clasificaciones!D:E, 2, FALSE), "DATO NO CARGADO")) -> Warner | D44: 04 abr | E44: 2025 | F44: No | G44: 45840 | H44: =IF( A44="", "", IF( AND( F44="No", OR(G44="",G44>M44), M44<TODAY() ), "Vencido", "A término" ) ) -> Vencido | I44: 45723 | J44: Invoice 553 | K44: WARNER BROS | M44: 45813 | O44: 13450 | P44: =IF(ISBLANK(N44), "", VLOOKUP(D44&" "&E44, 'Info Tipo de Cambio y REM'!$A$24:$B$35, 2, FALSE)) | Q44: =IF(NOT(ISBLANK(N44)), N44 / P44, IF(NOT(ISBLANK(O44)), O44, "")) -> 13450
A45: Clientes a cobrar | B45: =IF( A45="", "", IF( OR(A45="Santander-Galicia-Nación", A45="Bank Of America", A45="Transferwise", A45="Custodia Socios", A45="Cheques en cartera", A45="Caja"), "Activo Liquido", IF( OR(A45="Otras Inversiones", A45="Santander Inversiones"), "Mediano Plazo", IF( A45="Clientes a cobrar", "Clientes a cobrar", "DATO NO CARGADO" ) ) ) ) -> Clientes a cobrar | C45: =IF(K45="", "", IFERROR(VLOOKUP(K45, Clasificaciones!D:E, 2, FALSE), "DATO NO CARGADO")) -> Warner | D45: 04 abr | E45: 2025 | F45: No | G45: 45845 | H45: =IF( A45="", "", IF( AND( F45="No", OR(G45="",G45>M45), M45<TODAY() ), "Vencido", "A término" ) ) -> Vencido | I45: 45751 | J45: Invoice 568 | K45: WARNER BROS | M45: 45841 | O45: 13450 | P45: =IF(ISBLANK(N45), "", VLOOKUP(D45&" "&E45, 'Info Tipo de Cambio y REM'!$A$24:$B$35, 2, FALSE)) | Q45: =IF(NOT(ISBLANK(N45)), N45 / P45, IF(NOT(ISBLANK(O45)), O45, "")) -> 13450
A46: Clientes a cobrar | B46: =IF( A46="", "", IF( OR(A46="Santander-Galicia-Nación", A46="Bank Of America", A46="Transferwise", A46="Custodia Socios", A46="Cheques en cartera", A46="Caja"), "Activo Liquido", IF( OR(A46="Otras Inversiones", A46="Santander Inversiones"), "Mediano Plazo", IF( A46="Clientes a cobrar", "Clientes a cobrar", "DATO NO CARGADO" ) ) ) ) -> Clientes a cobrar | C46: =IF(K46="", "", IFERROR(VLOOKUP(K46, Clasificaciones!D:E, 2, FALSE), "DATO NO CARGADO")) -> Warner | D46: 04 abr | E46: 2025 | F46: No | G46: 45861 | H46: =IF( A46="", "", IF( AND( F46="No", OR(G46="",G46>M46), M46<TODAY() ), "Vencido", "A término" ) ) -> A término | I46: 45770 | J46: Invoice 575 | K46: WARNER BROS | M46: 45865 | O46: 1300 | P46: =IF(ISBLANK(N46), "", VLOOKUP(D46&" "&E46, 'Info Tipo de Cambio y REM'!$A$24:$B$35, 2, FALSE)) | Q46: =IF(NOT(ISBLANK(N46)), N46 / P46, IF(NOT(ISBLANK(O46)), O46, "")) -> 1300
A47: Clientes a cobrar | B47: =IF( A47="", "", IF( OR(A47="Santander-Galicia-Nación", A47="Bank Of America", A47="Transferwise", A47="Custodia Socios", A47="Cheques en cartera", A47="Caja"), "Activo Liquido", IF( OR(A47="Otras Inversiones", A47="Santander Inversiones"), "Mediano Plazo", IF( A47="Clientes a cobrar", "Clientes a cobrar", "DATO NO CARGADO" ) ) ) ) -> Clientes a cobrar | C47: =IF(K47="", "", IFERROR(VLOOKUP(K47, Clasificaciones!D:E, 2, FALSE), "DATO NO CARGADO")) -> Moreno Ocampo | D47: 04 abr | E47: 2025 | F47: No | G47: 45894 | H47: =IF( A47="", "", IF( AND( F47="No", OR(G47="",G47>M47), M47<TODAY() ), "Vencido", "A término" ) ) -> Vencido | I47: 45649 | J47: Invoice 532 | K47: MORENO OCAMPO | M47: 45678 | O47: 250 | P47: =IF(ISBLANK(N47), "", VLOOKUP(D47&" "&E47, 'Info Tipo de Cambio y REM'!$A$24:$B$35, 2, FALSE)) | Q47: =IF(NOT(ISBLANK(N47)), N47 / P47, IF(NOT(ISBLANK(O47)), O47, "")) -> 250
A48: Clientes a cobrar | B48: =IF( A48="", "", IF( OR(A48="Santander-Galicia-Nación", A48="Bank Of America", A48="Transferwise", A48="Custodia Socios", A48="Cheques en cartera", A48="Caja"), "Activo Liquido", IF( OR(A48="Otras Inversiones", A48="Santander Inversiones"), "Mediano Plazo", IF( A48="Clientes a cobrar", "Clientes a cobrar", "DATO NO CARGADO" ) ) ) ) -> Clientes a cobrar | C48: =IF(K48="", "", IFERROR(VLOOKUP(K48, Clasificaciones!D:E, 2, FALSE), "DATO NO CARGADO")) -> Coelsa | D48: 04 abr | E48: 2025 | H48: =IF( A48="", "", IF( AND( F48="No", OR(G48="",G48>M48), M48<TODAY() ), "Vencido", "A término" ) ) -> A término | I48: 45748 | J48: Factura de Crédito MiPyME (FCE) N° A-00008-00000938 | K48: COMPENSADORA ELECTRONICA SA | M48: 45778 | N48: 4832747 | P48: =IF(ISBLANK(N48), "", VLOOKUP(D48&" "&E48, 'Info Tipo de Cambio y REM'!$A$24:$B$35, 2, FALSE)) -> 1185 | Q48: =IF(NOT(ISBLANK(N48)), N48 / P48, IF(NOT(ISBLANK(O48)), O48, "")) -> 4078.2675
A49: Clientes a cobrar | B49: =IF( A49="", "", IF( OR(A49="Santander-Galicia-Nación", A49="Bank Of America", A49="Transferwise", A49="Custodia Socios", A49="Cheques en cartera", A49="Caja"), "Activo Liquido", IF( OR(A49="Otras Inversiones", A49="Santander Inversiones"), "Mediano Plazo", IF( A49="Clientes a cobrar", "Clientes a cobrar", "DATO NO CARGADO" ) ) ) ) -> Clientes a cobrar | C49: =IF(K49="", "", IFERROR(VLOOKUP(K49, Clasificaciones!D:E, 2, FALSE), "DATO NO CARGADO")) -> Coca-Cola | D49: 04 abr | E49: 2025 | F49: No | H49: =IF( A49="", "", IF( AND( F49="No", OR(G49="",G49>M49), M49<TODAY() ), "Vencido", "A término" ) ) -> Vencido | I49: 45775 | J49: Invoice 576 | K49: SERVICIOS INTEGRADOS DE ADMINISTRACION Y ALTA GER | M49: 45860 | O49: 5568 | P49: =IF(ISBLANK(N49), "", VLOOKUP(D49&" "&E49, 'Info Tipo de Cambio y REM'!$A$24:$B$35, 2, FALSE)) | Q49: =IF(NOT(ISBLANK(N49)), N49 / P49, IF(NOT(ISBLANK(O49)), O49, "")) -> 5568
A50: Clientes a cobrar | B50: =IF( A50="", "", IF( OR(A50="Santander-Galicia-Nación", A50="Bank Of America", A50="Transferwise", A50="Custodia Socios", A50="Cheques en cartera", A50="Caja"), "Activo Liquido", IF( OR(A50="Otras Inversiones", A50="Santander Inversiones"), "Mediano Plazo", IF( A50="Clientes a cobrar", "Clientes a cobrar", "DATO NO CARGADO" ) ) ) ) -> Clientes a cobrar | C50: =IF(K50="", "", IFERROR(VLOOKUP(K50, Clasificaciones!D:E, 2, FALSE), "DATO NO CARGADO")) -> Play Digital S.A (Modo) | D50: 05 may | E50: 2025 | F50: No | G50: 45811 | H50: =IF( A50="", "", IF( AND( F50="No", OR(G50="",G50>M50), M50<TODAY() ), "Vencido", "A término" ) ) -> A término | I50: 45782 | J50: A-00008-00001966 | K50: PLAY DIGITAL S. A. | M50: 45813 | N50: 5095279.7 | P50: =IF(ISBLANK(N50), "", VLOOKUP(D50&" "&E50, 'Info Tipo de Cambio y REM'!$A$24:$B$35, 2, FALSE)) -> 1180 | Q50: =IF(NOT(ISBLANK(N50)), N50 / P50, IF(NOT(ISBLANK(O50)), O50, "")) -> 4318.0336
A51: Clientes a cobrar | B51: =IF( A51="", "", IF( OR(A51="Santander-Galicia-Nación", A51="Bank Of America", A51="Transferwise", A51="Custodia Socios", A51="Cheques en cartera", A51="Caja"), "Activo Liquido", IF( OR(A51="Otras Inversiones", A51="Santander Inversiones"), "Mediano Plazo", IF( A51="Clientes a cobrar", "Clientes a cobrar", "DATO NO CARGADO" ) ) ) ) -> Clientes a cobrar | C51: =IF(K51="", "", IFERROR(VLOOKUP(K51, Clasificaciones!D:E, 2, FALSE), "DATO NO CARGADO")) -> Coelsa | D51: 05 may | E51: 2025 | F51: Si | H51: =IF( A51="", "", IF( AND( F51="No", OR(G51="",G51>M51), M51<TODAY() ), "Vencido", "A término" ) ) -> A término | I51: 45782 | J51: A-00008-00000951 | K51: COMPENSADORA ELECTRONICA SA | M51: 45813 | N51: 4832747.2 | P51: =IF(ISBLANK(N51), "", VLOOKUP(D51&" "&E51, 'Info Tipo de Cambio y REM'!$A$24:$B$35, 2, FALSE)) -> 1180 | Q51: =IF(NOT(ISBLANK(N51)), N51 / P51, IF(NOT(ISBLANK(O51)), O51, "")) -> 4095.5485
A52: Clientes a cobrar | B52: =IF( A52="", "", IF( OR(A52="Santander-Galicia-Nación", A52="Bank Of America", A52="Transferwise", A52="Custodia Socios", A52="Cheques en cartera", A52="Caja"), "Activo Liquido", IF( OR(A52="Otras Inversiones", A52="Santander Inversiones"), "Mediano Plazo", IF( A52="Clientes a cobrar", "Clientes a cobrar", "DATO NO CARGADO" ) ) ) ) -> Clientes a cobrar | C52: =IF(K52="", "", IFERROR(VLOOKUP(K52, Clasificaciones!D:E, 2, FALSE), "DATO NO CARGADO")) -> Vertical Media | D52: 05 may | E52: 2025 | F52: Si | H52: =IF( A52="", "", IF( AND( F52="No", OR(G52="",G52>M52), M52<TODAY() ), "Vencido", "A término" ) ) -> A término | I52: 45782 | J52: INVOICE 582 | K52: VERTICAL MEDIA LLC | M52: 45814 | O52: 1750 | P52: =IF(ISBLANK(N52), "", VLOOKUP(D52&" "&E52, 'Info Tipo de Cambio y REM'!$A$24:$B$35, 2, FALSE)) | Q52: =IF(NOT(ISBLANK(N52)), N52 / P52, IF(NOT(ISBLANK(O52)), O52, "")) -> 1750
A53: Clientes a cobrar | B53: =IF( A53="", "", IF( OR(A53="Santander-Galicia-Nación", A53="Bank Of America", A53="Transferwise", A53="Custodia Socios", A53="Cheques en cartera", A53="Caja"), "Activo Liquido", IF( OR(A53="Otras Inversiones", A53="Santander Inversiones"), "Mediano Plazo", IF( A53="Clientes a cobrar", "Clientes a cobrar", "DATO NO CARGADO" ) ) ) ) -> Clientes a cobrar | C53: =IF(K53="", "", IFERROR(VLOOKUP(K53, Clasificaciones!D:E, 2, FALSE), "DATO NO CARGADO")) -> Detroit | D53: 05 may | E53: 2025 | F53: Si | H53: =IF( A53="", "", IF( AND( F53="No", OR(G53="",G53>M53), M53<TODAY() ), "Vencido", "A término" ) ) -> A término | I53: 45779 | J53: FEE MAYO | K53: DETROIT | M53: 45809 | N53: 771250 | P53: =IF(ISBLANK(N53), "", VLOOKUP(D53&" "&E53, 'Info Tipo de Cambio y REM'!$A$24:$B$35, 2, FALSE)) -> 1180 | Q53: =IF(NOT(ISBLANK(N53)), N53 / P53, IF(NOT(ISBLANK(O53)), O53, "")) -> 653.60169
A54: Santander-Galicia-Nación | B54: =IF( A54="", "", IF( OR(A54="Santander-Galicia-Nación", A54="Bank Of America", A54="Transferwise", A54="Custodia Socios", A54="Cheques en cartera", A54="Caja"), "Activo Liquido", IF( OR(A54="Otras Inversiones", A54="Santander Inversiones"), "Mediano Plazo", IF( A54="Clientes a cobrar", "Clientes a cobrar", "DATO NO CARGADO" ) ) ) ) -> Activo Liquido | C54: =IF(K54="", "", IFERROR(VLOOKUP(K54, Clasificaciones!D:E, 2, FALSE), "DATO NO CARGADO")) | D54: 05 may | E54: 2025 | H54: =IF( A54="", "", IF( AND( F54="No", OR(G54="",G54>M54), M54<TODAY() ), "Vencido", "A término" ) ) -> A término | N54: 7822062 | P54: =IF(ISBLANK(N54), "", VLOOKUP(D54&" "&E54, 'Info Tipo de Cambio y REM'!$A$24:$B$35, 2, FALSE)) -> 1180 | Q54: =IF(NOT(ISBLANK(N54)), N54 / P54, IF(NOT(ISBLANK(O54)), O54, "")) -> 6628.8661
A55: Bank Of America | B55: =IF( A55="", "", IF( OR(A55="Santander-Galicia-Nación", A55="Bank Of America", A55="Transferwise", A55="Custodia Socios", A55="Cheques en cartera", A55="Caja"), "Activo Liquido", IF( OR(A55="Otras Inversiones", A55="Santander Inversiones"), "Mediano Plazo", IF( A55="Clientes a cobrar", "Clientes a cobrar", "DATO NO CARGADO" ) ) ) ) -> Activo Liquido | C55: =IF(K55="", "", IFERROR(VLOOKUP(K55, Clasificaciones!D:E, 2, FALSE), "DATO NO CARGADO")) | D55: 05 may | E55: 2025 | H55: =IF( A55="", "", IF( AND( F55="No", OR(G55="",G55>M55), M55<TODAY() ), "Vencido", "A término" ) ) -> A término | O55: -49062 | P55: =IF(ISBLANK(N55), "", VLOOKUP(D55&" "&E55, 'Info Tipo de Cambio y REM'!$A$24:$B$35, 2, FALSE)) | Q55: =IF(NOT(ISBLANK(N55)), N55 / P55, IF(NOT(ISBLANK(O55)), O55, "")) -> -49062
A56: Otras Inversiones | B56: =IF( A56="", "", IF( OR(A56="Santander-Galicia-Nación", A56="Bank Of America", A56="Transferwise", A56="Custodia Socios", A56="Cheques en cartera", A56="Caja"), "Activo Liquido", IF( OR(A56="Otras Inversiones", A56="Santander Inversiones"), "Mediano Plazo", IF( A56="Clientes a cobrar", "Clientes a cobrar", "DATO NO CARGADO" ) ) ) ) -> Mediano Plazo | C56: =IF(K56="", "", IFERROR(VLOOKUP(K56, Clasificaciones!D:E, 2, FALSE), "DATO NO CARGADO")) | D56: 05 may | E56: 2025 | H56: =IF( A56="", "", IF( AND( F56="No", OR(G56="",G56>M56), M56<TODAY() ), "Vencido", "A término" ) ) -> A término | O56: 2682 | P56: =IF(ISBLANK(N56), "", VLOOKUP(D56&" "&E56, 'Info Tipo de Cambio y REM'!$A$24:$B$35, 2, FALSE)) | Q56: =IF(NOT(ISBLANK(N56)), N56 / P56, IF(NOT(ISBLANK(O56)), O56, "")) -> 2682
A57: Clientes a cobrar | B57: =IF( A57="", "", IF( OR(A57="Santander-Galicia-Nación", A57="Bank Of America", A57="Transferwise", A57="Custodia Socios", A57="Cheques en cartera", A57="Caja"), "Activo Liquido", IF( OR(A57="Otras Inversiones", A57="Santander Inversiones"), "Mediano Plazo", IF( A57="Clientes a cobrar", "Clientes a cobrar", "DATO NO CARGADO" ) ) ) ) -> Clientes a cobrar | C57: =IF(K57="", "", IFERROR(VLOOKUP(K57, Clasificaciones!D:E, 2, FALSE), "DATO NO CARGADO")) -> Play Digital S.A (Modo) | D57: 06 jun | E57: 2025 | F57: No | G57: 45846 | H57: =IF( A57="", "", IF( AND( F57="No", OR(G57="",G57>M57), M57<TODAY() ), "Vencido", "A término" ) ) -> Vencido | I57: 45810 | J57: A-00008-00001977 | K57: PLAY DIGITAL S. A. | M57: 45840 | N57: 5562007 | P57: =IF(ISBLANK(N57), "", VLOOKUP(D57&" "&E57, 'Info Tipo de Cambio y REM'!$A$24:$B$35, 2, FALSE)) -> 1215 | Q57: =IF(NOT(ISBLANK(N57)), N57 / P57, IF(NOT(ISBLANK(O57)), O57, "")) -> 4577.7835
A58: Clientes a cobrar | B58: =IF( A58="", "", IF( OR(A58="Santander-Galicia-Nación", A58="Bank Of America", A58="Transferwise", A58="Custodia Socios", A58="Cheques en cartera", A58="Caja"), "Activo Liquido", IF( OR(A58="Otras Inversiones", A58="Santander Inversiones"), "Mediano Plazo", IF( A58="Clientes a cobrar", "Clientes a cobrar", "DATO NO CARGADO" ) ) ) ) -> Clientes a cobrar | C58: =IF(K58="", "", IFERROR(VLOOKUP(K58, Clasificaciones!D:E, 2, FALSE), "DATO NO CARGADO")) -> Coelsa | D58: 06 jun | E58: 2025 | F58: Si | H58: =IF( A58="", "", IF( AND( F58="No", OR(G58="",G58>M58), M58<TODAY() ), "Vencido", "A término" ) ) -> A término | I58: 45810 | J58: A-00008-00000958 | K58: COMPENSADORA ELECTRONICA SA | M58: 45840 | N58: 5275425.8 | P58: =IF(ISBLANK(N58), "", VLOOKUP(D58&" "&E58, 'Info Tipo de Cambio y REM'!$A$24:$B$35, 2, FALSE)) -> 1215 | Q58: =IF(NOT(ISBLANK(N58)), N58 / P58, IF(NOT(ISBLANK(O58)), O58, "")) -> 4341.9142
A59: Clientes a cobrar | B59: =IF( A59="", "", IF( OR(A59="Santander-Galicia-Nación", A59="Bank Of America", A59="Transferwise", A59="Custodia Socios", A59="Cheques en cartera", A59="Caja"), "Activo Liquido", IF( OR(A59="Otras Inversiones", A59="Santander Inversiones"), "Mediano Plazo", IF( A59="Clientes a cobrar", "Clientes a cobrar", "DATO NO CARGADO" ) ) ) ) -> Clientes a cobrar | C59: =IF(K59="", "", IFERROR(VLOOKUP(K59, Clasificaciones!D:E, 2, FALSE), "DATO NO CARGADO")) -> Detroit | D59: 06 jun | E59: 2025 | F59: Si | H59: =IF( A59="", "", IF( AND( F59="No", OR(G59="",G59>M59), M59<TODAY() ), "Vencido", "A término" ) ) -> A término | I59: 45810 | J59: FEE JUNIO | K59: DETROIT | M59: 45840 | N59: 1071885 | P59: =IF(ISBLANK(N59), "", VLOOKUP(D59&" "&E59, 'Info Tipo de Cambio y REM'!$A$24:$B$35, 2, FALSE)) -> 1215 | Q59: =IF(NOT(ISBLANK(N59)), N59 / P59, IF(NOT(ISBLANK(O59)), O59, "")) -> 882.20988
A60: Clientes a cobrar | B60: =IF( A60="", "", IF( OR(A60="Santander-Galicia-Nación", A60="Bank Of America", A60="Transferwise", A60="Custodia Socios", A60="Cheques en cartera", A60="Caja"), "Activo Liquido", IF( OR(A60="Otras Inversiones", A60="Santander Inversiones"), "Mediano Plazo", IF( A60="Clientes a cobrar", "Clientes a cobrar", "DATO NO CARGADO" ) ) ) ) -> Clientes a cobrar | C60: =IF(K60="", "", IFERROR(VLOOKUP(K60, Clasificaciones!D:E, 2, FALSE), "DATO NO CARGADO")) -> Vertical Media | D60: 06 jun | E60: 2025 | F60: Si | H60: =IF( A60="", "", IF( AND( F60="No", OR(G60="",G60>M60), M60<TODAY() ), "Vencido", "A término" ) ) -> A término | I60: 45810 | J60: INVOICE 590 | K60: VERTICAL MEDIA LLC | M60: 45840 | O60: 1750 | P60: =IF(ISBLANK(N60), "", VLOOKUP(D60&" "&E60, 'Info Tipo de Cambio y REM'!$A$24:$B$35, 2, FALSE)) | Q60: =IF(NOT(ISBLANK(N60)), N60 / P60, IF(NOT(ISBLANK(O60)), O60, "")) -> 1750
A61: Clientes a cobrar | B61: =IF( A61="", "", IF( OR(A61="Santander-Galicia-Nación", A61="Bank Of America", A61="Transferwise", A61="Custodia Socios", A61="Cheques en cartera", A61="Caja"), "Activo Liquido", IF( OR(A61="Otras Inversiones", A61="Santander Inversiones"), "Mediano Plazo", IF( A61="Clientes a cobrar", "Clientes a cobrar", "DATO NO CARGADO" ) ) ) ) -> Clientes a cobrar | C61: =IF(K61="", "", IFERROR(VLOOKUP(K61, Clasificaciones!D:E, 2, FALSE), "DATO NO CARGADO")) -> Uber | D61: 06 jun | E61: 2025 | F61: No | G61: 45884 | H61: =IF( A61="", "", IF( AND( F61="No", OR(G61="",G61>M61), M61<TODAY() ), "Vencido", "A término" ) ) -> A término | I61: 45827 | J61: INVOICE 595 | K61: UBER | M61: 45888 | O61: 7350 | P61: =IF(ISBLANK(N61), "", VLOOKUP(D61&" "&E61, 'Info Tipo de Cambio y REM'!$A$24:$B$35, 2, FALSE)) | Q61: =IF(NOT(ISBLANK(N61)), N61 / P61, IF(NOT(ISBLANK(O61)), O61, "")) -> 7350
A62: Clientes a cobrar | B62: =IF( A62="", "", IF( OR(A62="Santander-Galicia-Nación", A62="Bank Of America", A62="Transferwise", A62="Custodia Socios", A62="Cheques en cartera", A62="Caja"), "Activo Liquido", IF( OR(A62="Otras Inversiones", A62="Santander Inversiones"), "Mediano Plazo", IF( A62="Clientes a cobrar", "Clientes a cobrar", "DATO NO CARGADO" ) ) ) ) -> Clientes a cobrar | C62: =IF(K62="", "", IFERROR(VLOOKUP(K62, Clasificaciones!D:E, 2, FALSE), "DATO NO CARGADO")) -> Detroit | D62: 06 jun | E62: 2025 | F62: Si | H62: =IF( A62="", "", IF( AND( F62="No", OR(G62="",G62>M62), M62<TODAY() ), "Vencido", "A término" ) ) -> A término | I62: 45838 | J62: NOTA DE CREDITO | K62: DETROIT | M62: 45838 | N62: -20734 | P62: =IF(ISBLANK(N62), "", VLOOKUP(D62&" "&E62, 'Info Tipo de Cambio y REM'!$A$24:$B$35, 2, FALSE)) -> 1215 | Q62: =IF(NOT(ISBLANK(N62)), N62 / P62, IF(NOT(ISBLANK(O62)), O62, "")) -> -17.065021
A63: Bank Of America | B63: =IF( A63="", "", IF( OR(A63="Santander-Galicia-Nación", A63="Bank Of America", A63="Transferwise", A63="Custodia Socios", A63="Cheques en cartera", A63="Caja"), "Activo Liquido", IF( OR(A63="Otras Inversiones", A63="Santander Inversiones"), "Mediano Plazo", IF( A63="Clientes a cobrar", "Clientes a cobrar", "DATO NO CARGADO" ) ) ) ) -> Activo Liquido | C63: =IF(K63="", "", IFERROR(VLOOKUP(K63, Clasificaciones!D:E, 2, FALSE), "DATO NO CARGADO")) | D63: 06 jun | E63: 2025 | H63: =IF( A63="", "", IF( AND( F63="No", OR(G63="",G63>M63), M63<TODAY() ), "Vencido", "A término" ) ) -> A término | O63: -91979 | P63: =IF(ISBLANK(N63), "", VLOOKUP(D63&" "&E63, 'Info Tipo de Cambio y REM'!$A$24:$B$35, 2, FALSE)) | Q63: =IF(NOT(ISBLANK(N63)), N63 / P63, IF(NOT(ISBLANK(O63)), O63, "")) -> -91979
A64: Santander-Galicia-Nación | B64: =IF( A64="", "", IF( OR(A64="Santander-Galicia-Nación", A64="Bank Of America", A64="Transferwise", A64="Custodia Socios", A64="Cheques en cartera", A64="Caja"), "Activo Liquido", IF( OR(A64="Otras Inversiones", A64="Santander Inversiones"), "Mediano Plazo", IF( A64="Clientes a cobrar", "Clientes a cobrar", "DATO NO CARGADO" ) ) ) ) -> Activo Liquido | C64: =IF(K64="", "", IFERROR(VLOOKUP(K64, Clasificaciones!D:E, 2, FALSE), "DATO NO CARGADO")) | D64: 06 jun | E64: 2025 | H64: =IF( A64="", "", IF( AND( F64="No", OR(G64="",G64>M64), M64<TODAY() ), "Vencido", "A término" ) ) -> A término | N64: 3432410 | P64: =IF(ISBLANK(N64), "", VLOOKUP(D64&" "&E64, 'Info Tipo de Cambio y REM'!$A$24:$B$35, 2, FALSE)) -> 1215 | Q64: =IF(NOT(ISBLANK(N64)), N64 / P64, IF(NOT(ISBLANK(O64)), O64, "")) -> 2825.0288
A65: Otras Inversiones | B65: =IF( A65="", "", IF( OR(A65="Santander-Galicia-Nación", A65="Bank Of America", A65="Transferwise", A65="Custodia Socios", A65="Cheques en cartera", A65="Caja"), "Activo Liquido", IF( OR(A65="Otras Inversiones", A65="Santander Inversiones"), "Mediano Plazo", IF( A65="Clientes a cobrar", "Clientes a cobrar", "DATO NO CARGADO" ) ) ) ) -> Mediano Plazo | C65: =IF(K65="", "", IFERROR(VLOOKUP(K65, Clasificaciones!D:E, 2, FALSE), "DATO NO CARGADO")) | D65: 06 jun | E65: 2025 | H65: =IF( A65="", "", IF( AND( F65="No", OR(G65="",G65>M65), M65<TODAY() ), "Vencido", "A término" ) ) -> A término | O65: 2682 | P65: =IF(ISBLANK(N65), "", VLOOKUP(D65&" "&E65, 'Info Tipo de Cambio y REM'!$A$24:$B$35, 2, FALSE)) | Q65: =IF(NOT(ISBLANK(N65)), N65 / P65, IF(NOT(ISBLANK(O65)), O65, "")) -> 2682
A66: Transferwise | B66: =IF( A66="", "", IF( OR(A66="Santander-Galicia-Nación", A66="Bank Of America", A66="Transferwise", A66="Custodia Socios", A66="Cheques en cartera", A66="Caja"), "Activo Liquido", IF( OR(A66="Otras Inversiones", A66="Santander Inversiones"), "Mediano Plazo", IF( A66="Clientes a cobrar", "Clientes a cobrar", "DATO NO CARGADO" ) ) ) ) -> Activo Liquido | C66: =IF(K66="", "", IFERROR(VLOOKUP(K66, Clasificaciones!D:E, 2, FALSE), "DATO NO CARGADO")) | D66: 06 jun | E66: 2025 | H66: =IF( A66="", "", IF( AND( F66="No", OR(G66="",G66>M66), M66<TODAY() ), "Vencido", "A término" ) ) -> A término | O66: 230 | P66: =IF(ISBLANK(N66), "", VLOOKUP(D66&" "&E66, 'Info Tipo de Cambio y REM'!$A$24:$B$35, 2, FALSE)) | Q66: =IF(NOT(ISBLANK(N66)), N66 / P66, IF(NOT(ISBLANK(O66)), O66, "")) -> 230
A67: Clientes a cobrar | B67: =IF( A67="", "", IF( OR(A67="Santander-Galicia-Nación", A67="Bank Of America", A67="Transferwise", A67="Custodia Socios", A67="Cheques en cartera", A67="Caja"), "Activo Liquido", IF( OR(A67="Otras Inversiones", A67="Santander Inversiones"), "Mediano Plazo", IF( A67="Clientes a cobrar", "Clientes a cobrar", "DATO NO CARGADO" ) ) ) ) -> Clientes a cobrar | C67: Coelsa | D67: 07 jul | E67: 2025 | F67: Si | G67: 45863 | H67: =IF( A67="", "", IF( AND( F67="No", OR(G67="",G67>M67), M67<TODAY() ), "Vencido", "A término" ) ) -> A término | I67: 45839 | J67: A-00008-00000966 | K67: COMPENSADORA ELECTRONICA SA | M67: 45870 | N67: 5275425.8 | P67: =IF(ISBLANK(N67), "", VLOOKUP(D67&" "&E67, 'Info Tipo de Cambio y REM'!$A$24:$B$35, 2, FALSE)) -> 1320 | Q67: =IF(NOT(ISBLANK(N67)), N67 / P67, IF(NOT(ISBLANK(O67)), O67, "")) -> 3996.5347
A68: Clientes a cobrar | B68: =IF( A68="", "", IF( OR(A68="Santander-Galicia-Nación", A68="Bank Of America", A68="Transferwise", A68="Custodia Socios", A68="Cheques en cartera", A68="Caja"), "Activo Liquido", IF( OR(A68="Otras Inversiones", A68="Santander Inversiones"), "Mediano Plazo", IF( A68="Clientes a cobrar", "Clientes a cobrar", "DATO NO CARGADO" ) ) ) ) -> Clientes a cobrar | C68: =IF(K68="", "", IFERROR(VLOOKUP(K68, Clasificaciones!D:E, 2, FALSE), "DATO NO CARGADO")) -> Kimberly Clark | D68: 07 jul | E68: 2025 | F68: No | H68: =IF( A68="", "", IF( AND( F68="No", OR(G68="",G68>M68), M68<TODAY() ), "Vencido", "A término" ) ) -> A término | I68: 45845 | J68: INVOICE 608 | K68: KIMBERLY | M68: =I68+120 -> 45965 | O68: 8450 | P68: =IF(ISBLANK(N68), "", VLOOKUP(D68&" "&E68, 'Info Tipo de Cambio y REM'!$A$24:$B$35, 2, FALSE)) | Q68: =IF(NOT(ISBLANK(N68)), N68 / P68, IF(NOT(ISBLANK(O68)), O68, "")) -> 8450
A69: Clientes a cobrar | B69: =IF( A69="", "", IF( OR(A69="Santander-Galicia-Nación", A69="Bank Of America", A69="Transferwise", A69="Custodia Socios", A69="Cheques en cartera", A69="Caja"), "Activo Liquido", IF( OR(A69="Otras Inversiones", A69="Santander Inversiones"), "Mediano Plazo", IF( A69="Clientes a cobrar", "Clientes a cobrar", "DATO NO CARGADO" ) ) ) ) -> Clientes a cobrar | C69: =IF(K69="", "", IFERROR(VLOOKUP(K69, Clasificaciones!D:E, 2, FALSE), "DATO NO CARGADO")) -> Play Digital S.A (Modo) | D69: 07 jul | E69: 2025 | F69: No | G69: 45876 | H69: =IF( A69="", "", IF( AND( F69="No", OR(G69="",G69>M69), M69<TODAY() ), "Vencido", "A término" ) ) -> Vencido | I69: 45839 | J69: Factura de Venta N° A-00008-00001995 | K69: PLAY DIGITAL S. A. | M69: 45870 | N69: 5562007 | P69: =IF(ISBLANK(N69), "", VLOOKUP(D69&" "&E69, 'Info Tipo de Cambio y REM'!$A$24:$B$35, 2, FALSE)) -> 1320 | Q69: =IF(NOT(ISBLANK(N69)), N69 / P69, IF(NOT(ISBLANK(O69)), O69, "")) -> 4213.6417
A70: Clientes a cobrar | B70: =IF( A70="", "", IF( OR(A70="Santander-Galicia-Nación", A70="Bank Of America", A70="Transferwise", A70="Custodia Socios", A70="Cheques en cartera", A70="Caja"), "Activo Liquido", IF( OR(A70="Otras Inversiones", A70="Santander Inversiones"), "Mediano Plazo", IF( A70="Clientes a cobrar", "Clientes a cobrar", "DATO NO CARGADO" ) ) ) ) -> Clientes a cobrar | C70: =IF(K70="", "", IFERROR(VLOOKUP(K70, Clasificaciones!D:E, 2, FALSE), "DATO NO CARGADO")) -> Detroit | D70: 07 jul | E70: 2025 | F70: Si | H70: =IF( A70="", "", IF( AND( F70="No", OR(G70="",G70>M70), M70<TODAY() ), "Vencido", "A término" ) ) -> A término | I70: 45846 | J70: diseño por los tres mails | K70: DETROIT | M70: 45869 | N70: 130000 | P70: =IF(ISBLANK(N70), "", VLOOKUP(D70&" "&E70, 'Info Tipo de Cambio y REM'!$A$24:$B$35, 2, FALSE)) -> 1320 | Q70: =IF(NOT(ISBLANK(N70)), N70 / P70, IF(NOT(ISBLANK(O70)), O70, "")) -> 98.484848
A71: Clientes a cobrar | B71: =IF( A71="", "", IF( OR(A71="Santander-Galicia-Nación", A71="Bank Of America", A71="Transferwise", A71="Custodia Socios", A71="Cheques en cartera", A71="Caja"), "Activo Liquido", IF( OR(A71="Otras Inversiones", A71="Santander Inversiones"), "Mediano Plazo", IF( A71="Clientes a cobrar", "Clientes a cobrar", "DATO NO CARGADO" ) ) ) ) -> Clientes a cobrar | C71: =IF(K71="", "", IFERROR(VLOOKUP(K71, Clasificaciones!D:E, 2, FALSE), "DATO NO CARGADO")) -> Detroit | D71: 07 jul | E71: 2025 | F71: Si | H71: =IF( A71="", "", IF( AND( F71="No", OR(G71="",G71>M71), M71<TODAY() ), "Vencido", "A término" ) ) -> A término | I71: 45846 | J71: FEE MES DE JULIO | K71: DETROIT | M71: 45870 | N71: 1071885 | P71: =IF(ISBLANK(N71), "", VLOOKUP(D71&" "&E71, 'Info Tipo de Cambio y REM'!$A$24:$B$35, 2, FALSE)) -> 1320 | Q71: =IF(NOT(ISBLANK(N71)), N71 / P71, IF(NOT(ISBLANK(O71)), O71, "")) -> 812.03409
A72: Clientes a cobrar | B72: =IF( A72="", "", IF( OR(A72="Santander-Galicia-Nación", A72="Bank Of America", A72="Transferwise", A72="Custodia Socios", A72="Cheques en cartera", A72="Caja"), "Activo Liquido", IF( OR(A72="Otras Inversiones", A72="Santander Inversiones"), "Mediano Plazo", IF( A72="Clientes a cobrar", "Clientes a cobrar", "DATO NO CARGADO" ) ) ) ) -> Clientes a cobrar | C72: =IF(K72="", "", IFERROR(VLOOKUP(K72, Clasificaciones!D:E, 2, FALSE), "DATO NO CARGADO")) -> Animal Studio | D72: 07 jul | E72: 2025 | F72: No | G72: 45870 | H72: =IF( A72="", "", IF( AND( F72="No", OR(G72="",G72>M72), M72<TODAY() ), "Vencido", "A término" ) ) -> A término | I72: 45856 | J72: Factura de Venta N° A-00008-00002002 | K72: ANIMAL STUDIO S.R.L. | M72: 45887 | N72: 1052700 | P72: =IF(ISBLANK(N72), "", VLOOKUP(D72&" "&E72, 'Info Tipo de Cambio y REM'!$A$24:$B$35, 2, FALSE)) -> 1320 | Q72: =IF(NOT(ISBLANK(N72)), N72 / P72, IF(NOT(ISBLANK(O72)), O72, "")) -> 797.5
A73: Clientes a cobrar | B73: Clientes a cobrar | C73: Detroit | D73: 07 jul | E73: 2025 | F73: No | G73: 45897 | H73: =IF( A73="", "", IF( AND( F73="No", OR(G73="",G73>M73), M73<TODAY() ), "Vencido", "A término" ) ) -> Vencido | I73: 45839 | J73: SALDO | K73: DETROIT | L73: ESTO NO VA | M73: 45870 | N73: 364995 | P73: =IF(ISBLANK(N73), "", VLOOKUP(D73&" "&E73, 'Info Tipo de Cambio y REM'!$A$24:$B$35, 2, FALSE)) -> 1320 | Q73: =IF(NOT(ISBLANK(N73)), N73 / P73, IF(NOT(ISBLANK(O73)), O73, "")) -> 276.51136
A74: Santander-Galicia-Nación | B74: =IF( A74="", "", IF( OR(A74="Santander-Galicia-Nación", A74="Bank Of America", A74="Transferwise", A74="Custodia Socios", A74="Cheques en cartera", A74="Caja"), "Activo Liquido", IF( OR(A74="Otras Inversiones", A74="Santander Inversiones"), "Mediano Plazo", IF( A74="Clientes a cobrar", "Clientes a cobrar", "DATO NO CARGADO" ) ) ) ) -> Activo Liquido | C74: =IF(K74="", "", IFERROR(VLOOKUP(K74, Clasificaciones!D:E, 2, FALSE), "DATO NO CARGADO")) | D74: 07 jul | E74: 2025 | H74: =IF( A74="", "", IF( AND( F74="No", OR(G74="",G74>M74), M74<TODAY() ), "Vencido", "A término" ) ) -> A término | N74: -579983 | P74: =IF(ISBLANK(N74), "", VLOOKUP(D74&" "&E74, 'Info Tipo de Cambio y REM'!$A$24:$B$35, 2, FALSE)) -> 1320 | Q74: =IF(NOT(ISBLANK(N74)), N74 / P74, IF(NOT(ISBLANK(O74)), O74, "")) -> -439.38106
A75: Bank Of America | B75: =IF( A75="", "", IF( OR(A75="Santander-Galicia-Nación", A75="Bank Of America", A75="Transferwise", A75="Custodia Socios", A75="Cheques en cartera", A75="Caja"), "Activo Liquido", IF( OR(A75="Otras Inversiones", A75="Santander Inversiones"), "Mediano Plazo", IF( A75="Clientes a cobrar", "Clientes a cobrar", "DATO NO CARGADO" ) ) ) ) -> Activo Liquido | C75: =IF(K75="", "", IFERROR(VLOOKUP(K75, Clasificaciones!D:E, 2, FALSE), "DATO NO CARGADO")) | D75: 07 jul | E75: 2025 | H75: =IF( A75="", "", IF( AND( F75="No", OR(G75="",G75>M75), M75<TODAY() ), "Vencido", "A término" ) ) -> A término | O75: -68302 | P75: =IF(ISBLANK(N75), "", VLOOKUP(D75&" "&E75, 'Info Tipo de Cambio y REM'!$A$24:$B$35, 2, FALSE)) | Q75: =IF(NOT(ISBLANK(N75)), N75 / P75, IF(NOT(ISBLANK(O75)), O75, "")) -> -68302
A76: Transferwise | B76: =IF( A76="", "", IF( OR(A76="Santander-Galicia-Nación", A76="Bank Of America", A76="Transferwise", A76="Custodia Socios", A76="Cheques en cartera", A76="Caja"), "Activo Liquido", IF( OR(A76="Otras Inversiones", A76="Santander Inversiones"), "Mediano Plazo", IF( A76="Clientes a cobrar", "Clientes a cobrar", "DATO NO CARGADO" ) ) ) ) -> Activo Liquido | C76: =IF(K76="", "", IFERROR(VLOOKUP(K76, Clasificaciones!D:E, 2, FALSE), "DATO NO CARGADO")) | D76: 07 jul | E76: 2025 | H76: =IF( A76="", "", IF( AND( F76="No", OR(G76="",G76>M76), M76<TODAY() ), "Vencido", "A término" ) ) -> A término | O76: 230 | P76: =IF(ISBLANK(N76), "", VLOOKUP(D76&" "&E76, 'Info Tipo de Cambio y REM'!$A$24:$B$35, 2, FALSE)) | Q76: =IF(NOT(ISBLANK(N76)), N76 / P76, IF(NOT(ISBLANK(O76)), O76, "")) -> 230
A77: Otras Inversiones | B77: =IF( A77="", "", IF( OR(A77="Santander-Galicia-Nación", A77="Bank Of America", A77="Transferwise", A77="Custodia Socios", A77="Cheques en cartera", A77="Caja"), "Activo Liquido", IF( OR(A77="Otras Inversiones", A77="Santander Inversiones"), "Mediano Plazo", IF( A77="Clientes a cobrar", "Clientes a cobrar", "DATO NO CARGADO" ) ) ) ) -> Mediano Plazo | C77: =IF(K77="", "", IFERROR(VLOOKUP(K77, Clasificaciones!D:E, 2, FALSE), "DATO NO CARGADO")) | D77: 07 jul | E77: 2025 | H77: =IF( A77="", "", IF( AND( F77="No", OR(G77="",G77>M77), M77<TODAY() ), "Vencido", "A término" ) ) -> A término | O77: 2682 | P77: =IF(ISBLANK(N77), "", VLOOKUP(D77&" "&E77, 'Info Tipo de Cambio y REM'!$A$24:$B$35, 2, FALSE)) | Q77: =IF(NOT(ISBLANK(N77)), N77 / P77, IF(NOT(ISBLANK(O77)), O77, "")) -> 2682
A78: Clientes a cobrar | B78: Clientes a cobrar | C78: Coelsa | D78: 08 ago | E78: 2025 | F78: No | G78: 45904 | H78: =IF( A78="", "", IF( AND( F78="No", OR(G78="",G78>M78), M78<TODAY() ), "Vencido", "A término" ) ) -> A término | I78: 45873 | J78: Factura de Crédito MiPyME (FCE) N° A-00008-00000975 | K78: COMPENSADORA ELECTRONICA SA | M78: 45904 | N78: 5275426 | P78: =IF(ISBLANK(N78), "", VLOOKUP(D78&" "&E78, 'Info Tipo de Cambio y REM'!$A$24:$B$35, 2, FALSE)) -> 1345 | Q78: =IF(NOT(ISBLANK(N78)), N78 / P78, IF(NOT(ISBLANK(O78)), O78, "")) -> 3922.2498
A79: Clientes a cobrar | B79: Clientes a cobrar | C79: Play Digital S.A (Modo) | D79: 08 ago | E79: 2025 | F79: No | G79: 45909 | H79: =IF( A79="", "", IF( AND( F79="No", OR(G79="",G79>M79), M79<TODAY() ), "Vencido", "A término" ) ) -> Vencido | I79: 45873 | J79: Factura de Venta N° A-00008-00002010 | K79: PLAY DIGITAL S. A. | M79: 45904 | N79: 3720750 | P79: =IF(ISBLANK(N79), "", VLOOKUP(D79&" "&E79, 'Info Tipo de Cambio y REM'!$A$24:$B$35, 2, FALSE)) -> 1345 | Q79: =IF(NOT(ISBLANK(N79)), N79 / P79, IF(NOT(ISBLANK(O79)), O79, "")) -> 2766.3569
A80: Clientes a cobrar | B80: Clientes a cobrar | C80: Detroit | D80: 08 ago | E80: 2025 | F80: Si | H80: =IF( A80="", "", IF( AND( F80="No", OR(G80="",G80>M80), M80<TODAY() ), "Vencido", "A término" ) ) -> A término | I80: 45873 | J80: FEE MES DE AGOSTO | K80: DETROIT | M80: 45904 | N80: 1071885 | P80: =IF(ISBLANK(N80), "", VLOOKUP(D80&" "&E80, 'Info Tipo de Cambio y REM'!$A$24:$B$35, 2, FALSE)) -> 1345 | Q80: =IF(NOT(ISBLANK(N80)), N80 / P80, IF(NOT(ISBLANK(O80)), O80, "")) -> 796.94052
A81: Clientes a cobrar | B81: Clientes a cobrar | C81: =IF(K81="", "", IFERROR(VLOOKUP(K81, Clasificaciones!D:E, 2, FALSE), "DATO NO CARGADO")) -> Detroit | D81: 08 ago | E81: 2025 | F81: Si | H81: =IF( A81="", "", IF( AND( F81="No", OR(G81="",G81>M81), M81<TODAY() ), "Vencido", "A término" ) ) -> A término | I81: 45873 | J81: AJUSTES PAGINA WEB | K81: DETROIT | M81: 45904 | N81: 370000 | P81: =IF(ISBLANK(N81), "", VLOOKUP(D81&" "&E81, 'Info Tipo de Cambio y REM'!$A$24:$B$35, 2, FALSE)) -> 1345 | Q81: =IF(NOT(ISBLANK(N81)), N81 / P81, IF(NOT(ISBLANK(O81)), O81, "")) -> 275.09294
A82: Clientes a cobrar | B82: Clientes a cobrar | C82: Warner | D82: 08 ago | E82: 2025 | F82: Si | H82: =IF( A82="", "", IF( AND( F82="No", OR(G82="",G82>M82), M82<TODAY() ), "Vencido", "A término" ) ) -> A término | I82: 45870 | J82: INVOICE 606 | K82: WARNER | M82: 45868 | O82: 29230 | P82: =IF(ISBLANK(N82), "", VLOOKUP(D82&" "&E82, 'Info Tipo de Cambio y REM'!$A$24:$B$35, 2, FALSE)) | Q82: =IF(NOT(ISBLANK(N82)), N82 / P82, IF(NOT(ISBLANK(O82)), O82, "")) -> 29230
A83: Clientes a cobrar | B83: Clientes a cobrar | C83: Warner | D83: 08 ago | E83: 2025 | F83: Si | H83: =IF( A83="", "", IF( AND( F83="No", OR(G83="",G83>M83), M83<TODAY() ), "Vencido", "A término" ) ) -> A término | I83: 45870 | J83: INVOICE 612 | K83: WARNER | M83: 45899 | O83: 29230 | P83: =IF(ISBLANK(N83), "", VLOOKUP(D83&" "&E83, 'Info Tipo de Cambio y REM'!$A$24:$B$35, 2, FALSE)) | Q83: =IF(NOT(ISBLANK(N83)), N83 / P83, IF(NOT(ISBLANK(O83)), O83, "")) -> 29230
A84: Clientes a cobrar | B84: Clientes a cobrar | C84: Warner | D84: 08 ago | E84: 2025 | F84: No | G84: 45933 | H84: =IF( A84="", "", IF( AND( F84="No", OR(G84="",G84>M84), M84<TODAY() ), "Vencido", "A término" ) ) -> Vencido | I84: 45870 | J84: INVOICE 617 | K84: WARNER | M84: 45929 | O84: 29230 | P84: =IF(ISBLANK(N84), "", VLOOKUP(D84&" "&E84, 'Info Tipo de Cambio y REM'!$A$24:$B$35, 2, FALSE)) | Q84: =IF(NOT(ISBLANK(N84)), N84 / P84, IF(NOT(ISBLANK(O84)), O84, "")) -> 29230
A85: Clientes a cobrar | B85: Clientes a cobrar | C85: Warner | D85: 08 ago | E85: 2025 | F85: No | H85: =IF( A85="", "", IF( AND( F85="No", OR(G85="",G85>M85), M85<TODAY() ), "Vencido", "A término" ) ) -> A término | I85: 45870 | J85: INVOICE 623 | K85: WARNER | M85: 45960 | O85: 29230 | P85: =IF(ISBLANK(N85), "", VLOOKUP(D85&" "&E85, 'Info Tipo de Cambio y REM'!$A$24:$B$35, 2, FALSE)) | Q85: =IF(NOT(ISBLANK(N85)), N85 / P85, IF(NOT(ISBLANK(O85)), O85, "")) -> 29230
A86: Clientes a cobrar | B86: Clientes a cobrar | C86: Kimberly Clark | D86: 08 ago | E86: 2025 | F86: No | H86: =IF( A86="", "", IF( AND( F86="No", OR(G86="",G86>M86), M86<TODAY() ), "Vencido", "A término" ) ) -> A término | I86: 45873 | J86: INVOICE 615 | K86: KIMBERLY | M86: 45993 | O86: 8450 | P86: =IF(ISBLANK(N86), "", VLOOKUP(D86&" "&E86, 'Info Tipo de Cambio y REM'!$A$24:$B$35, 2, FALSE)) | Q86: =IF(NOT(ISBLANK(N86)), N86 / P86, IF(NOT(ISBLANK(O86)), O86, "")) -> 8450
A87: Clientes a cobrar | B87: Clientes a cobrar | C87: Kimberly Clark | D87: 08 ago | E87: 2025 | F87: No | H87: =IF( A87="", "", IF( AND( F87="No", OR(G87="",G87>M87), M87<TODAY() ), "Vencido", "A término" ) ) -> A término | I87: 45873 | J87: INVOICE 616 | K87: KIMBERLY | M87: 45993 | O87: 4224 | P87: =IF(ISBLANK(N87), "", VLOOKUP(D87&" "&E87, 'Info Tipo de Cambio y REM'!$A$24:$B$35, 2, FALSE)) | Q87: =IF(NOT(ISBLANK(N87)), N87 / P87, IF(NOT(ISBLANK(O87)), O87, "")) -> 4224
A88: Clientes a cobrar | B88: Clientes a cobrar | C88: Tortugas Open Mall | D88: 08 ago | E88: 2025 | F88: No | G88: 45919 | H88: =IF( A88="", "", IF( AND( F88="No", OR(G88="",G88>M88), M88<TODAY() ), "Vencido", "A término" ) ) -> A término | I88: 45890 | J88: Factura de Venta N° A-00008-00002018 | K88: BA MALL SAU | M88: 45921 | N88: 2026750 | P88: =IF(ISBLANK(N88), "", VLOOKUP(D88&" "&E88, 'Info Tipo de Cambio y REM'!$A$24:$B$35, 2, FALSE)) -> 1345 | Q88: =IF(NOT(ISBLANK(N88)), N88 / P88, IF(NOT(ISBLANK(O88)), O88, "")) -> 1506.8773
A89: Clientes a cobrar | B89: Clientes a cobrar | C89: Kimberly Clark | D89: 08 ago | E89: 2025 | F89: No | H89: =IF( A89="", "", IF( AND( F89="No", OR(G89="",G89>M89), M89<TODAY() ), "Vencido", "A término" ) ) -> A término | I89: 45889 | J89: INVOICE 629 | K89: KIMBERLY | M89: 46009 | O89: 4225 | P89: =IF(ISBLANK(N89), "", VLOOKUP(D89&" "&E89, 'Info Tipo de Cambio y REM'!$A$24:$B$35, 2, FALSE)) | Q89: =IF(NOT(ISBLANK(N89)), N89 / P89, IF(NOT(ISBLANK(O89)), O89, "")) -> 4225
A90: Clientes a cobrar | B90: Clientes a cobrar | C90: Moreno Ocampo | D90: 08 ago | E90: 2025 | F90: Si | H90: =IF( A90="", "", IF( AND( F90="No", OR(G90="",G90>M90), M90<TODAY() ), "Vencido", "A término" ) ) -> A término | I90: 45894 | J90: NOTA DE CREDITO | K90: MORENO OCAMPO | M90: 45894 | O90: -250 | P90: =IF(ISBLANK(N90), "", VLOOKUP(D90&" "&E90, 'Info Tipo de Cambio y REM'!$A$24:$B$35, 2, FALSE)) | Q90: =IF(NOT(ISBLANK(N90)), N90 / P90, IF(NOT(ISBLANK(O90)), O90, "")) -> -250
A91: Santander-Galicia-Nación | B91: =IF( A91="", "", IF( OR(A91="Santander-Galicia-Nación", A91="Bank Of America", A91="Transferwise", A91="Custodia Socios", A91="Cheques en cartera", A91="Caja"), "Activo Liquido", IF( OR(A91="Otras Inversiones", A91="Santander Inversiones"), "Mediano Plazo", IF( A91="Clientes a cobrar", "Clientes a cobrar", "DATO NO CARGADO" ) ) ) ) -> Activo Liquido | C91: =IF(K91="", "", IFERROR(VLOOKUP(K91, Clasificaciones!D:E, 2, FALSE), "DATO NO CARGADO")) | D91: 08 ago | E91: 2025 | H91: =IF( A91="", "", IF( AND( F91="No", OR(G91="",G91>M91), M91<TODAY() ), "Vencido", "A término" ) ) -> A término | N91: -7314769 | P91: =IF(ISBLANK(N91), "", VLOOKUP(D91&" "&E91, 'Info Tipo de Cambio y REM'!$A$24:$B$35, 2, FALSE)) -> 1345 | Q91: =IF(NOT(ISBLANK(N91)), N91 / P91, IF(NOT(ISBLANK(O91)), O91, "")) -> -5438.49
A92: Bank Of America | B92: =IF( A92="", "", IF( OR(A92="Santander-Galicia-Nación", A92="Bank Of America", A92="Transferwise", A92="Custodia Socios", A92="Cheques en cartera", A92="Caja"), "Activo Liquido", IF( OR(A92="Otras Inversiones", A92="Santander Inversiones"), "Mediano Plazo", IF( A92="Clientes a cobrar", "Clientes a cobrar", "DATO NO CARGADO" ) ) ) ) -> Activo Liquido | C92: =IF(K92="", "", IFERROR(VLOOKUP(K92, Clasificaciones!D:E, 2, FALSE), "DATO NO CARGADO")) | D92: 08 ago | E92: 2025 | H92: =IF( A92="", "", IF( AND( F92="No", OR(G92="",G92>M92), M92<TODAY() ), "Vencido", "A término" ) ) -> A término | O92: -42553 | P92: =IF(ISBLANK(N92), "", VLOOKUP(D92&" "&E92, 'Info Tipo de Cambio y REM'!$A$24:$B$35, 2, FALSE)) | Q92: =IF(NOT(ISBLANK(N92)), N92 / P92, IF(NOT(ISBLANK(O92)), O92, "")) -> -42553
A93: Transferwise | B93: =IF( A93="", "", IF( OR(A93="Santander-Galicia-Nación", A93="Bank Of America", A93="Transferwise", A93="Custodia Socios", A93="Cheques en cartera", A93="Caja"), "Activo Liquido", IF( OR(A93="Otras Inversiones", A93="Santander Inversiones"), "Mediano Plazo", IF( A93="Clientes a cobrar", "Clientes a cobrar", "DATO NO CARGADO" ) ) ) ) -> Activo Liquido | C93: =IF(K93="", "", IFERROR(VLOOKUP(K93, Clasificaciones!D:E, 2, FALSE), "DATO NO CARGADO")) | D93: 08 ago | E93: 2025 | H93: =IF( A93="", "", IF( AND( F93="No", OR(G93="",G93>M93), M93<TODAY() ), "Vencido", "A término" ) ) -> A término | O93: 230 | P93: =IF(ISBLANK(N93), "", VLOOKUP(D93&" "&E93, 'Info Tipo de Cambio y REM'!$A$24:$B$35, 2, FALSE)) | Q93: =IF(NOT(ISBLANK(N93)), N93 / P93, IF(NOT(ISBLANK(O93)), O93, "")) -> 230
A94: Otras Inversiones | B94: =IF( A94="", "", IF( OR(A94="Santander-Galicia-Nación", A94="Bank Of America", A94="Transferwise", A94="Custodia Socios", A94="Cheques en cartera", A94="Caja"), "Activo Liquido", IF( OR(A94="Otras Inversiones", A94="Santander Inversiones"), "Mediano Plazo", IF( A94="Clientes a cobrar", "Clientes a cobrar", "DATO NO CARGADO" ) ) ) ) -> Mediano Plazo | C94: =IF(K94="", "", IFERROR(VLOOKUP(K94, Clasificaciones!D:E, 2, FALSE), "DATO NO CARGADO")) | D94: 08 ago | E94: 2025 | H94: =IF( A94="", "", IF( AND( F94="No", OR(G94="",G94>M94), M94<TODAY() ), "Vencido", "A término" ) ) -> A término | O94: 2417 | P94: =IF(ISBLANK(N94), "", VLOOKUP(D94&" "&E94, 'Info Tipo de Cambio y REM'!$A$24:$B$35, 2, FALSE)) | Q94: =IF(NOT(ISBLANK(N94)), N94 / P94, IF(NOT(ISBLANK(O94)), O94, "")) -> 2417
A95: Clientes a cobrar | B95: =IF( A95="", "", IF( OR(A95="Santander-Galicia-Nación", A95="Bank Of America", A95="Transferwise", A95="Custodia Socios", A95="Cheques en cartera", A95="Caja"), "Activo Liquido", IF( OR(A95="Otras Inversiones", A95="Santander Inversiones"), "Mediano Plazo", IF( A95="Clientes a cobrar", "Clientes a cobrar", "DATO NO CARGADO" ) ) ) ) -> Clientes a cobrar | C95: =IF(K95="", "", IFERROR(VLOOKUP(K95, Clasificaciones!D:E, 2, FALSE), "DATO NO CARGADO")) -> Animal Studio | D95: 09 sep | E95: 2025 | F95: Si | G95: 45904 | H95: =IF( A95="", "", IF( AND( F95="No", OR(G95="",G95>M95), M95<TODAY() ), "Vencido", "A término" ) ) -> A término | I95: 45903 | J95: A-00008-00002023 | K95: ANIMAL STUDIO S.R.L. | M95: 45933 | N95: 2042746.2 | P95: =IF(ISBLANK(N95), "", VLOOKUP(D95&" "&E95, 'Info Tipo de Cambio y REM'!$A$24:$B$35, 2, FALSE)) -> 1445 | Q95: =IF(NOT(ISBLANK(N95)), N95 / P95, IF(NOT(ISBLANK(O95)), O95, "")) -> 1413.6652
A96: Clientes a cobrar | B96: =IF( A96="", "", IF( OR(A96="Santander-Galicia-Nación", A96="Bank Of America", A96="Transferwise", A96="Custodia Socios", A96="Cheques en cartera", A96="Caja"), "Activo Liquido", IF( OR(A96="Otras Inversiones", A96="Santander Inversiones"), "Mediano Plazo", IF( A96="Clientes a cobrar", "Clientes a cobrar", "DATO NO CARGADO" ) ) ) ) -> Clientes a cobrar | C96: =IF(K96="", "", IFERROR(VLOOKUP(K96, Clasificaciones!D:E, 2, FALSE), "DATO NO CARGADO")) -> Coelsa | D96: 09 sep | E96: 2025 | F96: No | H96: =IF( A96="", "", IF( AND( F96="No", OR(G96="",G96>M96), M96<TODAY() ), "Vencido", "A término" ) ) -> Vencido | I96: 45902 | J96: A-00008-00000984 | K96: COMPENSADORA ELECTRONICA SA | M96: 45932 | N96: 5539197.3 | P96: =IF(ISBLANK(N96), "", VLOOKUP(D96&" "&E96, 'Info Tipo de Cambio y REM'!$A$24:$B$35, 2, FALSE)) -> 1445 | Q96: =IF(NOT(ISBLANK(N96)), N96 / P96, IF(NOT(ISBLANK(O96)), O96, "")) -> 3833.3545
A97: Clientes a cobrar | B97: =IF( A97="", "", IF( OR(A97="Santander-Galicia-Nación", A97="Bank Of America", A97="Transferwise", A97="Custodia Socios", A97="Cheques en cartera", A97="Caja"), "Activo Liquido", IF( OR(A97="Otras Inversiones", A97="Santander Inversiones"), "Mediano Plazo", IF( A97="Clientes a cobrar", "Clientes a cobrar", "DATO NO CARGADO" ) ) ) ) -> Clientes a cobrar | C97: =IF(K97="", "", IFERROR(VLOOKUP(K97, Clasificaciones!D:E, 2, FALSE), "DATO NO CARGADO")) -> PeYa | D97: 09 sep | E97: 2025 | F97: No | H97: =IF( A97="", "", IF( AND( F97="No", OR(G97="",G97>M97), M97<TODAY() ), "Vencido", "A término" ) ) -> Vencido | I97: 45901 | J97: A-00008-00000983 | K97: DELIVERY HERO E-COMMERCE S. A. | M97: 45931 | N97: 5143105 | P97: =IF(ISBLANK(N97), "", VLOOKUP(D97&" "&E97, 'Info Tipo de Cambio y REM'!$A$24:$B$35, 2, FALSE)) -> 1445 | Q97: =IF(NOT(ISBLANK(N97)), N97 / P97, IF(NOT(ISBLANK(O97)), O97, "")) -> 3559.2422
A98: Clientes a cobrar | B98: =IF( A98="", "", IF( OR(A98="Santander-Galicia-Nación", A98="Bank Of America", A98="Transferwise", A98="Custodia Socios", A98="Cheques en cartera", A98="Caja"), "Activo Liquido", IF( OR(A98="Otras Inversiones", A98="Santander Inversiones"), "Mediano Plazo", IF( A98="Clientes a cobrar", "Clientes a cobrar", "DATO NO CARGADO" ) ) ) ) -> Clientes a cobrar | C98: =IF(K98="", "", IFERROR(VLOOKUP(K98, Clasificaciones!D:E, 2, FALSE), "DATO NO CARGADO")) -> Play Digital S.A (Modo) | D98: 09 sep | E98: 2025 | F98: No | H98: =IF( A98="", "", IF( AND( F98="No", OR(G98="",G98>M98), M98<TODAY() ), "Vencido", "A término" ) ) -> Vencido | I98: 45902 | J98: A-00008-00002020 | K98: PLAY DIGITAL S. A. | M98: 45932 | N98: 3720750 | P98: =IF(ISBLANK(N98), "", VLOOKUP(D98&" "&E98, 'Info Tipo de Cambio y REM'!$A$24:$B$35, 2, FALSE)) -> 1445 | Q98: =IF(NOT(ISBLANK(N98)), N98 / P98, IF(NOT(ISBLANK(O98)), O98, "")) -> 2574.9135
A99: Clientes a cobrar | B99: =IF( A99="", "", IF( OR(A99="Santander-Galicia-Nación", A99="Bank Of America", A99="Transferwise", A99="Custodia Socios", A99="Cheques en cartera", A99="Caja"), "Activo Liquido", IF( OR(A99="Otras Inversiones", A99="Santander Inversiones"), "Mediano Plazo", IF( A99="Clientes a cobrar", "Clientes a cobrar", "DATO NO CARGADO" ) ) ) ) -> Clientes a cobrar | C99: =IF(K99="", "", IFERROR(VLOOKUP(K99, Clasificaciones!D:E, 2, FALSE), "DATO NO CARGADO")) -> Detroit | D99: 09 sep | E99: 2025 | F99: Si | G99: 45912 | H99: =IF( A99="", "", IF( AND( F99="No", OR(G99="",G99>M99), M99<TODAY() ), "Vencido", "A término" ) ) -> A término | I99: 45901 | J99: FEE MES DE SEPTIEMBRE | K99: DETROIT | M99: 45931 | N99: 1114000 | P99: =IF(ISBLANK(N99), "", VLOOKUP(D99&" "&E99, 'Info Tipo de Cambio y REM'!$A$24:$B$35, 2, FALSE)) -> 1445 | Q99: =IF(NOT(ISBLANK(N99)), N99 / P99, IF(NOT(ISBLANK(O99)), O99, "")) -> 770.93426
A100: Clientes a cobrar | B100: =IF( A100="", "", IF( OR(A100="Santander-Galicia-Nación", A100="Bank Of America", A100="Transferwise", A100="Custodia Socios", A100="Cheques en cartera", A100="Caja"), "Activo Liquido", IF( OR(A100="Otras Inversiones", A100="Santander Inversiones"), "Mediano Plazo", IF( A100="Clientes a cobrar", "Clientes a cobrar", "DATO NO CARGADO" ) ) ) ) -> Clientes a cobrar | C100: =IF(K100="", "", IFERROR(VLOOKUP(K100, Clasificaciones!D:E, 2, FALSE), "DATO NO CARGADO")) -> Kimberly Clark | D100: 09 sep | E100: 2025 | F100: No | H100: =IF( A100="", "", IF( AND( F100="No", OR(G100="",G100>M100), M100<TODAY() ), "Vencido", "A término" ) ) -> Vencido | I100: 45902 | J100: INVOICE 635 | K100: KIMBERLY | M100: 45932 | O100: 4225 | P100: =IF(ISBLANK(N100), "", VLOOKUP(D100&" "&E100, 'Info Tipo de Cambio y REM'!$A$24:$B$35, 2, FALSE)) | Q100: =IF(NOT(ISBLANK(N100)), N100 / P100, IF(NOT(ISBLANK(O100)), O100, "")) -> 4225
...

Sheet ACTIVO BACK UP 5-9 previo cambi
A1: Concepto/Banco | B1: Tipo de Activo | C1: Cliente | D1: Mes | E1: Año | F1: Cobrado/No Cobrado AL CIERRE | G1: Fecha de pago | H1: Fecha Facturación | I1: Nro de Factura/Comprobante | J1: Razón Social/Cliente | K1: Detalle | L1: Fecha de vencimiento | M1: Moneda original ARS | N1: Moneda original USD | O1: Cotización | P1: Monto Total USD
A2: Santander-Galicia-Nación | B2: =IF( A2="", "", IF( OR(A2="Santander-Galicia-Nación", A2="Bank Of America", A2="Transferwise", A2="Custodia Socios", A2="Cheques en cartera", A2="Caja"), "Activo Liquido", IF( OR(A2="Otras Inversiones", A2="Santander Inversiones"), "Mediano Plazo", IF( A2="Clientes a cobrar", "Clientes a cobrar", "DATO NO CARGADO" ) ) ) ) -> Activo Liquido | C2: =IF(J2="", "", IFERROR(VLOOKUP(J2, Clasificaciones!D:E, 2, FALSE), "DATO NO CARGADO")) | D2: 01 ene | E2: 2025 | M2: 8217613 | O2: =IF(ISBLANK(M2), "", VLOOKUP(D2, 'Info Tipo de Cambio y REM'!$A$24:$B$35, 2, FALSE)) -> #N/A | P2: =IF(NOT(ISBLANK(M2)), M2 / O2, IF(NOT(ISBLANK(N2)), N2, "")) -> #N/A
A3: Bank Of America | B3: =IF( A3="", "", IF( OR(A3="Santander-Galicia-Nación", A3="Bank Of America", A3="Transferwise", A3="Custodia Socios", A3="Cheques en cartera", A3="Caja"), "Activo Liquido", IF( OR(A3="Otras Inversiones", A3="Santander Inversiones"), "Mediano Plazo", IF( A3="Clientes a cobrar", "Clientes a cobrar", "DATO NO CARGADO" ) ) ) ) -> Activo Liquido | C3: =IF(J3="", "", IFERROR(VLOOKUP(J3, Clasificaciones!D:E, 2, FALSE), "DATO NO CARGADO")) | D3: 01 ene | E3: 2025 | N3: -2840 | O3: =IF(ISBLANK(M3), "", VLOOKUP(D3, 'Info Tipo de Cambio y REM'!$A$24:$B$35, 2, FALSE)) | P3: =IF(NOT(ISBLANK(M3)), M3 / O3, IF(NOT(ISBLANK(N3)), N3, "")) -> -2840
A4: Transferwise | B4: =IF( A4="", "", IF( OR(A4="Santander-Galicia-Nación", A4="Bank Of America", A4="Transferwise", A4="Custodia Socios", A4="Cheques en cartera", A4="Caja"), "Activo Liquido", IF( OR(A4="Otras Inversiones", A4="Santander Inversiones"), "Mediano Plazo", IF( A4="Clientes a cobrar", "Clientes a cobrar", "DATO NO CARGADO" ) ) ) ) -> Activo Liquido | C4: =IF(J4="", "", IFERROR(VLOOKUP(J4, Clasificaciones!D:E, 2, FALSE), "DATO NO CARGADO")) | D4: 01 ene | E4: 2025 | N4: 230 | O4: =IF(ISBLANK(M4), "", VLOOKUP(D4, 'Info Tipo de Cambio y REM'!$A$24:$B$35, 2, FALSE)) | P4: =IF(NOT(ISBLANK(M4)), M4 / O4, IF(NOT(ISBLANK(N4)), N4, "")) -> 230
A5: Otras Inversiones | B5: =IF( A5="", "", IF( OR(A5="Santander-Galicia-Nación", A5="Bank Of America", A5="Transferwise", A5="Custodia Socios", A5="Cheques en cartera", A5="Caja"), "Activo Liquido", IF( OR(A5="Otras Inversiones", A5="Santander Inversiones"), "Mediano Plazo", IF( A5="Clientes a cobrar", "Clientes a cobrar", "DATO NO CARGADO" ) ) ) ) -> Mediano Plazo | C5: =IF(J5="", "", IFERROR(VLOOKUP(J5, Clasificaciones!D:E, 2, FALSE), "DATO NO CARGADO")) | D5: 01 ene | E5: 2025 | N5: 9200 | O5: =IF(ISBLANK(M5), "", VLOOKUP(D5, 'Info Tipo de Cambio y REM'!$A$24:$B$35, 2, FALSE)) | P5: =IF(NOT(ISBLANK(M5)), M5 / O5, IF(NOT(ISBLANK(N5)), N5, "")) -> 9200
A6: Clientes a cobrar | B6: =IF( A6="", "", IF( OR(A6="Santander-Galicia-Nación", A6="Bank Of America", A6="Transferwise", A6="Custodia Socios", A6="Cheques en cartera", A6="Caja"), "Activo Liquido", IF( OR(A6="Otras Inversiones", A6="Santander Inversiones"), "Mediano Plazo", IF( A6="Clientes a cobrar", "Clientes a cobrar", "DATO NO CARGADO" ) ) ) ) -> Clientes a cobrar | C6: =IF(J6="", "", IFERROR(VLOOKUP(J6, Clasificaciones!D:E, 2, FALSE), "DATO NO CARGADO")) -> Arcos Dorados | D6: 01 ene | E6: 2025 | I6: Factura de Crédito MiPyME (FCE) N° A-00008-00000898 | J6: ARCOS DORADOS ARGENTINA S.A. | L6: 45680 | M6: 508200 | O6: =IF(ISBLANK(M6), "", VLOOKUP(D6, 'Info Tipo de Cambio y REM'!$A$24:$B$35, 2, FALSE)) -> #N/A | P6: =IF(NOT(ISBLANK(M6)), M6 / O6, IF(NOT(ISBLANK(N6)), N6, "")) -> #N/A
A7: Clientes a cobrar | B7: =IF( A7="", "", IF( OR(A7="Santander-Galicia-Nación", A7="Bank Of America", A7="Transferwise", A7="Custodia Socios", A7="Cheques en cartera", A7="Caja"), "Activo Liquido", IF( OR(A7="Otras Inversiones", A7="Santander Inversiones"), "Mediano Plazo", IF( A7="Clientes a cobrar", "Clientes a cobrar", "DATO NO CARGADO" ) ) ) ) -> Clientes a cobrar | C7: =IF(J7="", "", IFERROR(VLOOKUP(J7, Clasificaciones!D:E, 2, FALSE), "DATO NO CARGADO")) -> Play Digital S.A (Modo) | D7: 01 ene | E7: 2025 | I7: Factura de Venta N° A-00008-00001931 | J7: PLAY DIGITAL S. A. | L7: 45688 | M7: 4744208 | O7: =IF(ISBLANK(M7), "", VLOOKUP(D7, 'Info Tipo de Cambio y REM'!$A$24:$B$35, 2, FALSE)) -> #N/A | P7: =IF(NOT(ISBLANK(M7)), M7 / O7, IF(NOT(ISBLANK(N7)), N7, "")) -> #N/A
A8: Clientes a cobrar | B8: =IF( A8="", "", IF( OR(A8="Santander-Galicia-Nación", A8="Bank Of America", A8="Transferwise", A8="Custodia Socios", A8="Cheques en cartera", A8="Caja"), "Activo Liquido", IF( OR(A8="Otras Inversiones", A8="Santander Inversiones"), "Mediano Plazo", IF( A8="Clientes a cobrar", "Clientes a cobrar", "DATO NO CARGADO" ) ) ) ) -> Clientes a cobrar | C8: =IF(J8="", "", IFERROR(VLOOKUP(J8, Clasificaciones!D:E, 2, FALSE), "DATO NO CARGADO")) -> Coelsa | D8: 01 ene | E8: 2025 | I8: Factura de Crédito MiPyME (FCE) N° A-00008-00000886 | J8: COMPENSADORA ELECTRONICA SA | L8: 45659 | M8: 4499766 | O8: =IF(ISBLANK(M8), "", VLOOKUP(D8, 'Info Tipo de Cambio y REM'!$A$24:$B$35, 2, FALSE)) -> #N/A | P8: =IF(NOT(ISBLANK(M8)), M8 / O8, IF(NOT(ISBLANK(N8)), N8, "")) -> #N/A
A9: Clientes a cobrar | B9: =IF( A9="", "", IF( OR(A9="Santander-Galicia-Nación", A9="Bank Of America", A9="Transferwise", A9="Custodia Socios", A9="Cheques en cartera", A9="Caja"), "Activo Liquido", IF( OR(A9="Otras Inversiones", A9="Santander Inversiones"), "Mediano Plazo", IF( A9="Clientes a cobrar", "Clientes a cobrar", "DATO NO CARGADO" ) ) ) ) -> Clientes a cobrar | C9: =IF(J9="", "", IFERROR(VLOOKUP(J9, Clasificaciones!D:E, 2, FALSE), "DATO NO CARGADO")) -> Moreno Ocampo | D9: 01 ene | E9: 2025 | I9: Invoice 532 | J9: MORENO OCAMPO | L9: 45678 | N9: 250 | O9: =IF(ISBLANK(M9), "", VLOOKUP(D9, 'Info Tipo de Cambio y REM'!$A$24:$B$35, 2, FALSE)) | P9: =IF(NOT(ISBLANK(M9)), M9 / O9, IF(NOT(ISBLANK(N9)), N9, "")) -> 250
A10: Clientes a cobrar | B10: =IF( A10="", "", IF( OR(A10="Santander-Galicia-Nación", A10="Bank Of America", A10="Transferwise", A10="Custodia Socios", A10="Cheques en cartera", A10="Caja"), "Activo Liquido", IF( OR(A10="Otras Inversiones", A10="Santander Inversiones"), "Mediano Plazo", IF( A10="Clientes a cobrar", "Clientes a cobrar", "DATO NO CARGADO" ) ) ) ) -> Clientes a cobrar | C10: =IF(J10="", "", IFERROR(VLOOKUP(J10, Clasificaciones!D:E, 2, FALSE), "DATO NO CARGADO")) -> Warner | D10: 01 ene | E10: 2025 | I10: Invoice 515 | J10: WARNER BROS | L10: 45714 | N10: 13450 | O10: =IF(ISBLANK(M10), "", VLOOKUP(D10, 'Info Tipo de Cambio y REM'!$A$24:$B$35, 2, FALSE)) | P10: =IF(NOT(ISBLANK(M10)), M10 / O10, IF(NOT(ISBLANK(N10)), N10, "")) -> 13450
A11: Clientes a cobrar | B11: =IF( A11="", "", IF( OR(A11="Santander-Galicia-Nación", A11="Bank Of America", A11="Transferwise", A11="Custodia Socios", A11="Cheques en cartera", A11="Caja"), "Activo Liquido", IF( OR(A11="Otras Inversiones", A11="Santander Inversiones"), "Mediano Plazo", IF( A11="Clientes a cobrar", "Clientes a cobrar", "DATO NO CARGADO" ) ) ) ) -> Clientes a cobrar | C11: =IF(J11="", "", IFERROR(VLOOKUP(J11, Clasificaciones!D:E, 2, FALSE), "DATO NO CARGADO")) -> Warner | D11: 01 ene | E11: 2025 | I11: Invoice 525 | J11: WARNER BROS | L11: 45726 | N11: 13450 | O11: =IF(ISBLANK(M11), "", VLOOKUP(D11, 'Info Tipo de Cambio y REM'!$A$24:$B$35, 2, FALSE)) | P11: =IF(NOT(ISBLANK(M11)), M11 / O11, IF(NOT(ISBLANK(N11)), N11, "")) -> 13450
A12: Clientes a cobrar | B12: =IF( A12="", "", IF( OR(A12="Santander-Galicia-Nación", A12="Bank Of America", A12="Transferwise", A12="Custodia Socios", A12="Cheques en cartera", A12="Caja"), "Activo Liquido", IF( OR(A12="Otras Inversiones", A12="Santander Inversiones"), "Mediano Plazo", IF( A12="Clientes a cobrar", "Clientes a cobrar", "DATO NO CARGADO" ) ) ) ) -> Clientes a cobrar | C12: =IF(J12="", "", IFERROR(VLOOKUP(J12, Clasificaciones!D:E, 2, FALSE), "DATO NO CARGADO")) -> Warner | D12: 01 ene | E12: 2025 | I12: Invoice 534 | J12: WARNER BROS | L12: 45750 | N12: 13450 | O12: =IF(ISBLANK(M12), "", VLOOKUP(D12, 'Info Tipo de Cambio y REM'!$A$24:$B$35, 2, FALSE)) | P12: =IF(NOT(ISBLANK(M12)), M12 / O12, IF(NOT(ISBLANK(N12)), N12, "")) -> 13450
A13: Clientes a cobrar | B13: =IF( A13="", "", IF( OR(A13="Santander-Galicia-Nación", A13="Bank Of America", A13="Transferwise", A13="Custodia Socios", A13="Cheques en cartera", A13="Caja"), "Activo Liquido", IF( OR(A13="Otras Inversiones", A13="Santander Inversiones"), "Mediano Plazo", IF( A13="Clientes a cobrar", "Clientes a cobrar", "DATO NO CARGADO" ) ) ) ) -> Clientes a cobrar | C13: =IF(J13="", "", IFERROR(VLOOKUP(J13, Clasificaciones!D:E, 2, FALSE), "DATO NO CARGADO")) -> Vertical Media | D13: 01 ene | E13: 2025 | I13: INVOICE 539 | J13: VERTICAL MEDIA | L13: 45704 | N13: 1750 | O13: =IF(ISBLANK(M13), "", VLOOKUP(D13, 'Info Tipo de Cambio y REM'!$A$24:$B$35, 2, FALSE)) | P13: =IF(NOT(ISBLANK(M13)), M13 / O13, IF(NOT(ISBLANK(N13)), N13, "")) -> 1750
A14: Clientes a cobrar | B14: =IF( A14="", "", IF( OR(A14="Santander-Galicia-Nación", A14="Bank Of America", A14="Transferwise", A14="Custodia Socios", A14="Cheques en cartera", A14="Caja"), "Activo Liquido", IF( OR(A14="Otras Inversiones", A14="Santander Inversiones"), "Mediano Plazo", IF( A14="Clientes a cobrar", "Clientes a cobrar", "DATO NO CARGADO" ) ) ) ) -> Clientes a cobrar | C14: =IF(J14="", "", IFERROR(VLOOKUP(J14, Clasificaciones!D:E, 2, FALSE), "DATO NO CARGADO")) -> Uber | D14: 01 ene | E14: 2025 | I14: Invoice 520 | J14: UBER | L14: 45690 | N14: 7150 | O14: =IF(ISBLANK(M14), "", VLOOKUP(D14, 'Info Tipo de Cambio y REM'!$A$24:$B$35, 2, FALSE)) | P14: =IF(NOT(ISBLANK(M14)), M14 / O14, IF(NOT(ISBLANK(N14)), N14, "")) -> 7150
A15: Clientes a cobrar | B15: =IF( A15="", "", IF( OR(A15="Santander-Galicia-Nación", A15="Bank Of America", A15="Transferwise", A15="Custodia Socios", A15="Cheques en cartera", A15="Caja"), "Activo Liquido", IF( OR(A15="Otras Inversiones", A15="Santander Inversiones"), "Mediano Plazo", IF( A15="Clientes a cobrar", "Clientes a cobrar", "DATO NO CARGADO" ) ) ) ) -> Clientes a cobrar | C15: Detroit | D15: 01 ene | E15: 2025 | M15: 718100 | O15: =IF(ISBLANK(M15), "", VLOOKUP(D15, 'Info Tipo de Cambio y REM'!$A$24:$B$35, 2, FALSE)) -> #N/A | P15: =IF(NOT(ISBLANK(M15)), M15 / O15, IF(NOT(ISBLANK(N15)), N15, "")) -> #N/A
A16: Santander-Galicia-Nación | B16: =IF( A16="", "", IF( OR(A16="Santander-Galicia-Nación", A16="Bank Of America", A16="Transferwise", A16="Custodia Socios", A16="Cheques en cartera", A16="Caja"), "Activo Liquido", IF( OR(A16="Otras Inversiones", A16="Santander Inversiones"), "Mediano Plazo", IF( A16="Clientes a cobrar", "Clientes a cobrar", "DATO NO CARGADO" ) ) ) ) -> Activo Liquido | C16: =IF(J16="", "", IFERROR(VLOOKUP(J16, Clasificaciones!D:E, 2, FALSE), "DATO NO CARGADO")) | D16: 02 feb | E16: 2025 | M16: 29367 | O16: =IF(ISBLANK(M16), "", VLOOKUP(D16, 'Info Tipo de Cambio y REM'!$A$24:$B$35, 2, FALSE)) -> #N/A | P16: =IF(NOT(ISBLANK(M16)), M16 / O16, IF(NOT(ISBLANK(N16)), N16, "")) -> #N/A
A17: Bank Of America | B17: =IF( A17="", "", IF( OR(A17="Santander-Galicia-Nación", A17="Bank Of America", A17="Transferwise", A17="Custodia Socios", A17="Cheques en cartera", A17="Caja"), "Activo Liquido", IF( OR(A17="Otras Inversiones", A17="Santander Inversiones"), "Mediano Plazo", IF( A17="Clientes a cobrar", "Clientes a cobrar", "DATO NO CARGADO" ) ) ) ) -> Activo Liquido | C17: =IF(J17="", "", IFERROR(VLOOKUP(J17, Clasificaciones!D:E, 2, FALSE), "DATO NO CARGADO")) | D17: 02 feb | E17: 2025 | N17: -7604 | O17: =IF(ISBLANK(M17), "", VLOOKUP(D17, 'Info Tipo de Cambio y REM'!$A$24:$B$35, 2, FALSE)) | P17: =IF(NOT(ISBLANK(M17)), M17 / O17, IF(NOT(ISBLANK(N17)), N17, "")) -> -7604
A18: Transferwise | B18: =IF( A18="", "", IF( OR(A18="Santander-Galicia-Nación", A18="Bank Of America", A18="Transferwise", A18="Custodia Socios", A18="Cheques en cartera", A18="Caja"), "Activo Liquido", IF( OR(A18="Otras Inversiones", A18="Santander Inversiones"), "Mediano Plazo", IF( A18="Clientes a cobrar", "Clientes a cobrar", "DATO NO CARGADO" ) ) ) ) -> Activo Liquido | C18: =IF(J18="", "", IFERROR(VLOOKUP(J18, Clasificaciones!D:E, 2, FALSE), "DATO NO CARGADO")) | D18: 02 feb | E18: 2025 | N18: 230 | O18: =IF(ISBLANK(M18), "", VLOOKUP(D18, 'Info Tipo de Cambio y REM'!$A$24:$B$35, 2, FALSE)) | P18: =IF(NOT(ISBLANK(M18)), M18 / O18, IF(NOT(ISBLANK(N18)), N18, "")) -> 230
A19: Otras Inversiones | B19: =IF( A19="", "", IF( OR(A19="Santander-Galicia-Nación", A19="Bank Of America", A19="Transferwise", A19="Custodia Socios", A19="Cheques en cartera", A19="Caja"), "Activo Liquido", IF( OR(A19="Otras Inversiones", A19="Santander Inversiones"), "Mediano Plazo", IF( A19="Clientes a cobrar", "Clientes a cobrar", "DATO NO CARGADO" ) ) ) ) -> Mediano Plazo | C19: =IF(J19="", "", IFERROR(VLOOKUP(J19, Clasificaciones!D:E, 2, FALSE), "DATO NO CARGADO")) | D19: 02 feb | E19: 2025 | N19: 6983 | O19: =IF(ISBLANK(M19), "", VLOOKUP(D19, 'Info Tipo de Cambio y REM'!$A$24:$B$35, 2, FALSE)) | P19: =IF(NOT(ISBLANK(M19)), M19 / O19, IF(NOT(ISBLANK(N19)), N19, "")) -> 6983
A20: Clientes a cobrar | B20: =IF( A20="", "", IF( OR(A20="Santander-Galicia-Nación", A20="Bank Of America", A20="Transferwise", A20="Custodia Socios", A20="Cheques en cartera", A20="Caja"), "Activo Liquido", IF( OR(A20="Otras Inversiones", A20="Santander Inversiones"), "Mediano Plazo", IF( A20="Clientes a cobrar", "Clientes a cobrar", "DATO NO CARGADO" ) ) ) ) -> Clientes a cobrar | C20: =IF(J20="", "", IFERROR(VLOOKUP(J20, Clasificaciones!D:E, 2, FALSE), "DATO NO CARGADO")) -> Play Digital S.A (Modo) | D20: 02 feb | E20: 2025 | I20: Factura de Venta N° A-00008-00001937 | J20: PLAY DIGITAL S. A. | L20: 45719 | M20: 4744208 | O20: =IF(ISBLANK(M20), "", VLOOKUP(D20, 'Info Tipo de Cambio y REM'!$A$24:$B$35, 2, FALSE)) -> #N/A | P20: =IF(NOT(ISBLANK(M20)), M20 / O20, IF(NOT(ISBLANK(N20)), N20, "")) -> #N/A
A21: Clientes a cobrar | B21: =IF( A21="", "", IF( OR(A21="Santander-Galicia-Nación", A21="Bank Of America", A21="Transferwise", A21="Custodia Socios", A21="Cheques en cartera", A21="Caja"), "Activo Liquido", IF( OR(A21="Otras Inversiones", A21="Santander Inversiones"), "Mediano Plazo", IF( A21="Clientes a cobrar", "Clientes a cobrar", "DATO NO CARGADO" ) ) ) ) -> Clientes a cobrar | C21: =IF(J21="", "", IFERROR(VLOOKUP(J21, Clasificaciones!D:E, 2, FALSE), "DATO NO CARGADO")) -> Coelsa | D21: 02 feb | E21: 2025 | I21: Factura de Crédito MiPyME (FCE) N° A-00008-00000906 | J21: COMPENSADORA ELECTRONICA SA | L21: 45719 | M21: 4499766 | O21: =IF(ISBLANK(M21), "", VLOOKUP(D21, 'Info Tipo de Cambio y REM'!$A$24:$B$35, 2, FALSE)) -> #N/A | P21: =IF(NOT(ISBLANK(M21)), M21 / O21, IF(NOT(ISBLANK(N21)), N21, "")) -> #N/A
A22: Clientes a cobrar | B22: =IF( A22="", "", IF( OR(A22="Santander-Galicia-Nación", A22="Bank Of America", A22="Transferwise", A22="Custodia Socios", A22="Cheques en cartera", A22="Caja"), "Activo Liquido", IF( OR(A22="Otras Inversiones", A22="Santander Inversiones"), "Mediano Plazo", IF( A22="Clientes a cobrar", "Clientes a cobrar", "DATO NO CARGADO" ) ) ) ) -> Clientes a cobrar | C22: =IF(J22="", "", IFERROR(VLOOKUP(J22, Clasificaciones!D:E, 2, FALSE), "DATO NO CARGADO")) -> Moreno Ocampo | D22: 02 feb | E22: 2025 | I22: Invoice 532 | J22: MORENO OCAMPO | L22: 45678 | N22: 250 | O22: =IF(ISBLANK(M22), "", VLOOKUP(D22, 'Info Tipo de Cambio y REM'!$A$24:$B$35, 2, FALSE)) | P22: =IF(NOT(ISBLANK(M22)), M22 / O22, IF(NOT(ISBLANK(N22)), N22, "")) -> 250
A23: Clientes a cobrar | B23: =IF( A23="", "", IF( OR(A23="Santander-Galicia-Nación", A23="Bank Of America", A23="Transferwise", A23="Custodia Socios", A23="Cheques en cartera", A23="Caja"), "Activo Liquido", IF( OR(A23="Otras Inversiones", A23="Santander Inversiones"), "Mediano Plazo", IF( A23="Clientes a cobrar", "Clientes a cobrar", "DATO NO CARGADO" ) ) ) ) -> Clientes a cobrar | C23: =IF(J23="", "", IFERROR(VLOOKUP(J23, Clasificaciones!D:E, 2, FALSE), "DATO NO CARGADO")) -> Warner | D23: 02 feb | E23: 2025 | I23: Invoice 525 | J23: WARNER BROS | L23: 45726 | N23: 13450 | O23: =IF(ISBLANK(M23), "", VLOOKUP(D23, 'Info Tipo de Cambio y REM'!$A$24:$B$35, 2, FALSE)) | P23: =IF(NOT(ISBLANK(M23)), M23 / O23, IF(NOT(ISBLANK(N23)), N23, "")) -> 13450
A24: Clientes a cobrar | B24: =IF( A24="", "", IF( OR(A24="Santander-Galicia-Nación", A24="Bank Of America", A24="Transferwise", A24="Custodia Socios", A24="Cheques en cartera", A24="Caja"), "Activo Liquido", IF( OR(A24="Otras Inversiones", A24="Santander Inversiones"), "Mediano Plazo", IF( A24="Clientes a cobrar", "Clientes a cobrar", "DATO NO CARGADO" ) ) ) ) -> Clientes a cobrar | C24: =IF(J24="", "", IFERROR(VLOOKUP(J24, Clasificaciones!D:E, 2, FALSE), "DATO NO CARGADO")) -> Warner | D24: 02 feb | E24: 2025 | I24: Invoice 534 | J24: WARNER BROS | L24: 45750 | N24: 13450 | O24: =IF(ISBLANK(M24), "", VLOOKUP(D24, 'Info Tipo de Cambio y REM'!$A$24:$B$35, 2, FALSE)) | P24: =IF(NOT(ISBLANK(M24)), M24 / O24, IF(NOT(ISBLANK(N24)), N24, "")) -> 13450
A25: Clientes a cobrar | B25: =IF( A25="", "", IF( OR(A25="Santander-Galicia-Nación", A25="Bank Of America", A25="Transferwise", A25="Custodia Socios", A25="Cheques en cartera", A25="Caja"), "Activo Liquido", IF( OR(A25="Otras Inversiones", A25="Santander Inversiones"), "Mediano Plazo", IF( A25="Clientes a cobrar", "Clientes a cobrar", "DATO NO CARGADO" ) ) ) ) -> Clientes a cobrar | C25: =IF(J25="", "", IFERROR(VLOOKUP(J25, Clasificaciones!D:E, 2, FALSE), "DATO NO CARGADO")) -> Warner | D25: 02 feb | E25: 2025 | I25: Invoice 547 | J25: WARNER BROS | L25: 45782 | N25: 13450 | O25: =IF(ISBLANK(M25), "", VLOOKUP(D25, 'Info Tipo de Cambio y REM'!$A$24:$B$35, 2, FALSE)) | P25: =IF(NOT(ISBLANK(M25)), M25 / O25, IF(NOT(ISBLANK(N25)), N25, "")) -> 13450
A26: Clientes a cobrar | B26: =IF( A26="", "", IF( OR(A26="Santander-Galicia-Nación", A26="Bank Of America", A26="Transferwise", A26="Custodia Socios", A26="Cheques en cartera", A26="Caja"), "Activo Liquido", IF( OR(A26="Otras Inversiones", A26="Santander Inversiones"), "Mediano Plazo", IF( A26="Clientes a cobrar", "Clientes a cobrar", "DATO NO CARGADO" ) ) ) ) -> Clientes a cobrar | C26: =IF(J26="", "", IFERROR(VLOOKUP(J26, Clasificaciones!D:E, 2, FALSE), "DATO NO CARGADO")) -> Vertical Media | D26: 02 feb | E26: 2025 | I26: Invoice 544 | J26: VERTICAL MEDIA | L26: 45719 | N26: 1750 | O26: =IF(ISBLANK(M26), "", VLOOKUP(D26, 'Info Tipo de Cambio y REM'!$A$24:$B$35, 2, FALSE)) | P26: =IF(NOT(ISBLANK(M26)), M26 / O26, IF(NOT(ISBLANK(N26)), N26, "")) -> 1750
A27: Clientes a cobrar | B27: =IF( A27="", "", IF( OR(A27="Santander-Galicia-Nación", A27="Bank Of America", A27="Transferwise", A27="Custodia Socios", A27="Cheques en cartera", A27="Caja"), "Activo Liquido", IF( OR(A27="Otras Inversiones", A27="Santander Inversiones"), "Mediano Plazo", IF( A27="Clientes a cobrar", "Clientes a cobrar", "DATO NO CARGADO" ) ) ) ) -> Clientes a cobrar | C27: Detroit | D27: 02 feb | E27: 2025 | M27: 144000 | O27: =IF(ISBLANK(M27), "", VLOOKUP(D27, 'Info Tipo de Cambio y REM'!$A$24:$B$35, 2, FALSE)) -> #N/A | P27: =IF(NOT(ISBLANK(M27)), M27 / O27, IF(NOT(ISBLANK(N27)), N27, "")) -> #N/A
A28: Clientes a cobrar | B28: =IF( A28="", "", IF( OR(A28="Santander-Galicia-Nación", A28="Bank Of America", A28="Transferwise", A28="Custodia Socios", A28="Cheques en cartera", A28="Caja"), "Activo Liquido", IF( OR(A28="Otras Inversiones", A28="Santander Inversiones"), "Mediano Plazo", IF( A28="Clientes a cobrar", "Clientes a cobrar", "DATO NO CARGADO" ) ) ) ) -> Clientes a cobrar | C28: Detroit | D28: 02 feb | E28: 2025 | M28: 718000 | O28: =IF(ISBLANK(M28), "", VLOOKUP(D28, 'Info Tipo de Cambio y REM'!$A$24:$B$35, 2, FALSE)) -> #N/A | P28: =IF(NOT(ISBLANK(M28)), M28 / O28, IF(NOT(ISBLANK(N28)), N28, "")) -> #N/A
A29: Santander-Galicia-Nación | B29: =IF( A29="", "", IF( OR(A29="Santander-Galicia-Nación", A29="Bank Of America", A29="Transferwise", A29="Custodia Socios", A29="Cheques en cartera", A29="Caja"), "Activo Liquido", IF( OR(A29="Otras Inversiones", A29="Santander Inversiones"), "Mediano Plazo", IF( A29="Clientes a cobrar", "Clientes a cobrar", "DATO NO CARGADO" ) ) ) ) -> Activo Liquido | C29: =IF(J29="", "", IFERROR(VLOOKUP(J29, Clasificaciones!D:E, 2, FALSE), "DATO NO CARGADO")) | D29: 03 mar | E29: 2025 | M29: -429974 | O29: =IF(ISBLANK(M29), "", VLOOKUP(D29, 'Info Tipo de Cambio y REM'!$A$24:$B$35, 2, FALSE)) -> #N/A | P29: =IF(NOT(ISBLANK(M29)), M29 / O29, IF(NOT(ISBLANK(N29)), N29, "")) -> #N/A
A30: Bank Of America | B30: =IF( A30="", "", IF( OR(A30="Santander-Galicia-Nación", A30="Bank Of America", A30="Transferwise", A30="Custodia Socios", A30="Cheques en cartera", A30="Caja"), "Activo Liquido", IF( OR(A30="Otras Inversiones", A30="Santander Inversiones"), "Mediano Plazo", IF( A30="Clientes a cobrar", "Clientes a cobrar", "DATO NO CARGADO" ) ) ) ) -> Activo Liquido | C30: =IF(J30="", "", IFERROR(VLOOKUP(J30, Clasificaciones!D:E, 2, FALSE), "DATO NO CARGADO")) | D30: 03 mar | E30: 2025 | N30: -26706 | O30: =IF(ISBLANK(M30), "", VLOOKUP(D30, 'Info Tipo de Cambio y REM'!$A$24:$B$35, 2, FALSE)) | P30: =IF(NOT(ISBLANK(M30)), M30 / O30, IF(NOT(ISBLANK(N30)), N30, "")) -> -26706
A31: Transferwise | B31: =IF( A31="", "", IF( OR(A31="Santander-Galicia-Nación", A31="Bank Of America", A31="Transferwise", A31="Custodia Socios", A31="Cheques en cartera", A31="Caja"), "Activo Liquido", IF( OR(A31="Otras Inversiones", A31="Santander Inversiones"), "Mediano Plazo", IF( A31="Clientes a cobrar", "Clientes a cobrar", "DATO NO CARGADO" ) ) ) ) -> Activo Liquido | C31: =IF(J31="", "", IFERROR(VLOOKUP(J31, Clasificaciones!D:E, 2, FALSE), "DATO NO CARGADO")) | D31: 03 mar | E31: 2025 | N31: 230 | O31: =IF(ISBLANK(M31), "", VLOOKUP(D31, 'Info Tipo de Cambio y REM'!$A$24:$B$35, 2, FALSE)) | P31: =IF(NOT(ISBLANK(M31)), M31 / O31, IF(NOT(ISBLANK(N31)), N31, "")) -> 230
A32: Otras Inversiones | B32: =IF( A32="", "", IF( OR(A32="Santander-Galicia-Nación", A32="Bank Of America", A32="Transferwise", A32="Custodia Socios", A32="Cheques en cartera", A32="Caja"), "Activo Liquido", IF( OR(A32="Otras Inversiones", A32="Santander Inversiones"), "Mediano Plazo", IF( A32="Clientes a cobrar", "Clientes a cobrar", "DATO NO CARGADO" ) ) ) ) -> Mediano Plazo | C32: =IF(J32="", "", IFERROR(VLOOKUP(J32, Clasificaciones!D:E, 2, FALSE), "DATO NO CARGADO")) | D32: 03 mar | E32: 2025 | N32: 2499 | O32: =IF(ISBLANK(M32), "", VLOOKUP(D32, 'Info Tipo de Cambio y REM'!$A$24:$B$35, 2, FALSE)) | P32: =IF(NOT(ISBLANK(M32)), M32 / O32, IF(NOT(ISBLANK(N32)), N32, "")) -> 2499
A33: Clientes a cobrar | B33: =IF( A33="", "", IF( OR(A33="Santander-Galicia-Nación", A33="Bank Of America", A33="Transferwise", A33="Custodia Socios", A33="Cheques en cartera", A33="Caja"), "Activo Liquido", IF( OR(A33="Otras Inversiones", A33="Santander Inversiones"), "Mediano Plazo", IF( A33="Clientes a cobrar", "Clientes a cobrar", "DATO NO CARGADO" ) ) ) ) -> Clientes a cobrar | C33: =IF(J33="", "", IFERROR(VLOOKUP(J33, Clasificaciones!D:E, 2, FALSE), "DATO NO CARGADO")) -> Play Digital S.A (Modo) | D33: 03 mar | E33: 2025 | I33: Factura de Venta N° A-00008-00001939 | J33: PLAY DIGITAL S. A. | L33: 45752 | M33: 5095280 | O33: =IF(ISBLANK(M33), "", VLOOKUP(D33, 'Info Tipo de Cambio y REM'!$A$24:$B$35, 2, FALSE)) -> #N/A | P33: =IF(NOT(ISBLANK(M33)), M33 / O33, IF(NOT(ISBLANK(N33)), N33, "")) -> #N/A
A34: Clientes a cobrar | B34: =IF( A34="", "", IF( OR(A34="Santander-Galicia-Nación", A34="Bank Of America", A34="Transferwise", A34="Custodia Socios", A34="Cheques en cartera", A34="Caja"), "Activo Liquido", IF( OR(A34="Otras Inversiones", A34="Santander Inversiones"), "Mediano Plazo", IF( A34="Clientes a cobrar", "Clientes a cobrar", "DATO NO CARGADO" ) ) ) ) -> Clientes a cobrar | C34: =IF(J34="", "", IFERROR(VLOOKUP(J34, Clasificaciones!D:E, 2, FALSE), "DATO NO CARGADO")) -> Coelsa | D34: 03 mar | E34: 2025 | I34: Factura de Crédito MiPyME (FCE) N° A-00008-00000922 | J34: COMPENSADORA ELECTRONICA SA | L34: 45752 | M34: 4832747 | O34: =IF(ISBLANK(M34), "", VLOOKUP(D34, 'Info Tipo de Cambio y REM'!$A$24:$B$35, 2, FALSE)) -> #N/A | P34: =IF(NOT(ISBLANK(M34)), M34 / O34, IF(NOT(ISBLANK(N34)), N34, "")) -> #N/A
A35: Clientes a cobrar | B35: =IF( A35="", "", IF( OR(A35="Santander-Galicia-Nación", A35="Bank Of America", A35="Transferwise", A35="Custodia Socios", A35="Cheques en cartera", A35="Caja"), "Activo Liquido", IF( OR(A35="Otras Inversiones", A35="Santander Inversiones"), "Mediano Plazo", IF( A35="Clientes a cobrar", "Clientes a cobrar", "DATO NO CARGADO" ) ) ) ) -> Clientes a cobrar | C35: =IF(J35="", "", IFERROR(VLOOKUP(J35, Clasificaciones!D:E, 2, FALSE), "DATO NO CARGADO")) -> Arcos Dorados | D35: 03 mar | E35: 2025 | I35: Factura de Crédito MiPyME (FCE) N° A-00008-00000925 | J35: ARCOS DORADOS ARGENTINA S.A. | L35: 45771 | M35: 4150300 | O35: =IF(ISBLANK(M35), "", VLOOKUP(D35, 'Info Tipo de Cambio y REM'!$A$24:$B$35, 2, FALSE)) -> #N/A | P35: =IF(NOT(ISBLANK(M35)), M35 / O35, IF(NOT(ISBLANK(N35)), N35, "")) -> #N/A
A36: Clientes a cobrar | B36: =IF( A36="", "", IF( OR(A36="Santander-Galicia-Nación", A36="Bank Of America", A36="Transferwise", A36="Custodia Socios", A36="Cheques en cartera", A36="Caja"), "Activo Liquido", IF( OR(A36="Otras Inversiones", A36="Santander Inversiones"), "Mediano Plazo", IF( A36="Clientes a cobrar", "Clientes a cobrar", "DATO NO CARGADO" ) ) ) ) -> Clientes a cobrar | C36: =IF(J36="", "", IFERROR(VLOOKUP(J36, Clasificaciones!D:E, 2, FALSE), "DATO NO CARGADO")) -> Moreno Ocampo | D36: 03 mar | E36: 2025 | I36: Invoice 532 | J36: MORENO OCAMPO | L36: 45678 | N36: 250 | O36: =IF(ISBLANK(M36), "", VLOOKUP(D36, 'Info Tipo de Cambio y REM'!$A$24:$B$35, 2, FALSE)) | P36: =IF(NOT(ISBLANK(M36)), M36 / O36, IF(NOT(ISBLANK(N36)), N36, "")) -> 250
A37: Clientes a cobrar | B37: =IF( A37="", "", IF( OR(A37="Santander-Galicia-Nación", A37="Bank Of America", A37="Transferwise", A37="Custodia Socios", A37="Cheques en cartera", A37="Caja"), "Activo Liquido", IF( OR(A37="Otras Inversiones", A37="Santander Inversiones"), "Mediano Plazo", IF( A37="Clientes a cobrar", "Clientes a cobrar", "DATO NO CARGADO" ) ) ) ) -> Clientes a cobrar | C37: =IF(J37="", "", IFERROR(VLOOKUP(J37, Clasificaciones!D:E, 2, FALSE), "DATO NO CARGADO")) -> Warner | D37: 03 mar | E37: 2025 | I37: Invoice 525 | J37: WARNER BROS | L37: 45726 | N37: 13450 | O37: =IF(ISBLANK(M37), "", VLOOKUP(D37, 'Info Tipo de Cambio y REM'!$A$24:$B$35, 2, FALSE)) | P37: =IF(NOT(ISBLANK(M37)), M37 / O37, IF(NOT(ISBLANK(N37)), N37, "")) -> 13450
A38: Clientes a cobrar | B38: =IF( A38="", "", IF( OR(A38="Santander-Galicia-Nación", A38="Bank Of America", A38="Transferwise", A38="Custodia Socios", A38="Cheques en cartera", A38="Caja"), "Activo Liquido", IF( OR(A38="Otras Inversiones", A38="Santander Inversiones"), "Mediano Plazo", IF( A38="Clientes a cobrar", "Clientes a cobrar", "DATO NO CARGADO" ) ) ) ) -> Clientes a cobrar | C38: =IF(J38="", "", IFERROR(VLOOKUP(J38, Clasificaciones!D:E, 2, FALSE), "DATO NO CARGADO")) -> Warner | D38: 03 mar | E38: 2025 | I38: Invoice 534 | J38: WARNER BROS | L38: 45750 | N38: 13450 | O38: =IF(ISBLANK(M38), "", VLOOKUP(D38, 'Info Tipo de Cambio y REM'!$A$24:$B$35, 2, FALSE)) | P38: =IF(NOT(ISBLANK(M38)), M38 / O38, IF(NOT(ISBLANK(N38)), N38, "")) -> 13450
A39: Clientes a cobrar | B39: =IF( A39="", "", IF( OR(A39="Santander-Galicia-Nación", A39="Bank Of America", A39="Transferwise", A39="Custodia Socios", A39="Cheques en cartera", A39="Caja"), "Activo Liquido", IF( OR(A39="Otras Inversiones", A39="Santander Inversiones"), "Mediano Plazo", IF( A39="Clientes a cobrar", "Clientes a cobrar", "DATO NO CARGADO" ) ) ) ) -> Clientes a cobrar | C39: =IF(J39="", "", IFERROR(VLOOKUP(J39, Clasificaciones!D:E, 2, FALSE), "DATO NO CARGADO")) -> Warner | D39: 03 mar | E39: 2025 | I39: Invoice 547 | J39: WARNER BROS | L39: 45782 | N39: 13450 | O39: =IF(ISBLANK(M39), "", VLOOKUP(D39, 'Info Tipo de Cambio y REM'!$A$24:$B$35, 2, FALSE)) | P39: =IF(NOT(ISBLANK(M39)), M39 / O39, IF(NOT(ISBLANK(N39)), N39, "")) -> 13450
A40: Clientes a cobrar | B40: =IF( A40="", "", IF( OR(A40="Santander-Galicia-Nación", A40="Bank Of America", A40="Transferwise", A40="Custodia Socios", A40="Cheques en cartera", A40="Caja"), "Activo Liquido", IF( OR(A40="Otras Inversiones", A40="Santander Inversiones"), "Mediano Plazo", IF( A40="Clientes a cobrar", "Clientes a cobrar", "DATO NO CARGADO" ) ) ) ) -> Clientes a cobrar | C40: =IF(J40="", "", IFERROR(VLOOKUP(J40, Clasificaciones!D:E, 2, FALSE), "DATO NO CARGADO")) -> Warner | D40: 03 mar | E40: 2025 | I40: Invoice 553 | J40: WARNER BROS | L40: 45813 | N40: 13450 | O40: =IF(ISBLANK(M40), "", VLOOKUP(D40, 'Info Tipo de Cambio y REM'!$A$24:$B$35, 2, FALSE)) | P40: =IF(NOT(ISBLANK(M40)), M40 / O40, IF(NOT(ISBLANK(N40)), N40, "")) -> 13450
A41: Clientes a cobrar | B41: =IF( A41="", "", IF( OR(A41="Santander-Galicia-Nación", A41="Bank Of America", A41="Transferwise", A41="Custodia Socios", A41="Cheques en cartera", A41="Caja"), "Activo Liquido", IF( OR(A41="Otras Inversiones", A41="Santander Inversiones"), "Mediano Plazo", IF( A41="Clientes a cobrar", "Clientes a cobrar", "DATO NO CARGADO" ) ) ) ) -> Clientes a cobrar | C41: =IF(J41="", "", IFERROR(VLOOKUP(J41, Clasificaciones!D:E, 2, FALSE), "DATO NO CARGADO")) -> Vertical Media | D41: 03 mar | E41: 2025 | I41: Invoice 560 | J41: VERTICAL MEDIA | L41: 45757 | N41: 1750 | O41: =IF(ISBLANK(M41), "", VLOOKUP(D41, 'Info Tipo de Cambio y REM'!$A$24:$B$35, 2, FALSE)) | P41: =IF(NOT(ISBLANK(M41)), M41 / O41, IF(NOT(ISBLANK(N41)), N41, "")) -> 1750
A42: Clientes a cobrar | B42: =IF( A42="", "", IF( OR(A42="Santander-Galicia-Nación", A42="Bank Of America", A42="Transferwise", A42="Custodia Socios", A42="Cheques en cartera", A42="Caja"), "Activo Liquido", IF( OR(A42="Otras Inversiones", A42="Santander Inversiones"), "Mediano Plazo", IF( A42="Clientes a cobrar", "Clientes a cobrar", "DATO NO CARGADO" ) ) ) ) -> Clientes a cobrar | C42: Detroit | D42: 03 mar | E42: 2025 | H42: 45748 | M42: 771250 | O42: =IF(ISBLANK(M42), "", VLOOKUP(D42, 'Info Tipo de Cambio y REM'!$A$24:$B$35, 2, FALSE)) -> #N/A | P42: =IF(NOT(ISBLANK(M42)), M42 / O42, IF(NOT(ISBLANK(N42)), N42, "")) -> #N/A
A43: Santander-Galicia-Nación | B43: =IF( A43="", "", IF( OR(A43="Santander-Galicia-Nación", A43="Bank Of America", A43="Transferwise", A43="Custodia Socios", A43="Cheques en cartera", A43="Caja"), "Activo Liquido", IF( OR(A43="Otras Inversiones", A43="Santander Inversiones"), "Mediano Plazo", IF( A43="Clientes a cobrar", "Clientes a cobrar", "DATO NO CARGADO" ) ) ) ) -> Activo Liquido | C43: =IF(J43="", "", IFERROR(VLOOKUP(J43, Clasificaciones!D:E, 2, FALSE), "DATO NO CARGADO")) | D43: 04 abr | E43: 2025 | M43: 5365042 | O43: =IF(ISBLANK(M43), "", VLOOKUP(D43, 'Info Tipo de Cambio y REM'!$A$24:$B$35, 2, FALSE)) -> #N/A | P43: =IF(NOT(ISBLANK(M43)), M43 / O43, IF(NOT(ISBLANK(N43)), N43, "")) -> #N/A
A44: Bank Of America | B44: =IF( A44="", "", IF( OR(A44="Santander-Galicia-Nación", A44="Bank Of America", A44="Transferwise", A44="Custodia Socios", A44="Cheques en cartera", A44="Caja"), "Activo Liquido", IF( OR(A44="Otras Inversiones", A44="Santander Inversiones"), "Mediano Plazo", IF( A44="Clientes a cobrar", "Clientes a cobrar", "DATO NO CARGADO" ) ) ) ) -> Activo Liquido | C44: =IF(J44="", "", IFERROR(VLOOKUP(J44, Clasificaciones!D:E, 2, FALSE), "DATO NO CARGADO")) | D44: 04 abr | E44: 2025 | N44: -27709 | O44: =IF(ISBLANK(M44), "", VLOOKUP(D44, 'Info Tipo de Cambio y REM'!$A$24:$B$35, 2, FALSE)) | P44: =IF(NOT(ISBLANK(M44)), M44 / O44, IF(NOT(ISBLANK(N44)), N44, "")) -> -27709
A45: Transferwise | B45: =IF( A45="", "", IF( OR(A45="Santander-Galicia-Nación", A45="Bank Of America", A45="Transferwise", A45="Custodia Socios", A45="Cheques en cartera", A45="Caja"), "Activo Liquido", IF( OR(A45="Otras Inversiones", A45="Santander Inversiones"), "Mediano Plazo", IF( A45="Clientes a cobrar", "Clientes a cobrar", "DATO NO CARGADO" ) ) ) ) -> Activo Liquido | C45: =IF(J45="", "", IFERROR(VLOOKUP(J45, Clasificaciones!D:E, 2, FALSE), "DATO NO CARGADO")) | D45: 04 abr | E45: 2025 | N45: 230 | O45: =IF(ISBLANK(M45), "", VLOOKUP(D45, 'Info Tipo de Cambio y REM'!$A$24:$B$35, 2, FALSE)) | P45: =IF(NOT(ISBLANK(M45)), M45 / O45, IF(NOT(ISBLANK(N45)), N45, "")) -> 230
A46: Otras Inversiones | B46: =IF( A46="", "", IF( OR(A46="Santander-Galicia-Nación", A46="Bank Of America", A46="Transferwise", A46="Custodia Socios", A46="Cheques en cartera", A46="Caja"), "Activo Liquido", IF( OR(A46="Otras Inversiones", A46="Santander Inversiones"), "Mediano Plazo", IF( A46="Clientes a cobrar", "Clientes a cobrar", "DATO NO CARGADO" ) ) ) ) -> Mediano Plazo | C46: =IF(J46="", "", IFERROR(VLOOKUP(J46, Clasificaciones!D:E, 2, FALSE), "DATO NO CARGADO")) | D46: 04 abr | E46: 2025 | N46: 2517 | O46: =IF(ISBLANK(M46), "", VLOOKUP(D46, 'Info Tipo de Cambio y REM'!$A$24:$B$35, 2, FALSE)) | P46: =IF(NOT(ISBLANK(M46)), M46 / O46, IF(NOT(ISBLANK(N46)), N46, "")) -> 2517
A47: Clientes a cobrar | B47: =IF( A47="", "", IF( OR(A47="Santander-Galicia-Nación", A47="Bank Of America", A47="Transferwise", A47="Custodia Socios", A47="Cheques en cartera", A47="Caja"), "Activo Liquido", IF( OR(A47="Otras Inversiones", A47="Santander Inversiones"), "Mediano Plazo", IF( A47="Clientes a cobrar", "Clientes a cobrar", "DATO NO CARGADO" ) ) ) ) -> Clientes a cobrar | C47: =IF(J47="", "", IFERROR(VLOOKUP(J47, Clasificaciones!D:E, 2, FALSE), "DATO NO CARGADO")) -> Warner | D47: 04 abr | E47: 2025 | H47: 45692 | I47: Invoice 547 | J47: WARNER BROS | L47: 45782 | N47: 13450 | O47: =IF(ISBLANK(M47), "", VLOOKUP(D47, 'Info Tipo de Cambio y REM'!$A$24:$B$35, 2, FALSE)) | P47: =IF(NOT(ISBLANK(M47)), M47 / O47, IF(NOT(ISBLANK(N47)), N47, "")) -> 13450
A48: Clientes a cobrar | B48: =IF( A48="", "", IF( OR(A48="Santander-Galicia-Nación", A48="Bank Of America", A48="Transferwise", A48="Custodia Socios", A48="Cheques en cartera", A48="Caja"), "Activo Liquido", IF( OR(A48="Otras Inversiones", A48="Santander Inversiones"), "Mediano Plazo", IF( A48="Clientes a cobrar", "Clientes a cobrar", "DATO NO CARGADO" ) ) ) ) -> Clientes a cobrar | C48: =IF(J48="", "", IFERROR(VLOOKUP(J48, Clasificaciones!D:E, 2, FALSE), "DATO NO CARGADO")) -> Warner | D48: 04 abr | E48: 2025 | H48: 45723 | I48: Invoice 553 | J48: WARNER BROS | L48: 45813 | N48: 13450 | O48: =IF(ISBLANK(M48), "", VLOOKUP(D48, 'Info Tipo de Cambio y REM'!$A$24:$B$35, 2, FALSE)) | P48: =IF(NOT(ISBLANK(M48)), M48 / O48, IF(NOT(ISBLANK(N48)), N48, "")) -> 13450
A49: Clientes a cobrar | B49: =IF( A49="", "", IF( OR(A49="Santander-Galicia-Nación", A49="Bank Of America", A49="Transferwise", A49="Custodia Socios", A49="Cheques en cartera", A49="Caja"), "Activo Liquido", IF( OR(A49="Otras Inversiones", A49="Santander Inversiones"), "Mediano Plazo", IF( A49="Clientes a cobrar", "Clientes a cobrar", "DATO NO CARGADO" ) ) ) ) -> Clientes a cobrar | C49: =IF(J49="", "", IFERROR(VLOOKUP(J49, Clasificaciones!D:E, 2, FALSE), "DATO NO CARGADO")) -> Warner | D49: 04 abr | E49: 2025 | H49: 45751 | I49: Invoice 568 | J49: WARNER BROS | L49: 45841 | N49: 13450 | O49: =IF(ISBLANK(M49), "", VLOOKUP(D49, 'Info Tipo de Cambio y REM'!$A$24:$B$35, 2, FALSE)) | P49: =IF(NOT(ISBLANK(M49)), M49 / O49, IF(NOT(ISBLANK(N49)), N49, "")) -> 13450
A50: Clientes a cobrar | B50: =IF( A50="", "", IF( OR(A50="Santander-Galicia-Nación", A50="Bank Of America", A50="Transferwise", A50="Custodia Socios", A50="Cheques en cartera", A50="Caja"), "Activo Liquido", IF( OR(A50="Otras Inversiones", A50="Santander Inversiones"), "Mediano Plazo", IF( A50="Clientes a cobrar", "Clientes a cobrar", "DATO NO CARGADO" ) ) ) ) -> Clientes a cobrar | C50: =IF(J50="", "", IFERROR(VLOOKUP(J50, Clasificaciones!D:E, 2, FALSE), "DATO NO CARGADO")) -> Warner | D50: 04 abr | E50: 2025 | H50: 45770 | I50: Invoice 575 | J50: WARNER BROS | L50: 45865 | N50: 1300 | O50: =IF(ISBLANK(M50), "", VLOOKUP(D50, 'Info Tipo de Cambio y REM'!$A$24:$B$35, 2, FALSE)) | P50: =IF(NOT(ISBLANK(M50)), M50 / O50, IF(NOT(ISBLANK(N50)), N50, "")) -> 1300
A51: Clientes a cobrar | B51: =IF( A51="", "", IF( OR(A51="Santander-Galicia-Nación", A51="Bank Of America", A51="Transferwise", A51="Custodia Socios", A51="Cheques en cartera", A51="Caja"), "Activo Liquido", IF( OR(A51="Otras Inversiones", A51="Santander Inversiones"), "Mediano Plazo", IF( A51="Clientes a cobrar", "Clientes a cobrar", "DATO NO CARGADO" ) ) ) ) -> Clientes a cobrar | C51: =IF(J51="", "", IFERROR(VLOOKUP(J51, Clasificaciones!D:E, 2, FALSE), "DATO NO CARGADO")) -> Moreno Ocampo | D51: 04 abr | E51: 2025 | H51: 45649 | I51: Invoice 532 | J51: MORENO OCAMPO | L51: 45678 | N51: 250 | O51: =IF(ISBLANK(M51), "", VLOOKUP(D51, 'Info Tipo de Cambio y REM'!$A$24:$B$35, 2, FALSE)) | P51: =IF(NOT(ISBLANK(M51)), M51 / O51, IF(NOT(ISBLANK(N51)), N51, "")) -> 250
A52: Clientes a cobrar | B52: =IF( A52="", "", IF( OR(A52="Santander-Galicia-Nación", A52="Bank Of America", A52="Transferwise", A52="Custodia Socios", A52="Cheques en cartera", A52="Caja"), "Activo Liquido", IF( OR(A52="Otras Inversiones", A52="Santander Inversiones"), "Mediano Plazo", IF( A52="Clientes a cobrar", "Clientes a cobrar", "DATO NO CARGADO" ) ) ) ) -> Clientes a cobrar | C52: =IF(J52="", "", IFERROR(VLOOKUP(J52, Clasificaciones!D:E, 2, FALSE), "DATO NO CARGADO")) -> Coelsa | D52: 04 abr | E52: 2025 | H52: 45748 | I52: Factura de Crédito MiPyME (FCE) N° A-00008-00000938 | J52: COMPENSADORA ELECTRONICA SA | L52: 45778 | M52: 4832747 | O52: =IF(ISBLANK(M52), "", VLOOKUP(D52, 'Info Tipo de Cambio y REM'!$A$24:$B$35, 2, FALSE)) -> #N/A | P52: =IF(NOT(ISBLANK(M52)), M52 / O52, IF(NOT(ISBLANK(N52)), N52, "")) -> #N/A
A53: Clientes a cobrar | B53: =IF( A53="", "", IF( OR(A53="Santander-Galicia-Nación", A53="Bank Of America", A53="Transferwise", A53="Custodia Socios", A53="Cheques en cartera", A53="Caja"), "Activo Liquido", IF( OR(A53="Otras Inversiones", A53="Santander Inversiones"), "Mediano Plazo", IF( A53="Clientes a cobrar", "Clientes a cobrar", "DATO NO CARGADO" ) ) ) ) -> Clientes a cobrar | C53: =IF(J53="", "", IFERROR(VLOOKUP(J53, Clasificaciones!D:E, 2, FALSE), "DATO NO CARGADO")) -> Coca-Cola | D53: 04 abr | E53: 2025 | H53: 45775 | I53: Invoice 576 | J53: SERVICIOS INTEGRADOS DE ADMINISTRACION Y ALTA GER | L53: 45860 | N53: 5568 | O53: =IF(ISBLANK(M53), "", VLOOKUP(D53, 'Info Tipo de Cambio y REM'!$A$24:$B$35, 2, FALSE)) | P53: =IF(NOT(ISBLANK(M53)), M53 / O53, IF(NOT(ISBLANK(N53)), N53, "")) -> 5568
A54: Clientes a cobrar | B54: =IF( A54="", "", IF( OR(A54="Santander-Galicia-Nación", A54="Bank Of America", A54="Transferwise", A54="Custodia Socios", A54="Cheques en cartera", A54="Caja"), "Activo Liquido", IF( OR(A54="Otras Inversiones", A54="Santander Inversiones"), "Mediano Plazo", IF( A54="Clientes a cobrar", "Clientes a cobrar", "DATO NO CARGADO" ) ) ) ) -> Clientes a cobrar | C54: Detroit | D54: 04 abr | E54: 2025 | H54: 45748 | M54: 792000 | O54: =IF(ISBLANK(M54), "", VLOOKUP(D54, 'Info Tipo de Cambio y REM'!$A$24:$B$35, 2, FALSE)) -> #N/A | P54: =IF(NOT(ISBLANK(M54)), M54 / O54, IF(NOT(ISBLANK(N54)), N54, "")) -> #N/A
A55: Clientes a cobrar | B55: =IF( A55="", "", IF( OR(A55="Santander-Galicia-Nación", A55="Bank Of America", A55="Transferwise", A55="Custodia Socios", A55="Cheques en cartera", A55="Caja"), "Activo Liquido", IF( OR(A55="Otras Inversiones", A55="Santander Inversiones"), "Mediano Plazo", IF( A55="Clientes a cobrar", "Clientes a cobrar", "DATO NO CARGADO" ) ) ) ) -> Clientes a cobrar | C55: Detroit | D55: 04 abr | E55: 2025 | H55: 45748 | M55: 144000 | O55: =IF(ISBLANK(M55), "", VLOOKUP(D55, 'Info Tipo de Cambio y REM'!$A$24:$B$35, 2, FALSE)) -> #N/A | P55: =IF(NOT(ISBLANK(M55)), M55 / O55, IF(NOT(ISBLANK(N55)), N55, "")) -> #N/A
A56: Clientes a cobrar | B56: =IF( A56="", "", IF( OR(A56="Santander-Galicia-Nación", A56="Bank Of America", A56="Transferwise", A56="Custodia Socios", A56="Cheques en cartera", A56="Caja"), "Activo Liquido", IF( OR(A56="Otras Inversiones", A56="Santander Inversiones"), "Mediano Plazo", IF( A56="Clientes a cobrar", "Clientes a cobrar", "DATO NO CARGADO" ) ) ) ) -> Clientes a cobrar | C56: Play Digital S.A (Modo) | D56: 04 abr | E56: 2025 | H56: 45748 | M56: 5095279.7 | O56: =IF(ISBLANK(M56), "", VLOOKUP(D56, 'Info Tipo de Cambio y REM'!$A$24:$B$35, 2, FALSE)) -> #N/A | P56: =IF(NOT(ISBLANK(M56)), M56 / O56, IF(NOT(ISBLANK(N56)), N56, "")) -> #N/A
A57: Clientes a cobrar | B57: =IF( A57="", "", IF( OR(A57="Santander-Galicia-Nación", A57="Bank Of America", A57="Transferwise", A57="Custodia Socios", A57="Cheques en cartera", A57="Caja"), "Activo Liquido", IF( OR(A57="Otras Inversiones", A57="Santander Inversiones"), "Mediano Plazo", IF( A57="Clientes a cobrar", "Clientes a cobrar", "DATO NO CARGADO" ) ) ) ) -> Clientes a cobrar | C57: =IF(J57="", "", IFERROR(VLOOKUP(J57, Clasificaciones!D:E, 2, FALSE), "DATO NO CARGADO")) -> Play Digital S.A (Modo) | D57: 05 may | E57: 2025 | F57: Si | H57: 45782 | I57: A-00008-00001966 | J57: PLAY DIGITAL S. A. | L57: 45813 | M57: 5095279.7 | O57: =IF(ISBLANK(M57), "", VLOOKUP(D57, 'Info Tipo de Cambio y REM'!$A$24:$B$35, 2, FALSE)) -> #N/A | P57: =IF(NOT(ISBLANK(M57)), M57 / O57, IF(NOT(ISBLANK(N57)), N57, "")) -> #N/A
A58: Clientes a cobrar | B58: =IF( A58="", "", IF( OR(A58="Santander-Galicia-Nación", A58="Bank Of America", A58="Transferwise", A58="Custodia Socios", A58="Cheques en cartera", A58="Caja"), "Activo Liquido", IF( OR(A58="Otras Inversiones", A58="Santander Inversiones"), "Mediano Plazo", IF( A58="Clientes a cobrar", "Clientes a cobrar", "DATO NO CARGADO" ) ) ) ) -> Clientes a cobrar | C58: =IF(J58="", "", IFERROR(VLOOKUP(J58, Clasificaciones!D:E, 2, FALSE), "DATO NO CARGADO")) -> Coelsa | D58: 05 may | E58: 2025 | F58: Si | H58: 45782 | I58: A-00008-00000951 | J58: COMPENSADORA ELECTRONICA SA | L58: 45813 | M58: 4832747.2 | O58: =IF(ISBLANK(M58), "", VLOOKUP(D58, 'Info Tipo de Cambio y REM'!$A$24:$B$35, 2, FALSE)) -> #N/A | P58: =IF(NOT(ISBLANK(M58)), M58 / O58, IF(NOT(ISBLANK(N58)), N58, "")) -> #N/A
A59: Clientes a cobrar | B59: =IF( A59="", "", IF( OR(A59="Santander-Galicia-Nación", A59="Bank Of America", A59="Transferwise", A59="Custodia Socios", A59="Cheques en cartera", A59="Caja"), "Activo Liquido", IF( OR(A59="Otras Inversiones", A59="Santander Inversiones"), "Mediano Plazo", IF( A59="Clientes a cobrar", "Clientes a cobrar", "DATO NO CARGADO" ) ) ) ) -> Clientes a cobrar | C59: =IF(J59="", "", IFERROR(VLOOKUP(J59, Clasificaciones!D:E, 2, FALSE), "DATO NO CARGADO")) -> Vertical Media | D59: 05 may | E59: 2025 | F59: Si | H59: 45782 | I59: INVOICE 582 | J59: VERTICAL MEDIA LLC | L59: 45814 | N59: 1750 | O59: =IF(ISBLANK(M59), "", VLOOKUP(D59, 'Info Tipo de Cambio y REM'!$A$24:$B$35, 2, FALSE)) | P59: =IF(NOT(ISBLANK(M59)), M59 / O59, IF(NOT(ISBLANK(N59)), N59, "")) -> 1750
A60: Clientes a cobrar | B60: =IF( A60="", "", IF( OR(A60="Santander-Galicia-Nación", A60="Bank Of America", A60="Transferwise", A60="Custodia Socios", A60="Cheques en cartera", A60="Caja"), "Activo Liquido", IF( OR(A60="Otras Inversiones", A60="Santander Inversiones"), "Mediano Plazo", IF( A60="Clientes a cobrar", "Clientes a cobrar", "DATO NO CARGADO" ) ) ) ) -> Clientes a cobrar | C60: =IF(J60="", "", IFERROR(VLOOKUP(J60, Clasificaciones!D:E, 2, FALSE), "DATO NO CARGADO")) -> Detroit | D60: 05 may | E60: 2025 | F60: Si | H60: 45779 | I60: FEE MAYO | J60: DETROIT | L60: 45809 | M60: 771250 | O60: =IF(ISBLANK(M60), "", VLOOKUP(D60, 'Info Tipo de Cambio y REM'!$A$24:$B$35, 2, FALSE)) -> #N/A | P60: =IF(NOT(ISBLANK(M60)), M60 / O60, IF(NOT(ISBLANK(N60)), N60, "")) -> #N/A
A61: Santander-Galicia-Nación | B61: =IF( A61="", "", IF( OR(A61="Santander-Galicia-Nación", A61="Bank Of America", A61="Transferwise", A61="Custodia Socios", A61="Cheques en cartera", A61="Caja"), "Activo Liquido", IF( OR(A61="Otras Inversiones", A61="Santander Inversiones"), "Mediano Plazo", IF( A61="Clientes a cobrar", "Clientes a cobrar", "DATO NO CARGADO" ) ) ) ) -> Activo Liquido | C61: =IF(J61="", "", IFERROR(VLOOKUP(J61, Clasificaciones!D:E, 2, FALSE), "DATO NO CARGADO")) | D61: 05 may | E61: 2025 | M61: 7822062 | O61: =IF(ISBLANK(M61), "", VLOOKUP(D61, 'Info Tipo de Cambio y REM'!$A$24:$B$35, 2, FALSE)) -> #N/A | P61: =IF(NOT(ISBLANK(M61)), M61 / O61, IF(NOT(ISBLANK(N61)), N61, "")) -> #N/A
A62: Bank Of America | B62: =IF( A62="", "", IF( OR(A62="Santander-Galicia-Nación", A62="Bank Of America", A62="Transferwise", A62="Custodia Socios", A62="Cheques en cartera", A62="Caja"), "Activo Liquido", IF( OR(A62="Otras Inversiones", A62="Santander Inversiones"), "Mediano Plazo", IF( A62="Clientes a cobrar", "Clientes a cobrar", "DATO NO CARGADO" ) ) ) ) -> Activo Liquido | C62: =IF(J62="", "", IFERROR(VLOOKUP(J62, Clasificaciones!D:E, 2, FALSE), "DATO NO CARGADO")) | D62: 05 may | E62: 2025 | N62: -49062 | O62: =IF(ISBLANK(M62), "", VLOOKUP(D62, 'Info Tipo de Cambio y REM'!$A$24:$B$35, 2, FALSE)) | P62: =IF(NOT(ISBLANK(M62)), M62 / O62, IF(NOT(ISBLANK(N62)), N62, "")) -> -49062
A63: Otras Inversiones | B63: =IF( A63="", "", IF( OR(A63="Santander-Galicia-Nación", A63="Bank Of America", A63="Transferwise", A63="Custodia Socios", A63="Cheques en cartera", A63="Caja"), "Activo Liquido", IF( OR(A63="Otras Inversiones", A63="Santander Inversiones"), "Mediano Plazo", IF( A63="Clientes a cobrar", "Clientes a cobrar", "DATO NO CARGADO" ) ) ) ) -> Mediano Plazo | C63: =IF(J63="", "", IFERROR(VLOOKUP(J63, Clasificaciones!D:E, 2, FALSE), "DATO NO CARGADO")) | D63: 05 may | E63: 2025 | N63: 2682 | O63: =IF(ISBLANK(M63), "", VLOOKUP(D63, 'Info Tipo de Cambio y REM'!$A$24:$B$35, 2, FALSE)) | P63: =IF(NOT(ISBLANK(M63)), M63 / O63, IF(NOT(ISBLANK(N63)), N63, "")) -> 2682
A64: Clientes a cobrar | B64: Clientes a cobrar | C64: Moreno Ocampo | D64: 05 may | E64: 2025 | F64: No | H64: 45649 | I64: INVOICE 532 | J64: MORENO OCAMPO | L64: 45649 | N64: 250 | O64: =IF(ISBLANK(M64), "", VLOOKUP(D64, 'Info Tipo de Cambio y REM'!$A$24:$B$35, 2, FALSE)) | P64: =IF(NOT(ISBLANK(M64)), M64 / O64, IF(NOT(ISBLANK(N64)), N64, "")) -> 250
A65: Clientes a cobrar | B65: Clientes a cobrar | C65: Warner | D65: 05 may | E65: 2025 | F65: No | H65: 45723 | I65: INVOICE 553 | J65: WARNER | L65: 45813 | N65: 13450 | O65: =IF(ISBLANK(M65), "", VLOOKUP(D65, 'Info Tipo de Cambio y REM'!$A$24:$B$35, 2, FALSE)) | P65: =IF(NOT(ISBLANK(M65)), M65 / O65, IF(NOT(ISBLANK(N65)), N65, "")) -> 13450
A66: Clientes a cobrar | B66: Clientes a cobrar | C66: Warner | D66: 05 may | E66: 2025 | F66: No | H66: 45751 | I66: INVOICE 568 | J66: WARNER | L66: 45841 | N66: 13450 | O66: =IF(ISBLANK(M66), "", VLOOKUP(D66, 'Info Tipo de Cambio y REM'!$A$24:$B$35, 2, FALSE)) | P66: =IF(NOT(ISBLANK(M66)), M66 / O66, IF(NOT(ISBLANK(N66)), N66, "")) -> 13450
A67: Clientes a cobrar | B67: Clientes a cobrar | C67: Warner | D67: 05 may | E67: 2025 | F67: No | H67: 45770 | I67: INVOICE 575 | J67: WARNER | L67: 45860 | N67: 1300 | O67: =IF(ISBLANK(M67), "", VLOOKUP(D67, 'Info Tipo de Cambio y REM'!$A$24:$B$35, 2, FALSE)) | P67: =IF(NOT(ISBLANK(M67)), M67 / O67, IF(NOT(ISBLANK(N67)), N67, "")) -> 1300
A68: Clientes a cobrar | B68: Clientes a cobrar | C68: Coca-Cola | D68: 05 may | E68: 2025 | F68: No | H68: 45775 | I68: INVOICE 576 | J68: SERVICIOS INTEGRADOS DE ADMINISTRACION Y ALTA GER | L68: 45865 | N68: 5568 | O68: =IF(ISBLANK(M68), "", VLOOKUP(D68, 'Info Tipo de Cambio y REM'!$A$24:$B$35, 2, FALSE)) | P68: =IF(NOT(ISBLANK(M68)), M68 / O68, IF(NOT(ISBLANK(N68)), N68, "")) -> 5568
A69: Clientes a cobrar | B69: =IF( A69="", "", IF( OR(A69="Santander-Galicia-Nación", A69="Bank Of America", A69="Transferwise", A69="Custodia Socios", A69="Cheques en cartera", A69="Caja"), "Activo Liquido", IF( OR(A69="Otras Inversiones", A69="Santander Inversiones"), "Mediano Plazo", IF( A69="Clientes a cobrar", "Clientes a cobrar", "DATO NO CARGADO" ) ) ) ) -> Clientes a cobrar | C69: =IF(J69="", "", IFERROR(VLOOKUP(J69, Clasificaciones!D:E, 2, FALSE), "DATO NO CARGADO")) -> Play Digital S.A (Modo) | D69: 06 jun | E69: 2025 | F69: Si | H69: 45810 | I69: A-00008-00001977 | J69: PLAY DIGITAL S. A. | L69: 45840 | M69: 5562007 | O69: =IF(ISBLANK(M69), "", VLOOKUP(D69, 'Info Tipo de Cambio y REM'!$A$24:$B$35, 2, FALSE)) -> #N/A | P69: =IF(NOT(ISBLANK(M69)), M69 / O69, IF(NOT(ISBLANK(N69)), N69, "")) -> #N/A
A70: Clientes a cobrar | B70: =IF( A70="", "", IF( OR(A70="Santander-Galicia-Nación", A70="Bank Of America", A70="Transferwise", A70="Custodia Socios", A70="Cheques en cartera", A70="Caja"), "Activo Liquido", IF( OR(A70="Otras Inversiones", A70="Santander Inversiones"), "Mediano Plazo", IF( A70="Clientes a cobrar", "Clientes a cobrar", "DATO NO CARGADO" ) ) ) ) -> Clientes a cobrar | C70: =IF(J70="", "", IFERROR(VLOOKUP(J70, Clasificaciones!D:E, 2, FALSE), "DATO NO CARGADO")) -> Coelsa | D70: 06 jun | E70: 2025 | F70: Si | H70: 45810 | I70: A-00008-00000958 | J70: COMPENSADORA ELECTRONICA SA | L70: 45840 | M70: 5275425.8 | O70: =IF(ISBLANK(M70), "", VLOOKUP(D70, 'Info Tipo de Cambio y REM'!$A$24:$B$35, 2, FALSE)) -> #N/A | P70: =IF(NOT(ISBLANK(M70)), M70 / O70, IF(NOT(ISBLANK(N70)), N70, "")) -> #N/A
A71: Clientes a cobrar | B71: =IF( A71="", "", IF( OR(A71="Santander-Galicia-Nación", A71="Bank Of America", A71="Transferwise", A71="Custodia Socios", A71="Cheques en cartera", A71="Caja"), "Activo Liquido", IF( OR(A71="Otras Inversiones", A71="Santander Inversiones"), "Mediano Plazo", IF( A71="Clientes a cobrar", "Clientes a cobrar", "DATO NO CARGADO" ) ) ) ) -> Clientes a cobrar | C71: =IF(J71="", "", IFERROR(VLOOKUP(J71, Clasificaciones!D:E, 2, FALSE), "DATO NO CARGADO")) -> Detroit | D71: 06 jun | E71: 2025 | F71: Si | H71: 45810 | I71: FEE JUNIO | J71: DETROIT | L71: 45840 | M71: 1071885 | O71: =IF(ISBLANK(M71), "", VLOOKUP(D71, 'Info Tipo de Cambio y REM'!$A$24:$B$35, 2, FALSE)) -> #N/A | P71: =IF(NOT(ISBLANK(M71)), M71 / O71, IF(NOT(ISBLANK(N71)), N71, "")) -> #N/A
A72: Clientes a cobrar | B72: =IF( A72="", "", IF( OR(A72="Santander-Galicia-Nación", A72="Bank Of America", A72="Transferwise", A72="Custodia Socios", A72="Cheques en cartera", A72="Caja"), "Activo Liquido", IF( OR(A72="Otras Inversiones", A72="Santander Inversiones"), "Mediano Plazo", IF( A72="Clientes a cobrar", "Clientes a cobrar", "DATO NO CARGADO" ) ) ) ) -> Clientes a cobrar | C72: =IF(J72="", "", IFERROR(VLOOKUP(J72, Clasificaciones!D:E, 2, FALSE), "DATO NO CARGADO")) -> Vertical Media | D72: 06 jun | E72: 2025 | F72: Si | H72: 45810 | I72: INVOICE 590 | J72: VERTICAL MEDIA LLC | L72: 45840 | N72: 1750 | O72: =IF(ISBLANK(M72), "", VLOOKUP(D72, 'Info Tipo de Cambio y REM'!$A$24:$B$35, 2, FALSE)) | P72: =IF(NOT(ISBLANK(M72)), M72 / O72, IF(NOT(ISBLANK(N72)), N72, "")) -> 1750
A73: Clientes a cobrar | B73: =IF( A73="", "", IF( OR(A73="Santander-Galicia-Nación", A73="Bank Of America", A73="Transferwise", A73="Custodia Socios", A73="Cheques en cartera", A73="Caja"), "Activo Liquido", IF( OR(A73="Otras Inversiones", A73="Santander Inversiones"), "Mediano Plazo", IF( A73="Clientes a cobrar", "Clientes a cobrar", "DATO NO CARGADO" ) ) ) ) -> Clientes a cobrar | C73: =IF(J73="", "", IFERROR(VLOOKUP(J73, Clasificaciones!D:E, 2, FALSE), "DATO NO CARGADO")) -> Uber | D73: 06 jun | E73: 2025 | F73: No | H73: 45827 | I73: INVOICE 595 | J73: UBER | L73: 45888 | N73: 7350 | O73: =IF(ISBLANK(M73), "", VLOOKUP(D73, 'Info Tipo de Cambio y REM'!$A$24:$B$35, 2, FALSE)) | P73: =IF(NOT(ISBLANK(M73)), M73 / O73, IF(NOT(ISBLANK(N73)), N73, "")) -> 7350
A74: Clientes a cobrar | B74: =IF( A74="", "", IF( OR(A74="Santander-Galicia-Nación", A74="Bank Of America", A74="Transferwise", A74="Custodia Socios", A74="Cheques en cartera", A74="Caja"), "Activo Liquido", IF( OR(A74="Otras Inversiones", A74="Santander Inversiones"), "Mediano Plazo", IF( A74="Clientes a cobrar", "Clientes a cobrar", "DATO NO CARGADO" ) ) ) ) -> Clientes a cobrar | C74: =IF(J74="", "", IFERROR(VLOOKUP(J74, Clasificaciones!D:E, 2, FALSE), "DATO NO CARGADO")) -> Detroit | D74: 06 jun | E74: 2025 | F74: Si | H74: 45838 | I74: NOTA DE CREDITO | J74: DETROIT | L74: 45838 | M74: -20734 | O74: =IF(ISBLANK(M74), "", VLOOKUP(D74, 'Info Tipo de Cambio y REM'!$A$24:$B$35, 2, FALSE)) -> #N/A | P74: =IF(NOT(ISBLANK(M74)), M74 / O74, IF(NOT(ISBLANK(N74)), N74, "")) -> #N/A
A75: Bank Of America | B75: =IF( A75="", "", IF( OR(A75="Santander-Galicia-Nación", A75="Bank Of America", A75="Transferwise", A75="Custodia Socios", A75="Cheques en cartera", A75="Caja"), "Activo Liquido", IF( OR(A75="Otras Inversiones", A75="Santander Inversiones"), "Mediano Plazo", IF( A75="Clientes a cobrar", "Clientes a cobrar", "DATO NO CARGADO" ) ) ) ) -> Activo Liquido | C75: =IF(J75="", "", IFERROR(VLOOKUP(J75, Clasificaciones!D:E, 2, FALSE), "DATO NO CARGADO")) | D75: 06 jun | E75: 2025 | N75: -91979 | O75: =IF(ISBLANK(M75), "", VLOOKUP(D75, 'Info Tipo de Cambio y REM'!$A$24:$B$35, 2, FALSE)) | P75: =IF(NOT(ISBLANK(M75)), M75 / O75, IF(NOT(ISBLANK(N75)), N75, "")) -> -91979
A76: Santander-Galicia-Nación | B76: =IF( A76="", "", IF( OR(A76="Santander-Galicia-Nación", A76="Bank Of America", A76="Transferwise", A76="Custodia Socios", A76="Cheques en cartera", A76="Caja"), "Activo Liquido", IF( OR(A76="Otras Inversiones", A76="Santander Inversiones"), "Mediano Plazo", IF( A76="Clientes a cobrar", "Clientes a cobrar", "DATO NO CARGADO" ) ) ) ) -> Activo Liquido | C76: =IF(J76="", "", IFERROR(VLOOKUP(J76, Clasificaciones!D:E, 2, FALSE), "DATO NO CARGADO")) | D76: 06 jun | E76: 2025 | M76: 3432410 | O76: =IF(ISBLANK(M76), "", VLOOKUP(D76, 'Info Tipo de Cambio y REM'!$A$24:$B$35, 2, FALSE)) -> #N/A | P76: =IF(NOT(ISBLANK(M76)), M76 / O76, IF(NOT(ISBLANK(N76)), N76, "")) -> #N/A
A77: Otras Inversiones | B77: =IF( A77="", "", IF( OR(A77="Santander-Galicia-Nación", A77="Bank Of America", A77="Transferwise", A77="Custodia Socios", A77="Cheques en cartera", A77="Caja"), "Activo Liquido", IF( OR(A77="Otras Inversiones", A77="Santander Inversiones"), "Mediano Plazo", IF( A77="Clientes a cobrar", "Clientes a cobrar", "DATO NO CARGADO" ) ) ) ) -> Mediano Plazo | C77: =IF(J77="", "", IFERROR(VLOOKUP(J77, Clasificaciones!D:E, 2, FALSE), "DATO NO CARGADO")) | D77: 06 jun | E77: 2025 | N77: 2682 | O77: =IF(ISBLANK(M77), "", VLOOKUP(D77, 'Info Tipo de Cambio y REM'!$A$24:$B$35, 2, FALSE)) | P77: =IF(NOT(ISBLANK(M77)), M77 / O77, IF(NOT(ISBLANK(N77)), N77, "")) -> 2682
A78: Transferwise | B78: =IF( A78="", "", IF( OR(A78="Santander-Galicia-Nación", A78="Bank Of America", A78="Transferwise", A78="Custodia Socios", A78="Cheques en cartera", A78="Caja"), "Activo Liquido", IF( OR(A78="Otras Inversiones", A78="Santander Inversiones"), "Mediano Plazo", IF( A78="Clientes a cobrar", "Clientes a cobrar", "DATO NO CARGADO" ) ) ) ) -> Activo Liquido | C78: =IF(J78="", "", IFERROR(VLOOKUP(J78, Clasificaciones!D:E, 2, FALSE), "DATO NO CARGADO")) | D78: 06 jun | E78: 2025 | N78: 230 | P78: =IF(NOT(ISBLANK(M78)), M78 / O78, IF(NOT(ISBLANK(N78)), N78, "")) -> 230
A79: Clientes a cobrar | B79: Clientes a cobrar | C79: Moreno Ocampo | D79: 06 jun | E79: 2025 | F79: No | H79: 45649 | I79: Invoice 532 | J79: MORENO OCAMPO | L79: 45678 | N79: 250 | O79: =IF(ISBLANK(M79), "", VLOOKUP(D79, 'Info Tipo de Cambio y REM'!$A$24:$B$35, 2, FALSE)) | P79: =IF(NOT(ISBLANK(M79)), M79 / O79, IF(NOT(ISBLANK(N79)), N79, "")) -> 250
A80: Clientes a cobrar | B80: Clientes a cobrar | C80: Warner | D80: 06 jun | E80: 2025 | F80: No | H80: 45723 | I80: INVOICE 553 | J80: WARNER BROS | L80: 45813 | N80: 13450 | O80: =IF(ISBLANK(M80), "", VLOOKUP(D80, 'Info Tipo de Cambio y REM'!$A$24:$B$35, 2, FALSE)) | P80: =IF(NOT(ISBLANK(M80)), M80 / O80, IF(NOT(ISBLANK(N80)), N80, "")) -> 13450
A81: Clientes a cobrar | B81: Clientes a cobrar | C81: Warner | D81: 06 jun | E81: 2025 | F81: No | H81: 45751 | I81: INVOICE 568 | J81: WARNER BROS | L81: 45841 | N81: 13450 | O81: =IF(ISBLANK(M81), "", VLOOKUP(D81, 'Info Tipo de Cambio y REM'!$A$24:$B$35, 2, FALSE)) | P81: =IF(NOT(ISBLANK(M81)), M81 / O81, IF(NOT(ISBLANK(N81)), N81, "")) -> 13450
A82: Clientes a cobrar | B82: Clientes a cobrar | C82: Warner | D82: 06 jun | E82: 2025 | F82: No | H82: 45770 | I82: INVOICE 575 | J82: WARNER BROS | L82: 45860 | N82: 1300 | O82: =IF(ISBLANK(M82), "", VLOOKUP(D82, 'Info Tipo de Cambio y REM'!$A$24:$B$35, 2, FALSE)) | P82: =IF(NOT(ISBLANK(M82)), M82 / O82, IF(NOT(ISBLANK(N82)), N82, "")) -> 1300
A83: Clientes a cobrar | B83: Clientes a cobrar | C83: Coca-Cola | D83: 06 jun | E83: 2025 | F83: No | H83: 45775 | I83: INVOICE 576 | J83: SERVICIOS INTEGRADOS DE ADMINISTRACION Y ALTA GER | L83: 45865 | N83: 5568 | O83: =IF(ISBLANK(M83), "", VLOOKUP(D83, 'Info Tipo de Cambio y REM'!$A$24:$B$35, 2, FALSE)) | P83: =IF(NOT(ISBLANK(M83)), M83 / O83, IF(NOT(ISBLANK(N83)), N83, "")) -> 5568
A84: Clientes a cobrar | B84: =IF( A84="", "", IF( OR(A84="Santander-Galicia-Nación", A84="Bank Of America", A84="Transferwise", A84="Custodia Socios", A84="Cheques en cartera", A84="Caja"), "Activo Liquido", IF( OR(A84="Otras Inversiones", A84="Santander Inversiones"), "Mediano Plazo", IF( A84="Clientes a cobrar", "Clientes a cobrar", "DATO NO CARGADO" ) ) ) ) -> Clientes a cobrar | C84: Coelsa | D84: 07 jul | E84: 2025 | F84: Si | H84: 45839 | I84: A-00008-00000966 | J84: COMPENSADORA ELECTRONICA SA | L84: 45870 | M84: 5275425.8 | O84: =IF(ISBLANK(M84), "", VLOOKUP(D84, 'Info Tipo de Cambio y REM'!$A$24:$B$35, 2, FALSE)) -> #N/A | P84: =IF(NOT(ISBLANK(M84)), M84 / O84, IF(NOT(ISBLANK(N84)), N84, "")) -> #N/A
A85: Clientes a cobrar | B85: =IF( A85="", "", IF( OR(A85="Santander-Galicia-Nación", A85="Bank Of America", A85="Transferwise", A85="Custodia Socios", A85="Cheques en cartera", A85="Caja"), "Activo Liquido", IF( OR(A85="Otras Inversiones", A85="Santander Inversiones"), "Mediano Plazo", IF( A85="Clientes a cobrar", "Clientes a cobrar", "DATO NO CARGADO" ) ) ) ) -> Clientes a cobrar | C85: =IF(J85="", "", IFERROR(VLOOKUP(J85, Clasificaciones!D:E, 2, FALSE), "DATO NO CARGADO")) -> Kimberly Clark | D85: 07 jul | E85: 2025 | F85: No | H85: 45845 | I85: INVOICE 00608 | J85: KIMBERLY | L85: =H85+120 -> 45965 | N85: 8450 | O85: =IF(ISBLANK(M85), "", VLOOKUP(D85, 'Info Tipo de Cambio y REM'!$A$24:$B$35, 2, FALSE)) | P85: =IF(NOT(ISBLANK(M85)), M85 / O85, IF(NOT(ISBLANK(N85)), N85, "")) -> 8450
A86: Clientes a cobrar | B86: =IF( A86="", "", IF( OR(A86="Santander-Galicia-Nación", A86="Bank Of America", A86="Transferwise", A86="Custodia Socios", A86="Cheques en cartera", A86="Caja"), "Activo Liquido", IF( OR(A86="Otras Inversiones", A86="Santander Inversiones"), "Mediano Plazo", IF( A86="Clientes a cobrar", "Clientes a cobrar", "DATO NO CARGADO" ) ) ) ) -> Clientes a cobrar | C86: =IF(J86="", "", IFERROR(VLOOKUP(J86, Clasificaciones!D:E, 2, FALSE), "DATO NO CARGADO")) -> Play Digital S.A (Modo) | D86: 07 jul | E86: 2025 | F86: Si | H86: 45839 | I86: Factura de Venta N° A-00008-00001995 | J86: PLAY DIGITAL S. A. | L86: 45870 | M86: 5562007 | O86: =IF(ISBLANK(M86), "", VLOOKUP(D86, 'Info Tipo de Cambio y REM'!$A$24:$B$35, 2, FALSE)) -> #N/A | P86: =IF(NOT(ISBLANK(M86)), M86 / O86, IF(NOT(ISBLANK(N86)), N86, "")) -> #N/A
A87: Clientes a cobrar | B87: =IF( A87="", "", IF( OR(A87="Santander-Galicia-Nación", A87="Bank Of America", A87="Transferwise", A87="Custodia Socios", A87="Cheques en cartera", A87="Caja"), "Activo Liquido", IF( OR(A87="Otras Inversiones", A87="Santander Inversiones"), "Mediano Plazo", IF( A87="Clientes a cobrar", "Clientes a cobrar", "DATO NO CARGADO" ) ) ) ) -> Clientes a cobrar | C87: =IF(J87="", "", IFERROR(VLOOKUP(J87, Clasificaciones!D:E, 2, FALSE), "DATO NO CARGADO")) -> Detroit | D87: 07 jul | E87: 2025 | F87: Si | H87: 45846 | I87: diseño por los tres mails | J87: DETROIT | L87: 45869 | M87: 130000 | O87: =IF(ISBLANK(M87), "", VLOOKUP(D87, 'Info Tipo de Cambio y REM'!$A$24:$B$35, 2, FALSE)) -> #N/A | P87: =IF(NOT(ISBLANK(M87)), M87 / O87, IF(NOT(ISBLANK(N87)), N87, "")) -> #N/A
A88: Clientes a cobrar | B88: =IF( A88="", "", IF( OR(A88="Santander-Galicia-Nación", A88="Bank Of America", A88="Transferwise", A88="Custodia Socios", A88="Cheques en cartera", A88="Caja"), "Activo Liquido", IF( OR(A88="Otras Inversiones", A88="Santander Inversiones"), "Mediano Plazo", IF( A88="Clientes a cobrar", "Clientes a cobrar", "DATO NO CARGADO" ) ) ) ) -> Clientes a cobrar | C88: =IF(J88="", "", IFERROR(VLOOKUP(J88, Clasificaciones!D:E, 2, FALSE), "DATO NO CARGADO")) -> Detroit | D88: 07 jul | E88: 2025 | F88: Si | H88: 45846 | I88: FEE MES DE JULIO | J88: DETROIT | L88: 45870 | M88: 1071885 | O88: =IF(ISBLANK(M88), "", VLOOKUP(D88, 'Info Tipo de Cambio y REM'!$A$24:$B$35, 2, FALSE)) -> #N/A | P88: =IF(NOT(ISBLANK(M88)), M88 / O88, IF(NOT(ISBLANK(N88)), N88, "")) -> #N/A
A89: Clientes a cobrar | B89: =IF( A89="", "", IF( OR(A89="Santander-Galicia-Nación", A89="Bank Of America", A89="Transferwise", A89="Custodia Socios", A89="Cheques en cartera", A89="Caja"), "Activo Liquido", IF( OR(A89="Otras Inversiones", A89="Santander Inversiones"), "Mediano Plazo", IF( A89="Clientes a cobrar", "Clientes a cobrar", "DATO NO CARGADO" ) ) ) ) -> Clientes a cobrar | C89: =IF(J89="", "", IFERROR(VLOOKUP(J89, Clasificaciones!D:E, 2, FALSE), "DATO NO CARGADO")) -> Animal Studio | D89: 07 jul | E89: 2025 | F89: Si | H89: 45856 | I89: Factura de Venta N° A-00008-00002002 | J89: ANIMAL STUDIO S.R.L. | L89: 45887 | M89: 1052700 | O89: =IF(ISBLANK(M89), "", VLOOKUP(D89, 'Info Tipo de Cambio y REM'!$A$24:$B$35, 2, FALSE)) -> #N/A | P89: =IF(NOT(ISBLANK(M89)), M89 / O89, IF(NOT(ISBLANK(N89)), N89, "")) -> #N/A
A90: Clientes a cobrar | B90: Clientes a cobrar | C90: Detroit | D90: 07 jul | E90: 2025 | F90: No | H90: 45839 | I90: SALDO | J90: DETROIT | K90: ESTO NO VA | L90: 45870 | O90: =IF(ISBLANK(M90), "", VLOOKUP(D90, 'Info Tipo de Cambio y REM'!$A$24:$B$35, 2, FALSE)) | P90: =IF(NOT(ISBLANK(M90)), M90 / O90, IF(NOT(ISBLANK(N90)), N90, ""))
A91: Clientes a cobrar | B91: Clientes a cobrar | C91: Moreno Ocampo | D91: 07 jul | E91: 2025 | F91: Si | H91: 45649 | I91: Invoice 532 | J91: MORENO OCAMPO | L91: 45678 | N91: 250 | O91: =IF(ISBLANK(M91), "", VLOOKUP(D91, 'Info Tipo de Cambio y REM'!$A$24:$B$35, 2, FALSE)) | P91: =IF(NOT(ISBLANK(M91)), M91 / O91, IF(NOT(ISBLANK(N91)), N91, "")) -> 250
A92: Clientes a cobrar | B92: Clientes a cobrar | C92: Coca-Cola | D92: 07 jul | E92: 2025 | F92: No | H92: 45775 | I92: INVOICE 576 | J92: SERVICIOS INTEGRADOS DE ADMINISTRACION Y ALTA GER | L92: 45865 | N92: 5568 | O92: =IF(ISBLANK(M92), "", VLOOKUP(D92, 'Info Tipo de Cambio y REM'!$A$24:$B$35, 2, FALSE)) | P92: =IF(NOT(ISBLANK(M92)), M92 / O92, IF(NOT(ISBLANK(N92)), N92, "")) -> 5568
A93: Clientes a cobrar | B93: Clientes a cobrar | C93: Uber | D93: 07 jul | E93: 2025 | F93: Si | H93: 45827 | I93: INVOICE 595 | J93: UBER | L93: 45887 | N93: 7350 | O93: =IF(ISBLANK(M93), "", VLOOKUP(D93, 'Info Tipo de Cambio y REM'!$A$24:$B$35, 2, FALSE)) | P93: =IF(NOT(ISBLANK(M93)), M93 / O93, IF(NOT(ISBLANK(N93)), N93, "")) -> 7350
A94: Santander-Galicia-Nación | B94: =IF( A94="", "", IF( OR(A94="Santander-Galicia-Nación", A94="Bank Of America", A94="Transferwise", A94="Custodia Socios", A94="Cheques en cartera", A94="Caja"), "Activo Liquido", IF( OR(A94="Otras Inversiones", A94="Santander Inversiones"), "Mediano Plazo", IF( A94="Clientes a cobrar", "Clientes a cobrar", "DATO NO CARGADO" ) ) ) ) -> Activo Liquido | C94: =IF(J94="", "", IFERROR(VLOOKUP(J94, Clasificaciones!D:E, 2, FALSE), "DATO NO CARGADO")) | D94: 07 jul | E94: 2025 | M94: -579983 | O94: =IF(ISBLANK(M94), "", VLOOKUP(D94, 'Info Tipo de Cambio y REM'!$A$24:$B$35, 2, FALSE)) -> #N/A | P94: =IF(NOT(ISBLANK(M94)), M94 / O94, IF(NOT(ISBLANK(N94)), N94, "")) -> #N/A
A95: Bank Of America | B95: =IF( A95="", "", IF( OR(A95="Santander-Galicia-Nación", A95="Bank Of America", A95="Transferwise", A95="Custodia Socios", A95="Cheques en cartera", A95="Caja"), "Activo Liquido", IF( OR(A95="Otras Inversiones", A95="Santander Inversiones"), "Mediano Plazo", IF( A95="Clientes a cobrar", "Clientes a cobrar", "DATO NO CARGADO" ) ) ) ) -> Activo Liquido | C95: =IF(J95="", "", IFERROR(VLOOKUP(J95, Clasificaciones!D:E, 2, FALSE), "DATO NO CARGADO")) | D95: 07 jul | E95: 2025 | N95: -68302 | O95: =IF(ISBLANK(M95), "", VLOOKUP(D95, 'Info Tipo de Cambio y REM'!$A$24:$B$35, 2, FALSE)) | P95: =IF(NOT(ISBLANK(M95)), M95 / O95, IF(NOT(ISBLANK(N95)), N95, "")) -> -68302
A96: Transferwise | B96: =IF( A96="", "", IF( OR(A96="Santander-Galicia-Nación", A96="Bank Of America", A96="Transferwise", A96="Custodia Socios", A96="Cheques en cartera", A96="Caja"), "Activo Liquido", IF( OR(A96="Otras Inversiones", A96="Santander Inversiones"), "Mediano Plazo", IF( A96="Clientes a cobrar", "Clientes a cobrar", "DATO NO CARGADO" ) ) ) ) -> Activo Liquido | C96: =IF(J96="", "", IFERROR(VLOOKUP(J96, Clasificaciones!D:E, 2, FALSE), "DATO NO CARGADO")) | D96: 07 jul | E96: 2025 | N96: 230 | O96: =IF(ISBLANK(M96), "", VLOOKUP(D96, 'Info Tipo de Cambio y REM'!$A$24:$B$35, 2, FALSE)) | P96: =IF(NOT(ISBLANK(M96)), M96 / O96, IF(NOT(ISBLANK(N96)), N96, "")) -> 230
A97: Otras Inversiones | B97: =IF( A97="", "", IF( OR(A97="Santander-Galicia-Nación", A97="Bank Of America", A97="Transferwise", A97="Custodia Socios", A97="Cheques en cartera", A97="Caja"), "Activo Liquido", IF( OR(A97="Otras Inversiones", A97="Santander Inversiones"), "Mediano Plazo", IF( A97="Clientes a cobrar", "Clientes a cobrar", "DATO NO CARGADO" ) ) ) ) -> Mediano Plazo | C97: =IF(J97="", "", IFERROR(VLOOKUP(J97, Clasificaciones!D:E, 2, FALSE), "DATO NO CARGADO")) | D97: 07 jul | E97: 2025 | N97: 2540 | O97: =IF(ISBLANK(M97), "", VLOOKUP(D97, 'Info Tipo de Cambio y REM'!$A$24:$B$35, 2, FALSE)) | P97: =IF(NOT(ISBLANK(M97)), M97 / O97, IF(NOT(ISBLANK(N97)), N97, "")) -> 2540
A98: Clientes a cobrar | B98: Clientes a cobrar | C98: Coelsa | D98: 08 ago | E98: 2025 | F98: No | H98: 45873 | I98: Factura de Crédito MiPyME (FCE) N° A-00008-00000975 | J98: COMPENSADORA ELECTRONICA SA | L98: 45904 | M98: 5275426 | O98: =IF(ISBLANK(M98), "", VLOOKUP(D98, 'Info Tipo de Cambio y REM'!$A$24:$B$35, 2, FALSE)) -> #N/A | P98: =IF(NOT(ISBLANK(M98)), M98 / O98, IF(NOT(ISBLANK(N98)), N98, "")) -> #N/A
A99: Clientes a cobrar | B99: Clientes a cobrar | C99: Play Digital S.A (Modo) | D99: 08 ago | E99: 2025 | F99: No | H99: 45873 | I99: Factura de Venta N° A-00008-00002010 | J99: PLAY DIGITAL S. A. | L99: 45904 | M99: 3720750 | O99: =IF(ISBLANK(M99), "", VLOOKUP(D99, 'Info Tipo de Cambio y REM'!$A$24:$B$35, 2, FALSE)) -> #N/A | P99: =IF(NOT(ISBLANK(M99)), M99 / O99, IF(NOT(ISBLANK(N99)), N99, "")) -> #N/A
A100: Clientes a cobrar | B100: Clientes a cobrar | C100: Detroit | D100: 08 ago | E100: 2025 | F100: Si | H100: 45873 | I100: FEE MES DE AGOSTO | J100: DETROIT | L100: 45904 | M100: 1071885 | O100: =IF(ISBLANK(M100), "", VLOOKUP(D100, 'Info Tipo de Cambio y REM'!$A$24:$B$35, 2, FALSE)) -> #N/A | P100: =IF(NOT(ISBLANK(M100)), M100 / O100, IF(NOT(ISBLANK(N100)), N100, "")) -> #N/A
...

Sheet PASIVO BACK UP 8-9 PREVIO CAMBI
A1: Detalle | B1: Subtipo de costo | C1: Mes | D1: Año | E1: Pagado/No Pagado AL CIERRE | F1: Fecha de pago | G1: Fecha emisión | H1: Concepto/Detalle | I1: Descripción/Factura | J1: Fecha de vencimiento | K1: Moneda original ARS | L1: Moneda original USD | M1: Cotización | N1: Monto Total USD
A2: Sosa Gonzalez Walter Gaston | B2: =IF(A2="", "", IFERROR(VLOOKUP(A2, Clasificaciones!A:B, 2, FALSE), "DATO NO CARGADO")) -> Otros Proveedores | C2: 01 ene | D2: 2025 | E2: No Pagado | H2: SOSA GONZALEZ WALTER GASTON | I2: Factura de Compra N° C-00001-00000125 | J2: 45413 | K2: 96000 | M2: =IF(ISBLANK(K2), "", VLOOKUP(C2, 'Info Tipo de Cambio y REM'!$A$24:$B$35, 2, FALSE)) -> #N/A | N2: =IFERROR(IF(NOT(ISBLANK(K2)), K2 / M2, IF(NOT(ISBLANK(L2)), L2, "")), "")
A3: Gloup by digital tie | B3: =IF(A3="", "", IFERROR(VLOOKUP(A3, Clasificaciones!A:B, 2, FALSE), "DATO NO CARGADO")) -> Otros Proveedores | C3: 01 ene | D3: 2025 | E3: Pagado | H3: GLOUP BY DIGITAL TIE | I3: Factura de Compra N° A-00002-00000591 | J3: 45690 | K3: 1827887 | M3: =IF(ISBLANK(K3), "", VLOOKUP(C3, 'Info Tipo de Cambio y REM'!$A$24:$B$35, 2, FALSE)) -> #N/A | N3: =IFERROR(IF(NOT(ISBLANK(K3)), K3 / M3, IF(NOT(ISBLANK(L3)), L3, "")), "")
A4: Cata Astiz | B4: =IF(A4="", "", IFERROR(VLOOKUP(A4, Clasificaciones!A:B, 2, FALSE), "DATO NO CARGADO")) -> Equipo | C4: 01 ene | D4: 2025 | E4: Pagado | H4: CATALINA ASTIZ | I4: EFVO. | J4: 45688 | K4: 218190 | M4: =IF(ISBLANK(K4), "", VLOOKUP(C4, 'Info Tipo de Cambio y REM'!$A$24:$B$35, 2, FALSE)) -> #N/A | N4: =IFERROR(IF(NOT(ISBLANK(K4)), K4 / M4, IF(NOT(ISBLANK(L4)), L4, "")), "")
A5: Aylu Tamer | B5: =IF(A5="", "", IFERROR(VLOOKUP(A5, Clasificaciones!A:B, 2, FALSE), "DATO NO CARGADO")) -> Equipo | C5: 01 ene | D5: 2025 | E5: Pagado | H5: AYLEN MAGALI TAMER | I5: C-00002-00000024 | J5: 45688 | K5: 644403 | M5: =IF(ISBLANK(K5), "", VLOOKUP(C5, 'Info Tipo de Cambio y REM'!$A$24:$B$35, 2, FALSE)) -> #N/A | N5: =IFERROR(IF(NOT(ISBLANK(K5)), K5 / M5, IF(NOT(ISBLANK(L5)), L5, "")), "")
A6: Lola Camara | B6: =IF(A6="", "", IFERROR(VLOOKUP(A6, Clasificaciones!A:B, 2, FALSE), "DATO NO CARGADO")) -> Equipo | C6: 01 ene | D6: 2025 | E6: Pagado | H6: CAMARA DOLORES | I6: C-00001-00000113 | J6: 45688 | K6: 1851120 | M6: =IF(ISBLANK(K6), "", VLOOKUP(C6, 'Info Tipo de Cambio y REM'!$A$24:$B$35, 2, FALSE)) -> #N/A | N6: =IFERROR(IF(NOT(ISBLANK(K6)), K6 / M6, IF(NOT(ISBLANK(L6)), L6, "")), "")
A7: Gastón Julian | B7: =IF(A7="", "", IFERROR(VLOOKUP(A7, Clasificaciones!A:B, 2, FALSE), "DATO NO CARGADO")) -> Administración Finanzas | C7: 01 ene | D7: 2025 | E7: Pagado | H7: GASTON LEONARDO JULIAN | I7: C-00001-00000240 | J7: 45688 | K7: 537700 | M7: =IF(ISBLANK(K7), "", VLOOKUP(C7, 'Info Tipo de Cambio y REM'!$A$24:$B$35, 2, FALSE)) -> #N/A | N7: =IFERROR(IF(NOT(ISBLANK(K7)), K7 / M7, IF(NOT(ISBLANK(L7)), L7, "")), "")
A8: Nazarena Drachemberg | B8: =IF(A8="", "", IFERROR(VLOOKUP(A8, Clasificaciones!A:B, 2, FALSE), "DATO NO CARGADO")) -> Otros Proveedores | C8: 01 ene | D8: 2025 | E8: Pagado | H8: MARIA NAZARENA DRACHEMBERG | I8: C-00001-00000010 | J8: 45688 | K8: 1280000 | M8: =IF(ISBLANK(K8), "", VLOOKUP(C8, 'Info Tipo de Cambio y REM'!$A$24:$B$35, 2, FALSE)) -> #N/A | N8: =IFERROR(IF(NOT(ISBLANK(K8)), K8 / M8, IF(NOT(ISBLANK(L8)), L8, "")), "")
A9: Vicky Achabal | B9: =IF(A9="", "", IFERROR(VLOOKUP(A9, Clasificaciones!A:B, 2, FALSE), "DATO NO CARGADO")) -> Equipo | C9: 01 ene | D9: 2025 | E9: Pagado | H9: MARIA VICTORIA ACHABAL | I9: C-00001-00000005 | J9: 45688 | K9: 2500000 | M9: =IF(ISBLANK(K9), "", VLOOKUP(C9, 'Info Tipo de Cambio y REM'!$A$24:$B$35, 2, FALSE)) -> #N/A | N9: =IFERROR(IF(NOT(ISBLANK(K9)), K9 / M9, IF(NOT(ISBLANK(L9)), L9, "")), "")
A10: Maricel Perez | B10: =IF(A10="", "", IFERROR(VLOOKUP(A10, Clasificaciones!A:B, 2, FALSE), "DATO NO CARGADO")) -> Equipo | C10: 01 ene | D10: 2025 | E10: Pagado | H10: MARICEL ELINA PEREZ | I10: C-00002-00000326 | J10: 45688 | K10: 776000 | M10: =IF(ISBLANK(K10), "", VLOOKUP(C10, 'Info Tipo de Cambio y REM'!$A$24:$B$35, 2, FALSE)) -> #N/A | N10: =IFERROR(IF(NOT(ISBLANK(K10)), K10 / M10, IF(NOT(ISBLANK(L10)), L10, "")), "")
A11: Mati Gonzalez | B11: =IF(A11="", "", IFERROR(VLOOKUP(A11, Clasificaciones!A:B, 2, FALSE), "DATO NO CARGADO")) -> Equipo | C11: 01 ene | D11: 2025 | E11: Pagado | H11: MATIAS GONZALEZ VIRGILI | I11: C-00001-00000007 | J11: 45688 | K11: 420501 | M11: =IF(ISBLANK(K11), "", VLOOKUP(C11, 'Info Tipo de Cambio y REM'!$A$24:$B$35, 2, FALSE)) -> #N/A | N11: =IFERROR(IF(NOT(ISBLANK(K11)), K11 / M11, IF(NOT(ISBLANK(L11)), L11, "")), "")
A12: Vicky Puricelli | B12: =IF(A12="", "", IFERROR(VLOOKUP(A12, Clasificaciones!A:B, 2, FALSE), "DATO NO CARGADO")) -> Board | C12: 01 ene | D12: 2025 | E12: Pagado | H12: MATIAS SMART (VICTORIA PURICELLI) | I12: C-00003-00000097 | J12: 45693 | K12: 898903 | M12: =IF(ISBLANK(K12), "", VLOOKUP(C12, 'Info Tipo de Cambio y REM'!$A$24:$B$35, 2, FALSE)) -> #N/A | N12: =IFERROR(IF(NOT(ISBLANK(K12)), K12 / M12, IF(NOT(ISBLANK(L12)), L12, "")), "")
A13: Vicky Puricelli | B13: =IF(A13="", "", IFERROR(VLOOKUP(A13, Clasificaciones!A:B, 2, FALSE), "DATO NO CARGADO")) -> Board | C13: 01 ene | D13: 2025 | E13: Pagado | H13: VICTORIA PURICELLI (SALDO) | I13: Fac E 2 | J13: 45692 | K13: 1085230 | M13: =IF(ISBLANK(K13), "", VLOOKUP(C13, 'Info Tipo de Cambio y REM'!$A$24:$B$35, 2, FALSE)) -> #N/A | N13: =IFERROR(IF(NOT(ISBLANK(K13)), K13 / M13, IF(NOT(ISBLANK(L13)), L13, "")), "")
... A23: Xavi Aranzana | B23: =IF(A23="", "", IFERROR(VLOOKUP(A23, Clasificaciones!A:B, 2, FALSE), "DATO NO CARGADO")) -> Equipo | C23: 01 ene | D23: 2025 | E23: Pagado | H23: XAVIER RICARDO ARANZANA | I23: C-00001-00000008 | J23: 45691 | K23: 2160000 | M23: =IF(ISBLANK(K23), "", VLOOKUP(C23, 'Info Tipo de Cambio y REM'!$A$24:$B$35, 2, FALSE)) -> #N/A | N23: =IFERROR(IF(NOT(ISBLANK(K23)), K23 / M23, IF(NOT(ISBLANK(L23)), L23, "")), "")
A24: People | B24: =IF(A24="", "", IFERROR(VLOOKUP(A24, Clasificaciones!A:B, 2, FALSE), "DATO NO CARGADO")) -> People | C24: 01 ene | D24: 2025 | E24: Pagado | H24: CAMILA FERRARIS (PEOPLE 8 hs.) | J24: 45693 | K24: 178400 | M24: =IF(ISBLANK(K24), "", VLOOKUP(C24, 'Info Tipo de Cambio y REM'!$A$24:$B$35, 2, FALSE)) -> #N/A | N24: =IFERROR(IF(NOT(ISBLANK(K24)), K24 / M24, IF(NOT(ISBLANK(L24)), L24, "")), "")
A25: Brandwatch | B25: =IF(A25="", "", IFERROR(VLOOKUP(A25, Clasificaciones!A:B, 2, FALSE), "DATO NO CARGADO")) -> Suscripciones/Herramientas | C25: 01 ene | D25: 2025 | E25: No Pagado | H25: BRANDWATCH SOLO CONSIDERAR 3 MESES | J25: 45536 | L25: 4050 | M25: =IF(ISBLANK(K25), "", VLOOKUP(C25, 'Info Tipo de Cambio y REM'!$A$24:$B$35, 2, FALSE)) | N25: =IFERROR(IF(NOT(ISBLANK(K25)), K25 / M25, IF(NOT(ISBLANK(L25)), L25, "")), "") -> 4050
A26: Luan Digital | B26: =IF(A26="", "", IFERROR(VLOOKUP(A26, Clasificaciones!A:B, 2, FALSE), "DATO NO CARGADO")) -> Gastos Varios | C26: 01 ene | D26: 2025 | E26: Pagado | H26: LUAN DIGITAL | J26: 45688 | L26: 600 | M26: =IF(ISBLANK(K26), "", VLOOKUP(C26, 'Info Tipo de Cambio y REM'!$A$24:$B$35, 2, FALSE)) | N26: =IFERROR(IF(NOT(ISBLANK(K26)), K26 / M26, IF(NOT(ISBLANK(L26)), L26, "")), "") -> 600
A27: Youscan | B27: =IF(A27="", "", IFERROR(VLOOKUP(A27, Clasificaciones!A:B, 2, FALSE), "DATO NO CARGADO")) -> Suscripciones/Herramientas | C27: 01 ene | D27: 2025 | E27: Pagado | H27: YOUSCAN | I27: LA ENVIAN CUANDO SE ABONA | J27: 45716 | L27: 7500 | M27: =IF(ISBLANK(K27), "", VLOOKUP(C27, 'Info Tipo de Cambio y REM'!$A$24:$B$35, 2, FALSE)) | N27: =IFERROR(IF(NOT(ISBLANK(K27)), K27 / M27, IF(NOT(ISBLANK(L27)), L27, "")), "") -> 7500
A28: Estudio Contable | B28: =IF(A28="", "", IFERROR(VLOOKUP(A28, Clasificaciones!A:B, 2, FALSE), "DATO NO CARGADO")) -> Estudio Contable | C28: 01 ene | D28: 2025 | E28: Pagado | H28: ESTUDIO CONTABLE Enero (VARIABLE) | J28: 45698 | K28: 86677 | M28: =IF(ISBLANK(K28), "", VLOOKUP(C28, 'Info Tipo de Cambio y REM'!$A$24:$B$35, 2, FALSE)) -> #N/A | N28: =IFERROR(IF(NOT(ISBLANK(K28)), K28 / M28, IF(NOT(ISBLANK(L28)), L28, "")), "")
A29: Tarjeta ARG | B29: =IF(A29="", "", IFERROR(VLOOKUP(A29, Clasificaciones!A:B, 2, FALSE), "DATO NO CARGADO")) -> Tarjeta | C29: 01 ene | D29: 2025 | E29: Pagado | H29: ***TARJETAS VISA/ AMEX Enero | J29: 45693 | K29: 28405 | M29: =IF(ISBLANK(K29), "", VLOOKUP(C29, 'Info Tipo de Cambio y REM'!$A$24:$B$35, 2, FALSE)) -> #N/A | N29: =IFERROR(IF(NOT(ISBLANK(K29)), K29 / M29, IF(NOT(ISBLANK(L29)), L29, "")), "")
A30: IIBB | B30: =IF(A30="", "", IFERROR(VLOOKUP(A30, Clasificaciones!A:B, 2, FALSE), "DATO NO CARGADO")) -> Impuestos ARG | C30: 01 ene | D30: 2025 | E30: Pagado | H30: INGRESOS BRUTOS Enero | J30: 45706 | K30: 579408 | M30: =IF(ISBLANK(K30), "", VLOOKUP(C30, 'Info Tipo de Cambio y REM'!$A$24:$B$35, 2, FALSE)) -> #N/A | N30: =IFERROR(IF(NOT(ISBLANK(K30)), K30 / M30, IF(NOT(ISBLANK(L30)), L30, "")), "")
A31: IVA | B31: =IF(A31="", "", IFERROR(VLOOKUP(A31, Clasificaciones!A:B, 2, FALSE), "DATO NO CARGADO")) -> Impuestos ARG | C31: 01 ene | D31: 2025 | E31: Pagado | H31: IVA Enero | J31: 45710 | K31: 2689779 | M31: =IF(ISBLANK(K31), "", VLOOKUP(C31, 'Info Tipo de Cambio y REM'!$A$24:$B$35, 2, FALSE)) -> #N/A | N31: =IFERROR(IF(NOT(ISBLANK(K31)), K31 / M31, IF(NOT(ISBLANK(L31)), L31, "")), "")
A32: Tomi Criado | B32: =IF(A32="", "", IFERROR(VLOOKUP(A32, Clasificaciones!A:B, 2, FALSE), "DATO NO CARGADO")) -> Board | C32: 01 ene | D32: 2025 | E32: Pagado | H32: HONORARIOS TOMAS Enero | J32: 45693 | K32: 3025000 | M32: =IF(ISBLANK(K32), "", VLOOKUP(C32, 'Info Tipo de Cambio y REM'!$A$24:$B$35, 2, FALSE)) -> #N/A | N32: =IFERROR(IF(NOT(ISBLANK(K32)), K32 / M32, IF(NOT(ISBLANK(L32)), L32, "")), "")
A33: Honorarios Oxean | B33: =IF(A33="", "", IFERROR(VLOOKUP(A33, Clasificaciones!A:B, 2, FALSE), "DATO NO CARGADO")) -> Oxean | C33: 01 ene | D33: 2025 | E33: Pagado | H33: HONORARIOS OXEAN ADMINISTRACION Enero | J33: 45693 | K33: 3025000 | M33: =IF(ISBLANK(K33), "", VLOOKUP(C33, 'Info Tipo de Cambio y REM'!$A$24:$B$35, 2, FALSE)) -> #N/A | N33: =IFERROR(IF(NOT(ISBLANK(K33)), K33 / M33, IF(NOT(ISBLANK(L33)), L33, "")), "")
A34: Tarjeta USA | B34: =IF(A34="", "", IFERROR(VLOOKUP(A34, Clasificaciones!A:B, 2, FALSE), "DATO NO CARGADO")) -> Tarjeta | C34: 01 ene | D34: 2025 | E34: Pagado | H34: DIGITALOCEAN.COM 01/31 PURCHASE 6468274366 NY DEBIT CARD *9122 | L34: 12 | M34: =IF(ISBLANK(K34), "", VLOOKUP(C34, 'Info Tipo de Cambio y REM'!$A$24:$B$35, 2, FALSE)) | N34: =IFERROR(IF(NOT(ISBLANK(K34)), K34 / M34, IF(NOT(ISBLANK(L34)), L34, "")), "") -> 12
A35: Tarjeta USA | B35: =IF(A35="", "", IFERROR(VLOOKUP(A35, Clasificaciones!A:B, 2, FALSE), "DATO NO CARGADO")) -> Tarjeta | C35: 01 ene | D35: 2025 | E35: Pagado | H35: GOOGLE*GSUITE EPI 02/01 PURCHASE 6502530000 CA DEBIT CARD *9122 | L35: 450 | M35: =IF(ISBLANK(K35), "", VLOOKUP(C35, 'Info Tipo de Cambio y REM'!$A$24:$B$35, 2, FALSE)) | N35: =IFERROR(IF(NOT(ISBLANK(K35)), K35 / M35, IF(NOT(ISBLANK(L35)), L35, "")), "") -> 450
A36: Tarjeta USA | B36: =IF(A36="", "", IFERROR(VLOOKUP(A36, Clasificaciones!A:B, 2, FALSE), "DATO NO CARGADO")) -> Tarjeta | C36: 01 ene | D36: 2025 | E36: Pagado | H36: Google ADS7881686 02/01 PURCHASE 6502530000 CA DEBIT CARD *9122 | L36: 303 | M36: =IF(ISBLANK(K36), "", VLOOKUP(C36, 'Info Tipo de Cambio y REM'!$A$24:$B$35, 2, FALSE)) | N36: =IFERROR(IF(NOT(ISBLANK(K36)), K36 / M36, IF(NOT(ISBLANK(L36)), L36, "")), "") -> 303
A37: Tarjeta USA | B37: =IF(A37="", "", IFERROR(VLOOKUP(A37, Clasificaciones!A:B, 2, FALSE), "DATO NO CARGADO")) -> Tarjeta | C37: 01 ene | D37: 2025 | E37: Pagado | H37: LinkedIn SN P2358 02/02 PURCHASE LINKEDIN.COM 00 DEBIT CARD *9122 | L37: 8 | M37: =IF(ISBLANK(K37), "", VLOOKUP(C37, 'Info Tipo de Cambio y REM'!$A$24:$B$35, 2, FALSE)) | N37: =IFERROR(IF(NOT(ISBLANK(K37)), K37 / M37, IF(NOT(ISBLANK(L37)), L37, "")), "") -> 8
A38: Tarjeta USA | B38: =IF(A38="", "", IFERROR(VLOOKUP(A38, Clasificaciones!A:B, 2, FALSE), "DATO NO CARGADO")) -> Tarjeta | C38: 01 ene | D38: 2025 | E38: Pagado | H38: APPLE.COM/BILL 02/02 PURCHASE 8667127753 CA DEBIT CARD *9122 | L38: 14.19 | M38: =IF(ISBLANK(K38), "", VLOOKUP(C38, 'Info Tipo de Cambio y REM'!$A$24:$B$35, 2, FALSE)) | N38: =IFERROR(IF(NOT(ISBLANK(K38)), K38 / M38, IF(NOT(ISBLANK(L38)), L38, "")), "") -> 14.19
A39: Tarjeta USA | B39: =IF(A39="", "", IFERROR(VLOOKUP(A39, Clasificaciones!A:B, 2, FALSE), "DATO NO CARGADO")) -> Tarjeta | C39: 01 ene | D39: 2025 | E39: Pagado | H39: ADOBE *ADOBE 02/03 PURCHASE 4085366000 CA DEBIT CARD *9122 | L39: 22.99 | M39: =IF(ISBLANK(K39), "", VLOOKUP(C39, 'Info Tipo de Cambio y REM'!$A$24:$B$35, 2, FALSE)) | N39: =IFERROR(IF(NOT(ISBLANK(K39)), K39 / M39, IF(NOT(ISBLANK(L39)), L39, "")), "") -> 22.99
A40: Tarjeta USA | B40: =IF(A40="", "", IFERROR(VLOOKUP(A40, Clasificaciones!A:B, 2, FALSE), "DATO NO CARGADO")) -> Tarjeta | C40: 01 ene | D40: 2025 | E40: Pagado | H40: REPLIT, INC. 02/04 PURCHASE 6282002281 CA DEBIT CARD *9122 | L40: 25 | M40: =IF(ISBLANK(K40), "", VLOOKUP(C40, 'Info Tipo de Cambio y REM'!$A$24:$B$35, 2, FALSE)) | N40: =IFERROR(IF(NOT(ISBLANK(K40)), K40 / M40, IF(NOT(ISBLANK(L40)), L40, "")), "") -> 25
A41: Impuestos USA | B41: =IF(A41="", "", IFERROR(VLOOKUP(A41, Clasificaciones!A:B, 2, FALSE), "DATO NO CARGADO")) -> Impuestos USA | C41: 01 ene | D41: 2025 | E41: No Pagado | H41: Impuestos a pagar USA | L41: 17732 | M41: =IF(ISBLANK(K41), "", VLOOKUP(C41, 'Info Tipo de Cambio y REM'!$A$24:$B$35, 2, FALSE)) | N41: =IFERROR(IF(NOT(ISBLANK(K41)), K41 / M41, IF(NOT(ISBLANK(L41)), L41, "")), "") -> 17732
A42: Sosa Gonzalez Walter Gaston | B42: =IF(A42="", "", IFERROR(VLOOKUP(A42, Clasificaciones!A:B, 2, FALSE), "DATO NO CARGADO")) -> Otros Proveedores | C42: 02 feb | D42: 2025 | E42: No Pagado | H42: SOSA GONZALEZ WALTER GASTON | I42: Factura de Compra N° C-00001-00000125 | J42: 45413 | K42: 96000 | M42: =IF(ISBLANK(K42), "", VLOOKUP(C42, 'Info Tipo de Cambio y REM'!$A$24:$B$35, 2, FALSE)) -> #N/A | N42: =IFERROR(IF(NOT(ISBLANK(K42)), K42 / M42, IF(NOT(ISBLANK(L42)), L42, "")), "")
A43: Gloup by digital tie | B43: =IF(A43="", "", IFERROR(VLOOKUP(A43, Clasificaciones!A:B, 2, FALSE), "DATO NO CARGADO")) -> Otros Proveedores | C43: 02 feb | D43: 2025 | E43: Pagado | H43: GLOUP BY DIGITAL TIE | I43: Factura de Compra N° A-00002-00000607 | J43: 45717 | K43: 1763636 | M43: =IF(ISBLANK(K43), "", VLOOKUP(C43, 'Info Tipo de Cambio y REM'!$A$24:$B$35, 2, FALSE)) -> #N/A | N43: =IFERROR(IF(NOT(ISBLANK(K43)), K43 / M43, IF(NOT(ISBLANK(L43)), L43, "")), "")
A44: Mati Gonzalez | B44: =IF(A44="", "", IFERROR(VLOOKUP(A44, Clasificaciones!A:B, 2, FALSE), "DATO NO CARGADO")) -> Equipo | C44: 02 feb | D44: 2025 | E44: Pagado | H44: MATIAS GONZALEZ VIRGILI | I44: C-00001-00000008 | J44: 45722 | K44: 1173315 | M44: =IF(ISBLANK(K44), "", VLOOKUP(C44, 'Info Tipo de Cambio y REM'!$A$24:$B$35, 2, FALSE)) -> #N/A | N44: =IFERROR(IF(NOT(ISBLANK(K44)), K44 / M44, IF(NOT(ISBLANK(L44)), L44, "")), "")
A45: Gast Guntren | B45: =IF(A45="", "", IFERROR(VLOOKUP(A45, Clasificaciones!A:B, 2, FALSE), "DATO NO CARGADO")) -> Equipo | C45: 02 feb | D45: 2025 | E45: Pagado | H45: GASTON ANDRES GUNTREN | I45: C-00001-00000046 | J45: 45716 | K45: 1926000 | M45: =IF(ISBLANK(K45), "", VLOOKUP(C45, 'Info Tipo de Cambio y REM'!$A$24:$B$35, 2, FALSE)) -> #N/A | N45: =IFERROR(IF(NOT(ISBLANK(K45)), K45 / M45, IF(NOT(ISBLANK(L45)), L45, "")), "")
A46: Romi Figueroa | B46: =IF(A46="", "", IFERROR(VLOOKUP(A46, Clasificaciones!A:B, 2, FALSE), "DATO NO CARGADO")) -> Equipo | C46: 02 feb | D46: 2025 | E46: Pagado | H46: ROMINA MARIANELA FIGUEROA GUERRA | I46: C-00002-00000020 | J46: 45716 | K46: 1782500 | M46: =IF(ISBLANK(K46), "", VLOOKUP(C46, 'Info Tipo de Cambio y REM'!$A$24:$B$35, 2, FALSE)) -> #N/A | N46: =IFERROR(IF(NOT(ISBLANK(K46)), K46 / M46, IF(NOT(ISBLANK(L46)), L46, "")), "")
A47: Vanu Lanza | B47: =IF(A47="", "", IFERROR(VLOOKUP(A47, Clasificaciones!A:B, 2, FALSE), "DATO NO CARGADO")) -> Equipo | C47: 02 feb | D47: 2025 | E47: Pagado | H47: VANINA LANZA | I47: C-00003-00000049 | J47: 45716 | K47: 1606924 | M47: =IF(ISBLANK(K47), "", VLOOKUP(C47, 'Info Tipo de Cambio y REM'!$A$24:$B$35, 2, FALSE)) -> #N/A | N47: =IFERROR(IF(NOT(ISBLANK(K47)), K47 / M47, IF(NOT(ISBLANK(L47)), L47, "")), "")
A48: Trini Petreigne | B48: =IF(A48="", "", IFERROR(VLOOKUP(A48, Clasificaciones!A:B, 2, FALSE), "DATO NO CARGADO")) -> Equipo | C48: 02 feb | D48: 2025 | E48: Pagado | H48: TRINIDAD PETREIGNE BACIGALUPE | I48: C-00001-00000072 | J48: 45716 | K48: 1219798 | M48: =IF(ISBLANK(K48), "", VLOOKUP(C48, 'Info Tipo de Cambio y REM'!$A$24:$B$35, 2, FALSE)) -> #N/A | N48: =IFERROR(IF(NOT(ISBLANK(K48)), K48 / M48, IF(NOT(ISBLANK(L48)), L48, "")), "")
A49: Aylu Tamer | B49: =IF(A49="", "", IFERROR(VLOOKUP(A49, Clasificaciones!A:B, 2, FALSE), "DATO NO CARGADO")) -> Equipo | C49: 02 feb | D49: 2025 | E49: Pagado | H49: AYLEN MAGALI TAMER | I49: C-00002-00000025 | J49: 45716 | K49: 965821 | M49: =IF(ISBLANK(K49), "", VLOOKUP(C49, 'Info Tipo de Cambio y REM'!$A$24:$B$35, 2, FALSE)) -> #N/A | N49: =IFERROR(IF(NOT(ISBLANK(K49)), K49 / M49, IF(NOT(ISBLANK(L49)), L49, "")), "")
A50: Male Quiroga | B50: =IF(A50="", "", IFERROR(VLOOKUP(A50, Clasificaciones!A:B, 2, FALSE), "DATO NO CARGADO")) -> Equipo | C50: 02 feb | D50: 2025 | E50: Pagado | H50: QUIROGA MALENA | I50: C-00001-00000059 | J50: 45716 | K50: 829482 | M50: =IF(ISBLANK(K50), "", VLOOKUP(C50, 'Info Tipo de Cambio y REM'!$A$24:$B$35, 2, FALSE)) -> #N/A | N50: =IFERROR(IF(NOT(ISBLANK(K50)), K50 / M50, IF(NOT(ISBLANK(L50)), L50, "")), "")
A51: Maricel Perez | B51: =IF(A51="", "", IFERROR(VLOOKUP(A51, Clasificaciones!A:B, 2, FALSE), "DATO NO CARGADO")) -> Equipo | C51: 02 feb | D51: 2025 | E51: Pagado | H51: MARICEL ELINA PEREZ | I51: C-00002-00000328 | J51: 45716 | K51: 810000 | M51: =IF(ISBLANK(K51), "", VLOOKUP(C51, 'Info Tipo de Cambio y REM'!$A$24:$B$35, 2, FALSE)) -> #N/A | N51: =IFERROR(IF(NOT(ISBLANK(K51)), K51 / M51, IF(NOT(ISBLANK(L51)), L51, "")), "")
A52: Xavi Aranzana | B52: =IF(A52="", "", IFERROR(VLOOKUP(A52, Clasificaciones!A:B, 2, FALSE), "DATO NO CARGADO")) -> Equipo | C52: 02 feb | D52: 2025 | E52: Pagado | H52: XAVIER RICARDO ARANZANA | I52: C-00001-00000009 | J52: 45716 | K52: 609300 | M52: =IF(ISBLANK(K52), "", VLOOKUP(C52, 'Info Tipo de Cambio y REM'!$A$24:$B$35, 2, FALSE)) -> #N/A | N52: =IFERROR(IF(NOT(ISBLANK(K52)), K52 / M52, IF(NOT(ISBLANK(L52)), L52, "")), "")
A53: Gastón Julian | B53: =IF(A53="", "", IFERROR(VLOOKUP(A53, Clasificaciones!A:B, 2, FALSE), "DATO NO CARGADO")) -> Administración Finanzas | C53: 02 feb | D53: 2025 | E53: Pagado | H53: GASTON LEONARDO JULIAN | I53: C-00001-00000243 | J53: 45716 | K53: 537700 | M53: =IF(ISBLANK(K53), "", VLOOKUP(C53, 'Info Tipo de Cambio y REM'!$A$24:$B$35, 2, FALSE)) -> #N/A | N53: =IFERROR(IF(NOT(ISBLANK(K53)), K53 / M53, IF(NOT(ISBLANK(L53)), L53, "")), "")
... A62: Vicky Puricelli | B62: =IF(A62="", "", IFERROR(VLOOKUP(A62, Clasificaciones!A:B, 2, FALSE), "DATO NO CARGADO")) -> Board | C62: 02 feb | D62: 2025 | E62: Pagado | H62: VICTORIA PURICELLI | I62: C-00002-00000227 | J62: 45722 | K62: 1403068 | M62: =IF(ISBLANK(K62), "", VLOOKUP(C62, 'Info Tipo de Cambio y REM'!$A$24:$B$35, 2, FALSE)) -> #N/A | N62: =IFERROR(IF(NOT(ISBLANK(K62)), K62 / M62, IF(NOT(ISBLANK(L62)), L62, "")), "")
A63: Cata Astiz | B63: =IF(A63="", "", IFERROR(VLOOKUP(A63, Clasificaciones!A:B, 2, FALSE), "DATO NO CARGADO")) -> Equipo | C63: 02 feb | D63: 2025 | E63: Pagado | H63: CATALINA ASTIZ | K63: 377230 | M63: =IF(ISBLANK(K63), "", VLOOKUP(C63, 'Info Tipo de Cambio y REM'!$A$24:$B$35, 2, FALSE)) -> #N/A | N63: =IFERROR(IF(NOT(ISBLANK(K63)), K63 / M63, IF(NOT(ISBLANK(L63)), L63, "")), "")
A64: Brandwatch | B64: =IF(A64="", "", IFERROR(VLOOKUP(A64, Clasificaciones!A:B, 2, FALSE), "DATO NO CARGADO")) -> Suscripciones/Herramientas | C64: 02 feb | D64: 2025 | E64: No Pagado | H64: BRANDWATCH SOLO CONSIDERAR 3 MESES | J64: 45536 | L64: 4050 | M64: =IF(ISBLANK(K64), "", VLOOKUP(C64, 'Info Tipo de Cambio y REM'!$A$24:$B$35, 2, FALSE)) | N64: =IFERROR(IF(NOT(ISBLANK(K64)), K64 / M64, IF(NOT(ISBLANK(L64)), L64, "")), "") -> 4050
A65: Luan Digital | B65: =IF(A65="", "", IFERROR(VLOOKUP(A65, Clasificaciones!A:B, 2, FALSE), "DATO NO CARGADO")) -> Gastos Varios | C65: 02 feb | D65: 2025 | E65: Pagado | H65: LUAN DIGITAL | I65: f/125 | J65: 45721 | L65: 600 | M65: =IF(ISBLANK(K65), "", VLOOKUP(C65, 'Info Tipo de Cambio y REM'!$A$24:$B$35, 2, FALSE)) | N65: =IFERROR(IF(NOT(ISBLANK(K65)), K65 / M65, IF(NOT(ISBLANK(L65)), L65, "")), "") -> 600
A66: Estudio Contable | B66: =IF(A66="", "", IFERROR(VLOOKUP(A66, Clasificaciones!A:B, 2, FALSE), "DATO NO CARGADO")) -> Estudio Contable | C66: 02 feb | D66: 2025 | E66: Pagado | H66: ESTUDIO CONTABLE Febrero (VARIABLE) | J66: 45726 | K66: 45838 | M66: =IF(ISBLANK(K66), "", VLOOKUP(C66, 'Info Tipo de Cambio y REM'!$A$24:$B$35, 2, FALSE)) -> #N/A | N66: =IFERROR(IF(NOT(ISBLANK(K66)), K66 / M66, IF(NOT(ISBLANK(L66)), L66, "")), "")
A67: Tarjeta ARG | B67: =IF(A67="", "", IFERROR(VLOOKUP(A67, Clasificaciones!A:B, 2, FALSE), "DATO NO CARGADO")) -> Tarjeta | C67: 02 feb | D67: 2025 | E67: Pagado | H67: ***TARJETAS VISA/ AMEX Febrero | J67: 45721 | K67: 86405 | M67: =IF(ISBLANK(K67), "", VLOOKUP(C67, 'Info Tipo de Cambio y REM'!$A$24:$B$35, 2, FALSE)) -> #N/A | N67: =IFERROR(IF(NOT(ISBLANK(K67)), K67 / M67, IF(NOT(ISBLANK(L67)), L67, "")), "")
A68: IIBB | B68: =IF(A68="", "", IFERROR(VLOOKUP(A68, Clasificaciones!A:B, 2, FALSE), "DATO NO CARGADO")) -> Impuestos ARG | C68: 02 feb | D68: 2025 | E68: Pagado | H68: INGRESOS BRUTOS Febrero | J68: 45734 | K68: 306411 | M68: =IF(ISBLANK(K68), "", VLOOKUP(C68, 'Info Tipo de Cambio y REM'!$A$24:$B$35, 2, FALSE)) -> #N/A | N68: =IFERROR(IF(NOT(ISBLANK(K68)), K68 / M68, IF(NOT(ISBLANK(L68)), L68, "")), "")
A69: IVA | B69: =IF(A69="", "", IFERROR(VLOOKUP(A69, Clasificaciones!A:B, 2, FALSE), "DATO NO CARGADO")) -> Impuestos ARG | C69: 02 feb | D69: 2025 | E69: Pagado | H69: IVA Febrero | J69: 45738 | K69: 1256673 | M69: =IF(ISBLANK(K69), "", VLOOKUP(C69, 'Info Tipo de Cambio y REM'!$A$24:$B$35, 2, FALSE)) -> #N/A | N69: =IFERROR(IF(NOT(ISBLANK(K69)), K69 / M69, IF(NOT(ISBLANK(L69)), L69, "")), "")
A70: Tomi Criado | B70: =IF(A70="", "", IFERROR(VLOOKUP(A70, Clasificaciones!A:B, 2, FALSE), "DATO NO CARGADO")) -> Board | C70: 02 feb | D70: 2025 | E70: Pagado | H70: HONORARIOS TOMAS Febrero | J70: 45721 | K70: 1263720 | M70: =IF(ISBLANK(K70), "", VLOOKUP(C70, 'Info Tipo de Cambio y REM'!$A$24:$B$35, 2, FALSE)) -> #N/A | N70: =IFERROR(IF(NOT(ISBLANK(K70)), K70 / M70, IF(NOT(ISBLANK(L70)), L70, "")), "")
A71: Honorarios Oxean | B71: =IF(A71="", "", IFERROR(VLOOKUP(A71, Clasificaciones!A:B, 2, FALSE), "DATO NO CARGADO")) -> Oxean | C71: 02 feb | D71: 2025 | E71: Pagado | H71: HONORARIOS OXEAN ADMINISTRACION Febrero | J71: 45721 | K71: 3418250 | M71: =IF(ISBLANK(K71), "", VLOOKUP(C71, 'Info Tipo de Cambio y REM'!$A$24:$B$35, 2, FALSE)) -> #N/A | N71: =IFERROR(IF(NOT(ISBLANK(K71)), K71 / M71, IF(NOT(ISBLANK(L71)), L71, "")), "")
A72: Tarjeta USA | B72: =IF(A72="", "", IFERROR(VLOOKUP(A72, Clasificaciones!A:B, 2, FALSE), "DATO NO CARGADO")) -> Tarjeta | C72: 02 feb | D72: 2025 | E72: Pagado | I72: DIGITALOCEAN.COM 02/28 PURCHASE 6468274366 NY DEBIT CARD *9122 | L72: 12 | M72: =IF(ISBLANK(K72), "", VLOOKUP(C72, 'Info Tipo de Cambio y REM'!$A$24:$B$35, 2, FALSE)) | N72: =IFERROR(IF(NOT(ISBLANK(K72)), K72 / M72, IF(NOT(ISBLANK(L72)), L72, "")), "") -> 12
A73: Tarjeta USA | B73: =IF(A73="", "", IFERROR(VLOOKUP(A73, Clasificaciones!A:B, 2, FALSE), "DATO NO CARGADO")) -> Tarjeta | C73: 02 feb | D73: 2025 | E73: Pagado | I73: GOOGLE*GSUITE EPI 03/01 PURCHASE 6502530000 CA DEBIT CARD *9122 | L73: 466 | M73: =IF(ISBLANK(K73), "", VLOOKUP(C73, 'Info Tipo de Cambio y REM'!$A$24:$B$35, 2, FALSE)) | N73: =IFERROR(IF(NOT(ISBLANK(K73)), K73 / M73, IF(NOT(ISBLANK(L73)), L73, "")), "") -> 466
A74: Tarjeta USA | B74: =IF(A74="", "", IFERROR(VLOOKUP(A74, Clasificaciones!A:B, 2, FALSE), "DATO NO CARGADO")) -> Tarjeta | C74: 02 feb | D74: 2025 | E74: Pagado | I74: Google ADS7881686 03/01 PURCHASE 6502530000 CA DEBIT CARD *9122 | L74: 304 | M74: =IF(ISBLANK(K74), "", VLOOKUP(C74, 'Info Tipo de Cambio y REM'!$A$24:$B$35, 2, FALSE)) | N74: =IFERROR(IF(NOT(ISBLANK(K74)), K74 / M74, IF(NOT(ISBLANK(L74)), L74, "")), "") -> 304
A75: Tarjeta USA | B75: =IF(A75="", "", IFERROR(VLOOKUP(A75, Clasificaciones!A:B, 2, FALSE), "DATO NO CARGADO")) -> Tarjeta | C75: 02 feb | D75: 2025 | E75: Pagado | I75: LinkedIn SN P2707 03/02 PURCHASE LINKEDIN.COM 00 DEBIT CARD *9122 | L75: 8 | M75: =IF(ISBLANK(K75), "", VLOOKUP(C75, 'Info Tipo de Cambio y REM'!$A$24:$B$35, 2, FALSE)) | N75: =IFERROR(IF(NOT(ISBLANK(K75)), K75 / M75, IF(NOT(ISBLANK(L75)), L75, "")), "") -> 8
A76: Tarjeta USA | B76: =IF(A76="", "", IFERROR(VLOOKUP(A76, Clasificaciones!A:B, 2, FALSE), "DATO NO CARGADO")) -> Tarjeta | C76: 02 feb | D76: 2025 | E76: Pagado | I76: APPLE.COM/BILL 03/02 PURCHASE 8667127753 CA DEBIT CARD *9122 | L76: 14.19 | M76: =IF(ISBLANK(K76), "", VLOOKUP(C76, 'Info Tipo de Cambio y REM'!$A$24:$B$35, 2, FALSE)) | N76: =IFERROR(IF(NOT(ISBLANK(K76)), K76 / M76, IF(NOT(ISBLANK(L76)), L76, "")), "") -> 14.19
A77: Tarjeta USA | B77: =IF(A77="", "", IFERROR(VLOOKUP(A77, Clasificaciones!A:B, 2, FALSE), "DATO NO CARGADO")) -> Tarjeta | C77: 02 feb | D77: 2025 | E77: Pagado | I77: ADOBE *ADOBE 03/03 PURCHASE 4085366000 CA DEBIT CARD *9122 | L77: 22.99 | M77: =IF(ISBLANK(K77), "", VLOOKUP(C77, 'Info Tipo de Cambio y REM'!$A$24:$B$35, 2, FALSE)) | N77: =IFERROR(IF(NOT(ISBLANK(K77)), K77 / M77, IF(NOT(ISBLANK(L77)), L77, "")), "") -> 22.99
A78: Tarjeta USA | B78: =IF(A78="", "", IFERROR(VLOOKUP(A78, Clasificaciones!A:B, 2, FALSE), "DATO NO CARGADO")) -> Tarjeta | C78: 02 feb | D78: 2025 | E78: Pagado | I78: REPLIT, INC. 03/04 PURCHASE 6282002281 CA DEBIT CARD *9122 | L78: 25 | M78: =IF(ISBLANK(K78), "", VLOOKUP(C78, 'Info Tipo de Cambio y REM'!$A$24:$B$35, 2, FALSE)) | N78: =IFERROR(IF(NOT(ISBLANK(K78)), K78 / M78, IF(NOT(ISBLANK(L78)), L78, "")), "") -> 25
A79: Tarjeta USA | B79: =IF(A79="", "", IFERROR(VLOOKUP(A79, Clasificaciones!A:B, 2, FALSE), "DATO NO CARGADO")) -> Tarjeta | C79: 02 feb | D79: 2025 | E79: Pagado | I79: OPENAI *CHATGPT S 03/06 PURCHASE 4158799686 CA DEBIT CARD *9122 | L79: 20 | M79: =IF(ISBLANK(K79), "", VLOOKUP(C79, 'Info Tipo de Cambio y REM'!$A$24:$B$35, 2, FALSE)) | N79: =IFERROR(IF(NOT(ISBLANK(K79)), K79 / M79, IF(NOT(ISBLANK(L79)), L79, "")), "") -> 20
A80: Tarjeta USA | B80: =IF(A80="", "", IFERROR(VLOOKUP(A80, Clasificaciones!A:B, 2, FALSE), "DATO NO CARGADO")) -> Tarjeta | C80: 02 feb | D80: 2025 | E80: Pagado | I80: CANVA* I04448- 03/07 PURCHASE CAMDEN DE DEBIT CARD *9122 | L80: 6.49 | M80: =IF(ISBLANK(K80), "", VLOOKUP(C80, 'Info Tipo de Cambio y REM'!$A$24:$B$35, 2, FALSE)) | N80: =IFERROR(IF(NOT(ISBLANK(K80)), K80 / M80, IF(NOT(ISBLANK(L80)), L80, "")), "") -> 6.49
